target/reference/docker-maven-plugin-0.36.1.jar target/docker-maven-plugin-0.36.1.jar
--- target/reference/docker-maven-plugin-0.36.1.jar
+++ target/docker-maven-plugin-0.36.1.jar
├── zipinfo {}
│ @@ -1,8 +1,8 @@
│ -Zip file size: 691009 bytes, number of entries: 431
│ +Zip file size: 691036 bytes, number of entries: 431
│  -rw-r--r--  2.0 unx       81 b- defN 20-Nov-14 11:57 META-INF/MANIFEST.MF
│  drwxr-xr-x  2.0 unx        0 b- stor 20-Nov-14 11:57 META-INF/
│  drwxr-xr-x  2.0 unx        0 b- stor 20-Nov-14 11:57 META-INF/doc/
│  drwxr-xr-x  2.0 unx        0 b- stor 20-Nov-14 11:57 META-INF/doc/dmp/
│  drwxr-xr-x  2.0 unx        0 b- stor 20-Nov-14 11:57 META-INF/doc/dmp/inc/
│  drwxr-xr-x  2.0 unx        0 b- stor 20-Nov-14 11:57 META-INF/doc/dmp/inc/build/
│  drwxr-xr-x  2.0 unx        0 b- stor 20-Nov-14 11:57 META-INF/doc/dmp/inc/external/
│ @@ -109,15 +109,15 @@
│  -rw-r--r--  2.0 unx     1602 b- defN 20-Nov-14 11:57 io/fabric8/maven/docker/AbstractDockerMojo$1.class
│  -rw-r--r--  2.0 unx     1494 b- defN 20-Nov-14 11:57 io/fabric8/maven/docker/AbstractDockerMojo$2.class
│  -rw-r--r--  2.0 unx    25576 b- defN 20-Nov-14 11:57 io/fabric8/maven/docker/AbstractDockerMojo.class
│  -rw-r--r--  2.0 unx    11215 b- defN 20-Nov-14 11:57 io/fabric8/maven/docker/BuildMojo.class
│  -rw-r--r--  2.0 unx     1385 b- defN 20-Nov-14 11:57 io/fabric8/maven/docker/CopyMojo$ContainerRemover.class
│  -rw-r--r--  2.0 unx     1170 b- defN 20-Nov-14 11:57 io/fabric8/maven/docker/CopyMojo$FileRemover.class
│  -rw-r--r--  2.0 unx    14387 b- defN 20-Nov-14 11:57 io/fabric8/maven/docker/CopyMojo.class
│ --rw-r--r--  2.0 unx    11082 b- defN 20-Nov-14 11:57 io/fabric8/maven/docker/HelpMojo.class
│ +-rw-r--r--  2.0 unx    11110 b- defN 20-Nov-14 11:57 io/fabric8/maven/docker/HelpMojo.class
│  -rw-r--r--  2.0 unx     3663 b- defN 20-Nov-14 11:57 io/fabric8/maven/docker/LogsMojo.class
│  -rw-r--r--  2.0 unx     3592 b- defN 20-Nov-14 11:57 io/fabric8/maven/docker/PushMojo.class
│  -rw-r--r--  2.0 unx     7732 b- defN 20-Nov-14 11:57 io/fabric8/maven/docker/RemoveMojo.class
│  -rw-r--r--  2.0 unx      841 b- defN 20-Nov-14 11:57 io/fabric8/maven/docker/RunMojo.class
│  -rw-r--r--  2.0 unx     9757 b- defN 20-Nov-14 11:57 io/fabric8/maven/docker/SaveMojo.class
│  -rw-r--r--  2.0 unx     5005 b- defN 20-Nov-14 11:57 io/fabric8/maven/docker/SourceMojo.class
│  -rw-r--r--  2.0 unx      223 b- defN 20-Nov-14 11:57 io/fabric8/maven/docker/StartMojo$1.class
│ @@ -426,8 +426,8 @@
│  -rw-r--r--  2.0 unx     2457 b- defN 20-Nov-14 11:57 io/fabric8/maven/docker/wait/TcpPortChecker.class
│  -rw-r--r--  2.0 unx      223 b- defN 20-Nov-14 11:57 io/fabric8/maven/docker/wait/WaitChecker.class
│  -rw-r--r--  2.0 unx      582 b- defN 20-Nov-14 11:57 io/fabric8/maven/docker/wait/WaitTimeoutException.class
│  -rw-r--r--  2.0 unx      273 b- defN 20-Nov-14 11:57 io/fabric8/maven/docker/wait/WaitUtil$Precondition.class
│  -rw-r--r--  2.0 unx     4608 b- defN 20-Nov-14 11:57 io/fabric8/maven/docker/wait/WaitUtil.class
│  -rw-r--r--  2.0 unx    20628 b- defN 20-Nov-14 11:57 META-INF/maven/io.fabric8/docker-maven-plugin/pom.xml
│  -rw-r--r--  2.0 unx       65 b- defN 20-Nov-14 11:57 META-INF/maven/io.fabric8/docker-maven-plugin/pom.properties
│ -431 files, 1900070 bytes uncompressed, 611849 bytes compressed:  67.8%
│ +431 files, 1900098 bytes uncompressed, 611876 bytes compressed:  67.8%
├── io/fabric8/maven/docker/HelpMojo.class
│ ├── javap -verbose -constants -s -l -private {}
│ │ @@ -1,495 +1,495 @@
│ │    Compiled from "HelpMojo.java"
│ │  public class io.fabric8.maven.docker.HelpMojo extends org.apache.maven.plugin.AbstractMojo
│ │    minor version: 0
│ │    major version: 52
│ │    flags: (0x0021) ACC_PUBLIC, ACC_SUPER
│ │ -  this_class: #3                          // io/fabric8/maven/docker/HelpMojo
│ │ -  super_class: #121                       // org/apache/maven/plugin/AbstractMojo
│ │ +  this_class: #2                          // io/fabric8/maven/docker/HelpMojo
│ │ +  super_class: #4                         // org/apache/maven/plugin/AbstractMojo
│ │    interfaces: 0, fields: 6, methods: 16, attributes: 2
│ │  Constant pool:
│ │ -    #1 = Methodref          #121.#265     // org/apache/maven/plugin/AbstractMojo."<init>":()V
│ │ -    #2 = Methodref          #3.#266       // io/fabric8/maven/docker/HelpMojo.getLog:()Lorg/apache/maven/plugin/logging/Log;
│ │ -    #3 = Class              #267          // io/fabric8/maven/docker/HelpMojo
│ │ -    #4 = String             #268          // load plugin-help.xml: /META-INF/maven/io.fabric8/docker-maven-plugin/plugin-help.xml
│ │ -    #5 = InterfaceMethodref #269.#270     // org/apache/maven/plugin/logging/Log.debug:(Ljava/lang/CharSequence;)V
│ │ -    #6 = Methodref          #271.#272     // java/lang/Object.getClass:()Ljava/lang/Class;
│ │ -    #7 = String             #273          // /META-INF/maven/io.fabric8/docker-maven-plugin/plugin-help.xml
│ │ -    #8 = Methodref          #274.#275     // java/lang/Class.getResourceAsStream:(Ljava/lang/String;)Ljava/io/InputStream;
│ │ -    #9 = Methodref          #161.#276     // javax/xml/parsers/DocumentBuilderFactory.newInstance:()Ljavax/xml/parsers/DocumentBuilderFactory;
│ │ -   #10 = Methodref          #161.#277     // javax/xml/parsers/DocumentBuilderFactory.newDocumentBuilder:()Ljavax/xml/parsers/DocumentBuilder;
│ │ -   #11 = Methodref          #162.#278     // javax/xml/parsers/DocumentBuilder.parse:(Ljava/io/InputStream;)Lorg/w3c/dom/Document;
│ │ -   #12 = Methodref          #160.#279     // java/io/InputStream.close:()V
│ │ -   #13 = Class              #280          // java/io/IOException
│ │ -   #14 = Class              #281          // org/apache/maven/plugin/MojoExecutionException
│ │ -   #15 = Methodref          #13.#282      // java/io/IOException.getMessage:()Ljava/lang/String;
│ │ -   #16 = Methodref          #14.#283      // org/apache/maven/plugin/MojoExecutionException."<init>":(Ljava/lang/String;Ljava/lang/Exception;)V
│ │ -   #17 = Class              #284          // javax/xml/parsers/ParserConfigurationException
│ │ -   #18 = Methodref          #17.#282      // javax/xml/parsers/ParserConfigurationException.getMessage:()Ljava/lang/String;
│ │ -   #19 = Class              #285          // org/xml/sax/SAXException
│ │ -   #20 = Methodref          #19.#282      // org/xml/sax/SAXException.getMessage:()Ljava/lang/String;
│ │ -   #21 = Fieldref           #3.#286       // io/fabric8/maven/docker/HelpMojo.lineLength:I
│ │ -   #22 = String             #287          // The parameter \'lineLength\' should be positive, using \'80\' as default.
│ │ -   #23 = InterfaceMethodref #269.#288     // org/apache/maven/plugin/logging/Log.warn:(Ljava/lang/CharSequence;)V
│ │ -   #24 = Fieldref           #3.#289       // io/fabric8/maven/docker/HelpMojo.indentSize:I
│ │ -   #25 = String             #290          // The parameter \'indentSize\' should be positive, using \'2\' as default.
│ │ -   #26 = Methodref          #3.#291       // io/fabric8/maven/docker/HelpMojo.build:()Lorg/w3c/dom/Document;
│ │ -   #27 = Class              #292          // java/lang/StringBuilder
│ │ -   #28 = Methodref          #27.#265      // java/lang/StringBuilder."<init>":()V
│ │ -   #29 = String             #173          // plugin
│ │ -   #30 = Methodref          #3.#293       // io/fabric8/maven/docker/HelpMojo.getSingleChild:(Lorg/w3c/dom/Node;Ljava/lang/String;)Lorg/w3c/dom/Node;
│ │ -   #31 = String             #174          // name
│ │ -   #32 = Methodref          #3.#294       // io/fabric8/maven/docker/HelpMojo.getValue:(Lorg/w3c/dom/Node;Ljava/lang/String;)Ljava/lang/String;
│ │ -   #33 = String             #175          // version
│ │ -   #34 = String             #295          // groupId
│ │ -   #35 = Methodref          #27.#296      // java/lang/StringBuilder.append:(Ljava/lang/String;)Ljava/lang/StringBuilder;
│ │ -   #36 = String             #297          // :
│ │ -   #37 = String             #298          // artifactId
│ │ -   #38 = Methodref          #27.#299      // java/lang/StringBuilder.toString:()Ljava/lang/String;
│ │ -   #39 = Methodref          #3.#300       // io/fabric8/maven/docker/HelpMojo.isNotEmpty:(Ljava/lang/String;)Z
│ │ -   #40 = Methodref          #103.#301     // java/lang/String.contains:(Ljava/lang/CharSequence;)Z
│ │ -   #41 = String             #302          //
│ │ -   #42 = Methodref          #3.#303       // io/fabric8/maven/docker/HelpMojo.append:(Ljava/lang/StringBuilder;Ljava/lang/String;I)V
│ │ -   #43 = String             #216          // description
│ │ -   #44 = String             #304          //
│ │ -   #45 = String             #177          // goalPrefix
│ │ -   #46 = String             #179          // mojos
│ │ -   #47 = String             #167          // mojo
│ │ -   #48 = Methodref          #3.#305       // io/fabric8/maven/docker/HelpMojo.findNamedChild:(Lorg/w3c/dom/Node;Ljava/lang/String;)Ljava/util/List;
│ │ -   #49 = Fieldref           #3.#306       // io/fabric8/maven/docker/HelpMojo.goal:Ljava/lang/String;
│ │ -   #50 = Methodref          #103.#307     // java/lang/String.length:()I
│ │ -   #51 = String             #308          // This plugin has
│ │ -   #52 = InterfaceMethodref #183.#309     // java/util/List.size:()I
│ │ -   #53 = Methodref          #27.#310      // java/lang/StringBuilder.append:(I)Ljava/lang/StringBuilder;
│ │ -   #54 = String             #311          //  goals:
│ │ -   #55 = String             #312          //  goal:
│ │ -   #56 = InterfaceMethodref #183.#313     // java/util/List.iterator:()Ljava/util/Iterator;
│ │ -   #57 = InterfaceMethodref #184.#314     // java/util/Iterator.hasNext:()Z
│ │ -   #58 = InterfaceMethodref #184.#315     // java/util/Iterator.next:()Ljava/lang/Object;
│ │ -   #59 = Class              #316          // org/w3c/dom/Node
│ │ -   #60 = Class              #317          // org/w3c/dom/Element
│ │ -   #61 = Methodref          #3.#318       // io/fabric8/maven/docker/HelpMojo.writeGoal:(Ljava/lang/StringBuilder;Ljava/lang/String;Lorg/w3c/dom/Element;)V
│ │ -   #62 = InterfaceMethodref #269.#319     // org/apache/maven/plugin/logging/Log.isInfoEnabled:()Z
│ │ -   #63 = InterfaceMethodref #269.#320     // org/apache/maven/plugin/logging/Log.info:(Ljava/lang/CharSequence;)V
│ │ -   #64 = InterfaceMethodref #59.#321      // org/w3c/dom/Node.getTextContent:()Ljava/lang/String;
│ │ -   #65 = InterfaceMethodref #183.#322     // java/util/List.isEmpty:()Z
│ │ -   #66 = String             #323          // Could not find
│ │ -   #67 = String             #324          //  in plugin-help.xml
│ │ -   #68 = Methodref          #14.#325      // org/apache/maven/plugin/MojoExecutionException."<init>":(Ljava/lang/String;)V
│ │ -   #69 = String             #326          // Multiple
│ │ -   #70 = InterfaceMethodref #183.#327     // java/util/List.get:(I)Ljava/lang/Object;
│ │ -   #71 = Class              #328          // java/util/ArrayList
│ │ -   #72 = Methodref          #71.#265      // java/util/ArrayList."<init>":()V
│ │ -   #73 = InterfaceMethodref #59.#329      // org/w3c/dom/Node.getChildNodes:()Lorg/w3c/dom/NodeList;
│ │ -   #74 = InterfaceMethodref #202.#330     // org/w3c/dom/NodeList.getLength:()I
│ │ -   #75 = InterfaceMethodref #202.#331     // org/w3c/dom/NodeList.item:(I)Lorg/w3c/dom/Node;
│ │ -   #76 = InterfaceMethodref #59.#332      // org/w3c/dom/Node.getNodeName:()Ljava/lang/String;
│ │ -   #77 = Methodref          #103.#333     // java/lang/String.equals:(Ljava/lang/Object;)Z
│ │ -   #78 = InterfaceMethodref #183.#334     // java/util/List.add:(Ljava/lang/Object;)Z
│ │ -   #79 = String             #335          // in plugin-help.xml
│ │ -   #80 = String             #129          // goal
│ │ -   #81 = String             #336          // configuration
│ │ -   #82 = Methodref          #3.#337       // io/fabric8/maven/docker/HelpMojo.findSingleChild:(Lorg/w3c/dom/Node;Ljava/lang/String;)Lorg/w3c/dom/Node;
│ │ -   #83 = String             #212          // deprecated
│ │ -   #84 = String             #338          // Deprecated.
│ │ -   #85 = Fieldref           #3.#339       // io/fabric8/maven/docker/HelpMojo.detail:Z
│ │ -   #86 = String             #211          // parameters
│ │ -   #87 = String             #209          // parameter
│ │ -   #88 = String             #340          // Available parameters:
│ │ -   #89 = Methodref          #3.#341       // io/fabric8/maven/docker/HelpMojo.writeParameter:(Ljava/lang/StringBuilder;Lorg/w3c/dom/Node;Lorg/w3c/dom/Node;)V
│ │ -   #90 = String             #342          // default-value
│ │ -   #91 = InterfaceMethodref #60.#343      // org/w3c/dom/Element.hasAttribute:(Ljava/lang/String;)Z
│ │ -   #92 = String             #344          //  (Default:
│ │ -   #93 = InterfaceMethodref #60.#345      // org/w3c/dom/Element.getAttribute:(Ljava/lang/String;)Ljava/lang/String;
│ │ -   #94 = String             #346          // )
│ │ -   #95 = String             #347          // true
│ │ -   #96 = String             #348          // required
│ │ -   #97 = String             #349          // Required: Yes
│ │ -   #98 = InterfaceMethodref #60.#321      // org/w3c/dom/Element.getTextContent:()Ljava/lang/String;
│ │ -   #99 = Methodref          #3.#350       // io/fabric8/maven/docker/HelpMojo.getPropertyFromExpression:(Ljava/lang/String;)Ljava/lang/String;
│ │ -  #100 = String             #351          // User property:
│ │ -  #101 = Methodref          #27.#352      // java/lang/StringBuilder."<init>":(I)V
│ │ -  #102 = Methodref          #3.#353       // io/fabric8/maven/docker/HelpMojo.toLines:(Ljava/lang/String;III)Ljava/util/List;
│ │ -  #103 = Class              #354          // java/lang/String
│ │ -  #104 = Methodref          #27.#355      // java/lang/StringBuilder.append:(C)Ljava/lang/StringBuilder;
│ │ -  #105 = String             #356          // \t
│ │ -  #106 = Methodref          #3.#357       // io/fabric8/maven/docker/HelpMojo.repeat:(Ljava/lang/String;I)Ljava/lang/String;
│ │ -  #107 = String             #358          // (\r\n)|(\r)|(\n)
│ │ -  #108 = Methodref          #103.#359     // java/lang/String.split:(Ljava/lang/String;)[Ljava/lang/String;
│ │ -  #109 = Methodref          #3.#360       // io/fabric8/maven/docker/HelpMojo.toLines:(Ljava/util/List;Ljava/lang/String;II)V
│ │ -  #110 = Methodref          #3.#361       // io/fabric8/maven/docker/HelpMojo.getIndentLevel:(Ljava/lang/String;)I
│ │ -  #111 = String             #362          //  +
│ │ -  #112 = Methodref          #27.#307      // java/lang/StringBuilder.length:()I
│ │ -  #113 = Methodref          #27.#363      // java/lang/StringBuilder.setLength:(I)V
│ │ -  #114 = Methodref          #103.#364     // java/lang/String.charAt:(I)C
│ │ -  #115 = String             #365          // ${
│ │ -  #116 = Methodref          #103.#366     // java/lang/String.startsWith:(Ljava/lang/String;)Z
│ │ -  #117 = String             #367          // }
│ │ -  #118 = Methodref          #103.#368     // java/lang/String.endsWith:(Ljava/lang/String;)Z
│ │ -  #119 = Methodref          #103.#369     // java/lang/String.substring:(I)Ljava/lang/String;
│ │ -  #120 = Methodref          #103.#370     // java/lang/String.substring:(II)Ljava/lang/String;
│ │ -  #121 = Class              #371          // org/apache/maven/plugin/AbstractMojo
│ │ -  #122 = Utf8               detail
│ │ -  #123 = Utf8               Z
│ │ -  #124 = Utf8               RuntimeInvisibleAnnotations
│ │ -  #125 = Utf8               Lorg/apache/maven/plugins/annotations/Parameter;
│ │ -  #126 = Utf8               property
│ │ -  #127 = Utf8               defaultValue
│ │ -  #128 = Utf8               false
│ │ -  #129 = Utf8               goal
│ │ -  #130 = Utf8               Ljava/lang/String;
│ │ -  #131 = Utf8               lineLength
│ │ -  #132 = Utf8               I
│ │ -  #133 = Utf8               80
│ │ -  #134 = Utf8               indentSize
│ │ -  #135 = Utf8               2
│ │ -  #136 = Utf8               PLUGIN_HELP_PATH
│ │ -  #137 = Utf8               ConstantValue
│ │ -  #138 = Utf8               DEFAULT_LINE_LENGTH
│ │ -  #139 = Integer            80
│ │ -  #140 = Utf8               <init>
│ │ -  #141 = Utf8               ()V
│ │ -  #142 = Utf8               Code
│ │ -  #143 = Utf8               LineNumberTable
│ │ -  #144 = Utf8               LocalVariableTable
│ │ -  #145 = Utf8               this
│ │ -  #146 = Utf8               Lio/fabric8/maven/docker/HelpMojo;
│ │ -  #147 = Utf8               build
│ │ -  #148 = Utf8               ()Lorg/w3c/dom/Document;
│ │ -  #149 = Utf8               e
│ │ -  #150 = Utf8               Ljava/io/IOException;
│ │ -  #151 = Utf8               dbFactory
│ │ -  #152 = Utf8               Ljavax/xml/parsers/DocumentBuilderFactory;
│ │ -  #153 = Utf8               dBuilder
│ │ -  #154 = Utf8               Ljavax/xml/parsers/DocumentBuilder;
│ │ -  #155 = Utf8               Ljavax/xml/parsers/ParserConfigurationException;
│ │ -  #156 = Utf8               Lorg/xml/sax/SAXException;
│ │ -  #157 = Utf8               is
│ │ -  #158 = Utf8               Ljava/io/InputStream;
│ │ -  #159 = Utf8               StackMapTable
│ │ -  #160 = Class              #372          // java/io/InputStream
│ │ -  #161 = Class              #373          // javax/xml/parsers/DocumentBuilderFactory
│ │ -  #162 = Class              #374          // javax/xml/parsers/DocumentBuilder
│ │ -  #163 = Class              #375          // org/w3c/dom/Document
│ │ -  #164 = Class              #376          // java/lang/Throwable
│ │ -  #165 = Utf8               Exceptions
│ │ -  #166 = Utf8               execute
│ │ -  #167 = Utf8               mojo
│ │ -  #168 = Utf8               Lorg/w3c/dom/Node;
│ │ -  #169 = Utf8               doc
│ │ -  #170 = Utf8               Lorg/w3c/dom/Document;
│ │ -  #171 = Utf8               sb
│ │ -  #172 = Utf8               Ljava/lang/StringBuilder;
│ │ -  #173 = Utf8               plugin
│ │ -  #174 = Utf8               name
│ │ -  #175 = Utf8               version
│ │ -  #176 = Utf8               id
│ │ -  #177 = Utf8               goalPrefix
│ │ -  #178 = Utf8               mojos1
│ │ -  #179 = Utf8               mojos
│ │ -  #180 = Utf8               Ljava/util/List;
│ │ -  #181 = Utf8               LocalVariableTypeTable
│ │ -  #182 = Utf8               Ljava/util/List<Lorg/w3c/dom/Node;>;
│ │ -  #183 = Class              #377          // java/util/List
│ │ -  #184 = Class              #378          // java/util/Iterator
│ │ -  #185 = Utf8               isNotEmpty
│ │ -  #186 = Utf8               (Ljava/lang/String;)Z
│ │ -  #187 = Utf8               string
│ │ -  #188 = Utf8               getValue
│ │ -  #189 = Utf8               (Lorg/w3c/dom/Node;Ljava/lang/String;)Ljava/lang/String;
│ │ -  #190 = Utf8               node
│ │ -  #191 = Utf8               elementName
│ │ -  #192 = Utf8               getSingleChild
│ │ -  #193 = Utf8               (Lorg/w3c/dom/Node;Ljava/lang/String;)Lorg/w3c/dom/Node;
│ │ -  #194 = Utf8               namedChild
│ │ -  #195 = Utf8               findNamedChild
│ │ -  #196 = Utf8               (Lorg/w3c/dom/Node;Ljava/lang/String;)Ljava/util/List;
│ │ -  #197 = Utf8               item
│ │ -  #198 = Utf8               i
│ │ -  #199 = Utf8               result
│ │ -  #200 = Utf8               childNodes
│ │ -  #201 = Utf8               Lorg/w3c/dom/NodeList;
│ │ -  #202 = Class              #379          // org/w3c/dom/NodeList
│ │ -  #203 = Utf8               Signature
│ │ -  #204 = Utf8               (Lorg/w3c/dom/Node;Ljava/lang/String;)Ljava/util/List<Lorg/w3c/dom/Node;>;
│ │ -  #205 = Utf8               findSingleChild
│ │ -  #206 = Utf8               elementsByTagName
│ │ -  #207 = Utf8               writeGoal
│ │ -  #208 = Utf8               (Ljava/lang/StringBuilder;Ljava/lang/String;Lorg/w3c/dom/Element;)V
│ │ -  #209 = Utf8               parameter
│ │ -  #210 = Utf8               parametersNode
│ │ -  #211 = Utf8               parameters
│ │ -  #212 = Utf8               deprecated
│ │ -  #213 = Utf8               Lorg/w3c/dom/Element;
│ │ -  #214 = Utf8               mojoGoal
│ │ -  #215 = Utf8               configurationElement
│ │ -  #216 = Utf8               description
│ │ -  #217 = Utf8               writeParameter
│ │ -  #218 = Utf8               (Ljava/lang/StringBuilder;Lorg/w3c/dom/Node;Lorg/w3c/dom/Node;)V
│ │ -  #219 = Utf8               parameterName
│ │ -  #220 = Utf8               parameterDescription
│ │ -  #221 = Utf8               fieldConfigurationElement
│ │ -  #222 = Utf8               parameterDefaultValue
│ │ -  #223 = Utf8               repeat
│ │ -  #224 = Utf8               (Ljava/lang/String;I)Ljava/lang/String;
│ │ -  #225 = Utf8               str
│ │ -  #226 = Utf8               buffer
│ │ -  #227 = Utf8               append
│ │ -  #228 = Utf8               (Ljava/lang/StringBuilder;Ljava/lang/String;I)V
│ │ -  #229 = Utf8               line
│ │ -  #230 = Utf8               indent
│ │ -  #231 = Utf8               toLines
│ │ -  #232 = Utf8               (Ljava/lang/String;III)Ljava/util/List;
│ │ -  #233 = Utf8               plainLine
│ │ -  #234 = Utf8               text
│ │ -  #235 = Utf8               lines
│ │ -  #236 = Utf8               ind
│ │ -  #237 = Utf8               plainLines
│ │ -  #238 = Utf8               [Ljava/lang/String;
│ │ -  #239 = Utf8               Ljava/util/List<Ljava/lang/String;>;
│ │ -  #240 = Class              #238          // "[Ljava/lang/String;"
│ │ -  #241 = Utf8               (Ljava/lang/String;III)Ljava/util/List<Ljava/lang/String;>;
│ │ -  #242 = Utf8               (Ljava/util/List;Ljava/lang/String;II)V
│ │ -  #243 = Utf8               c
│ │ -  #244 = Utf8               C
│ │ -  #245 = Utf8               j
│ │ -  #246 = Utf8               token
│ │ -  #247 = Utf8               lineIndent
│ │ -  #248 = Utf8               buf
│ │ -  #249 = Utf8               tokens
│ │ -  #250 = Utf8               (Ljava/util/List<Ljava/lang/String;>;Ljava/lang/String;II)V
│ │ -  #251 = Utf8               getIndentLevel
│ │ -  #252 = Utf8               (Ljava/lang/String;)I
│ │ -  #253 = Utf8               level
│ │ -  #254 = Utf8               getPropertyFromExpression
│ │ -  #255 = Utf8               (Ljava/lang/String;)Ljava/lang/String;
│ │ -  #256 = Utf8               expression
│ │ -  #257 = Utf8               SourceFile
│ │ -  #258 = Utf8               HelpMojo.java
│ │ -  #259 = Utf8               Lorg/apache/maven/plugins/annotations/Mojo;
│ │ -  #260 = Utf8               help
│ │ -  #261 = Utf8               requiresProject
│ │ -  #262 = Integer            0
│ │ -  #263 = Utf8               threadSafe
│ │ -  #264 = Integer            1
│ │ -  #265 = NameAndType        #140:#141     // "<init>":()V
│ │ -  #266 = NameAndType        #380:#381     // getLog:()Lorg/apache/maven/plugin/logging/Log;
│ │ -  #267 = Utf8               io/fabric8/maven/docker/HelpMojo
│ │ -  #268 = Utf8               load plugin-help.xml: /META-INF/maven/io.fabric8/docker-maven-plugin/plugin-help.xml
│ │ -  #269 = Class              #382          // org/apache/maven/plugin/logging/Log
│ │ -  #270 = NameAndType        #383:#384     // debug:(Ljava/lang/CharSequence;)V
│ │ -  #271 = Class              #385          // java/lang/Object
│ │ -  #272 = NameAndType        #386:#387     // getClass:()Ljava/lang/Class;
│ │ -  #273 = Utf8               /META-INF/maven/io.fabric8/docker-maven-plugin/plugin-help.xml
│ │ -  #274 = Class              #388          // java/lang/Class
│ │ -  #275 = NameAndType        #389:#390     // getResourceAsStream:(Ljava/lang/String;)Ljava/io/InputStream;
│ │ -  #276 = NameAndType        #391:#392     // newInstance:()Ljavax/xml/parsers/DocumentBuilderFactory;
│ │ -  #277 = NameAndType        #393:#394     // newDocumentBuilder:()Ljavax/xml/parsers/DocumentBuilder;
│ │ -  #278 = NameAndType        #395:#396     // parse:(Ljava/io/InputStream;)Lorg/w3c/dom/Document;
│ │ -  #279 = NameAndType        #397:#141     // close:()V
│ │ -  #280 = Utf8               java/io/IOException
│ │ -  #281 = Utf8               org/apache/maven/plugin/MojoExecutionException
│ │ -  #282 = NameAndType        #398:#399     // getMessage:()Ljava/lang/String;
│ │ -  #283 = NameAndType        #140:#400     // "<init>":(Ljava/lang/String;Ljava/lang/Exception;)V
│ │ -  #284 = Utf8               javax/xml/parsers/ParserConfigurationException
│ │ -  #285 = Utf8               org/xml/sax/SAXException
│ │ -  #286 = NameAndType        #131:#132     // lineLength:I
│ │ -  #287 = Utf8               The parameter \'lineLength\' should be positive, using \'80\' as default.
│ │ -  #288 = NameAndType        #401:#384     // warn:(Ljava/lang/CharSequence;)V
│ │ -  #289 = NameAndType        #134:#132     // indentSize:I
│ │ -  #290 = Utf8               The parameter \'indentSize\' should be positive, using \'2\' as default.
│ │ -  #291 = NameAndType        #147:#148     // build:()Lorg/w3c/dom/Document;
│ │ -  #292 = Utf8               java/lang/StringBuilder
│ │ -  #293 = NameAndType        #192:#193     // getSingleChild:(Lorg/w3c/dom/Node;Ljava/lang/String;)Lorg/w3c/dom/Node;
│ │ -  #294 = NameAndType        #188:#189     // getValue:(Lorg/w3c/dom/Node;Ljava/lang/String;)Ljava/lang/String;
│ │ -  #295 = Utf8               groupId
│ │ -  #296 = NameAndType        #227:#402     // append:(Ljava/lang/String;)Ljava/lang/StringBuilder;
│ │ -  #297 = Utf8               :
│ │ -  #298 = Utf8               artifactId
│ │ -  #299 = NameAndType        #403:#399     // toString:()Ljava/lang/String;
│ │ -  #300 = NameAndType        #185:#186     // isNotEmpty:(Ljava/lang/String;)Z
│ │ -  #301 = NameAndType        #404:#405     // contains:(Ljava/lang/CharSequence;)Z
│ │ -  #302 = Utf8
│ │ -  #303 = NameAndType        #227:#228     // append:(Ljava/lang/StringBuilder;Ljava/lang/String;I)V
│ │ -  #304 = Utf8
│ │ -  #305 = NameAndType        #195:#196     // findNamedChild:(Lorg/w3c/dom/Node;Ljava/lang/String;)Ljava/util/List;
│ │ -  #306 = NameAndType        #129:#130     // goal:Ljava/lang/String;
│ │ -  #307 = NameAndType        #406:#407     // length:()I
│ │ -  #308 = Utf8               This plugin has
│ │ -  #309 = NameAndType        #408:#407     // size:()I
│ │ -  #310 = NameAndType        #227:#409     // append:(I)Ljava/lang/StringBuilder;
│ │ -  #311 = Utf8                goals:
│ │ -  #312 = Utf8                goal:
│ │ -  #313 = NameAndType        #410:#411     // iterator:()Ljava/util/Iterator;
│ │ -  #314 = NameAndType        #412:#413     // hasNext:()Z
│ │ -  #315 = NameAndType        #414:#415     // next:()Ljava/lang/Object;
│ │ -  #316 = Utf8               org/w3c/dom/Node
│ │ -  #317 = Utf8               org/w3c/dom/Element
│ │ -  #318 = NameAndType        #207:#208     // writeGoal:(Ljava/lang/StringBuilder;Ljava/lang/String;Lorg/w3c/dom/Element;)V
│ │ -  #319 = NameAndType        #416:#413     // isInfoEnabled:()Z
│ │ -  #320 = NameAndType        #417:#384     // info:(Ljava/lang/CharSequence;)V
│ │ -  #321 = NameAndType        #418:#399     // getTextContent:()Ljava/lang/String;
│ │ -  #322 = NameAndType        #419:#413     // isEmpty:()Z
│ │ -  #323 = Utf8               Could not find
│ │ -  #324 = Utf8                in plugin-help.xml
│ │ -  #325 = NameAndType        #140:#420     // "<init>":(Ljava/lang/String;)V
│ │ -  #326 = Utf8               Multiple
│ │ -  #327 = NameAndType        #421:#422     // get:(I)Ljava/lang/Object;
│ │ -  #328 = Utf8               java/util/ArrayList
│ │ -  #329 = NameAndType        #423:#424     // getChildNodes:()Lorg/w3c/dom/NodeList;
│ │ -  #330 = NameAndType        #425:#407     // getLength:()I
│ │ -  #331 = NameAndType        #197:#426     // item:(I)Lorg/w3c/dom/Node;
│ │ -  #332 = NameAndType        #427:#399     // getNodeName:()Ljava/lang/String;
│ │ -  #333 = NameAndType        #428:#429     // equals:(Ljava/lang/Object;)Z
│ │ -  #334 = NameAndType        #430:#429     // add:(Ljava/lang/Object;)Z
│ │ -  #335 = Utf8               in plugin-help.xml
│ │ -  #336 = Utf8               configuration
│ │ -  #337 = NameAndType        #205:#193     // findSingleChild:(Lorg/w3c/dom/Node;Ljava/lang/String;)Lorg/w3c/dom/Node;
│ │ -  #338 = Utf8               Deprecated.
│ │ -  #339 = NameAndType        #122:#123     // detail:Z
│ │ -  #340 = Utf8               Available parameters:
│ │ -  #341 = NameAndType        #217:#218     // writeParameter:(Ljava/lang/StringBuilder;Lorg/w3c/dom/Node;Lorg/w3c/dom/Node;)V
│ │ -  #342 = Utf8               default-value
│ │ -  #343 = NameAndType        #431:#186     // hasAttribute:(Ljava/lang/String;)Z
│ │ -  #344 = Utf8                (Default:
│ │ -  #345 = NameAndType        #432:#255     // getAttribute:(Ljava/lang/String;)Ljava/lang/String;
│ │ -  #346 = Utf8               )
│ │ -  #347 = Utf8               true
│ │ -  #348 = Utf8               required
│ │ -  #349 = Utf8               Required: Yes
│ │ -  #350 = NameAndType        #254:#255     // getPropertyFromExpression:(Ljava/lang/String;)Ljava/lang/String;
│ │ -  #351 = Utf8               User property:
│ │ -  #352 = NameAndType        #140:#433     // "<init>":(I)V
│ │ -  #353 = NameAndType        #231:#232     // toLines:(Ljava/lang/String;III)Ljava/util/List;
│ │ -  #354 = Utf8               java/lang/String
│ │ -  #355 = NameAndType        #227:#434     // append:(C)Ljava/lang/StringBuilder;
│ │ -  #356 = Utf8               \t
│ │ -  #357 = NameAndType        #223:#224     // repeat:(Ljava/lang/String;I)Ljava/lang/String;
│ │ -  #358 = Utf8               (\r\n)|(\r)|(\n)
│ │ -  #359 = NameAndType        #435:#436     // split:(Ljava/lang/String;)[Ljava/lang/String;
│ │ -  #360 = NameAndType        #231:#242     // toLines:(Ljava/util/List;Ljava/lang/String;II)V
│ │ -  #361 = NameAndType        #251:#252     // getIndentLevel:(Ljava/lang/String;)I
│ │ -  #362 = Utf8                +
│ │ -  #363 = NameAndType        #437:#433     // setLength:(I)V
│ │ -  #364 = NameAndType        #438:#439     // charAt:(I)C
│ │ -  #365 = Utf8               ${
│ │ -  #366 = NameAndType        #440:#186     // startsWith:(Ljava/lang/String;)Z
│ │ -  #367 = Utf8               }
│ │ -  #368 = NameAndType        #441:#186     // endsWith:(Ljava/lang/String;)Z
│ │ -  #369 = NameAndType        #442:#443     // substring:(I)Ljava/lang/String;
│ │ -  #370 = NameAndType        #442:#444     // substring:(II)Ljava/lang/String;
│ │ -  #371 = Utf8               org/apache/maven/plugin/AbstractMojo
│ │ -  #372 = Utf8               java/io/InputStream
│ │ -  #373 = Utf8               javax/xml/parsers/DocumentBuilderFactory
│ │ -  #374 = Utf8               javax/xml/parsers/DocumentBuilder
│ │ -  #375 = Utf8               org/w3c/dom/Document
│ │ -  #376 = Utf8               java/lang/Throwable
│ │ -  #377 = Utf8               java/util/List
│ │ -  #378 = Utf8               java/util/Iterator
│ │ -  #379 = Utf8               org/w3c/dom/NodeList
│ │ -  #380 = Utf8               getLog
│ │ -  #381 = Utf8               ()Lorg/apache/maven/plugin/logging/Log;
│ │ -  #382 = Utf8               org/apache/maven/plugin/logging/Log
│ │ -  #383 = Utf8               debug
│ │ -  #384 = Utf8               (Ljava/lang/CharSequence;)V
│ │ -  #385 = Utf8               java/lang/Object
│ │ -  #386 = Utf8               getClass
│ │ -  #387 = Utf8               ()Ljava/lang/Class;
│ │ -  #388 = Utf8               java/lang/Class
│ │ -  #389 = Utf8               getResourceAsStream
│ │ -  #390 = Utf8               (Ljava/lang/String;)Ljava/io/InputStream;
│ │ -  #391 = Utf8               newInstance
│ │ -  #392 = Utf8               ()Ljavax/xml/parsers/DocumentBuilderFactory;
│ │ -  #393 = Utf8               newDocumentBuilder
│ │ -  #394 = Utf8               ()Ljavax/xml/parsers/DocumentBuilder;
│ │ -  #395 = Utf8               parse
│ │ -  #396 = Utf8               (Ljava/io/InputStream;)Lorg/w3c/dom/Document;
│ │ -  #397 = Utf8               close
│ │ -  #398 = Utf8               getMessage
│ │ -  #399 = Utf8               ()Ljava/lang/String;
│ │ -  #400 = Utf8               (Ljava/lang/String;Ljava/lang/Exception;)V
│ │ -  #401 = Utf8               warn
│ │ -  #402 = Utf8               (Ljava/lang/String;)Ljava/lang/StringBuilder;
│ │ -  #403 = Utf8               toString
│ │ -  #404 = Utf8               contains
│ │ -  #405 = Utf8               (Ljava/lang/CharSequence;)Z
│ │ -  #406 = Utf8               length
│ │ -  #407 = Utf8               ()I
│ │ -  #408 = Utf8               size
│ │ -  #409 = Utf8               (I)Ljava/lang/StringBuilder;
│ │ -  #410 = Utf8               iterator
│ │ -  #411 = Utf8               ()Ljava/util/Iterator;
│ │ -  #412 = Utf8               hasNext
│ │ -  #413 = Utf8               ()Z
│ │ -  #414 = Utf8               next
│ │ -  #415 = Utf8               ()Ljava/lang/Object;
│ │ -  #416 = Utf8               isInfoEnabled
│ │ -  #417 = Utf8               info
│ │ -  #418 = Utf8               getTextContent
│ │ -  #419 = Utf8               isEmpty
│ │ -  #420 = Utf8               (Ljava/lang/String;)V
│ │ -  #421 = Utf8               get
│ │ -  #422 = Utf8               (I)Ljava/lang/Object;
│ │ -  #423 = Utf8               getChildNodes
│ │ -  #424 = Utf8               ()Lorg/w3c/dom/NodeList;
│ │ -  #425 = Utf8               getLength
│ │ -  #426 = Utf8               (I)Lorg/w3c/dom/Node;
│ │ -  #427 = Utf8               getNodeName
│ │ -  #428 = Utf8               equals
│ │ -  #429 = Utf8               (Ljava/lang/Object;)Z
│ │ -  #430 = Utf8               add
│ │ -  #431 = Utf8               hasAttribute
│ │ -  #432 = Utf8               getAttribute
│ │ -  #433 = Utf8               (I)V
│ │ -  #434 = Utf8               (C)Ljava/lang/StringBuilder;
│ │ -  #435 = Utf8               split
│ │ -  #436 = Utf8               (Ljava/lang/String;)[Ljava/lang/String;
│ │ -  #437 = Utf8               setLength
│ │ -  #438 = Utf8               charAt
│ │ -  #439 = Utf8               (I)C
│ │ -  #440 = Utf8               startsWith
│ │ -  #441 = Utf8               endsWith
│ │ -  #442 = Utf8               substring
│ │ -  #443 = Utf8               (I)Ljava/lang/String;
│ │ -  #444 = Utf8               (II)Ljava/lang/String;
│ │ +    #1 = Utf8               io/fabric8/maven/docker/HelpMojo
│ │ +    #2 = Class              #1            // io/fabric8/maven/docker/HelpMojo
│ │ +    #3 = Utf8               org/apache/maven/plugin/AbstractMojo
│ │ +    #4 = Class              #3            // org/apache/maven/plugin/AbstractMojo
│ │ +    #5 = Utf8               HelpMojo.java
│ │ +    #6 = Utf8               Lorg/apache/maven/plugins/annotations/Mojo;
│ │ +    #7 = Utf8               name
│ │ +    #8 = Utf8               help
│ │ +    #9 = Utf8               requiresProject
│ │ +   #10 = Integer            0
│ │ +   #11 = Utf8               threadSafe
│ │ +   #12 = Integer            1
│ │ +   #13 = Utf8               detail
│ │ +   #14 = Utf8               Z
│ │ +   #15 = Utf8               Lorg/apache/maven/plugins/annotations/Parameter;
│ │ +   #16 = Utf8               property
│ │ +   #17 = Utf8               defaultValue
│ │ +   #18 = Utf8               false
│ │ +   #19 = Utf8               goal
│ │ +   #20 = Utf8               Ljava/lang/String;
│ │ +   #21 = Utf8               lineLength
│ │ +   #22 = Utf8               I
│ │ +   #23 = Utf8               80
│ │ +   #24 = Utf8               indentSize
│ │ +   #25 = Utf8               2
│ │ +   #26 = Utf8               PLUGIN_HELP_PATH
│ │ +   #27 = Utf8               /META-INF/maven/io.fabric8/docker-maven-plugin/plugin-help.xml
│ │ +   #28 = String             #27           // /META-INF/maven/io.fabric8/docker-maven-plugin/plugin-help.xml
│ │ +   #29 = Utf8               DEFAULT_LINE_LENGTH
│ │ +   #30 = Integer            80
│ │ +   #31 = Utf8               <init>
│ │ +   #32 = Utf8               ()V
│ │ +   #33 = NameAndType        #31:#32       // "<init>":()V
│ │ +   #34 = Methodref          #4.#33        // org/apache/maven/plugin/AbstractMojo."<init>":()V
│ │ +   #35 = Utf8               this
│ │ +   #36 = Utf8               Lio/fabric8/maven/docker/HelpMojo;
│ │ +   #37 = Utf8               build
│ │ +   #38 = Utf8               ()Lorg/w3c/dom/Document;
│ │ +   #39 = Utf8               org/apache/maven/plugin/MojoExecutionException
│ │ +   #40 = Class              #39           // org/apache/maven/plugin/MojoExecutionException
│ │ +   #41 = Utf8               java/io/IOException
│ │ +   #42 = Class              #41           // java/io/IOException
│ │ +   #43 = Utf8               javax/xml/parsers/ParserConfigurationException
│ │ +   #44 = Class              #43           // javax/xml/parsers/ParserConfigurationException
│ │ +   #45 = Utf8               org/xml/sax/SAXException
│ │ +   #46 = Class              #45           // org/xml/sax/SAXException
│ │ +   #47 = Utf8               getLog
│ │ +   #48 = Utf8               ()Lorg/apache/maven/plugin/logging/Log;
│ │ +   #49 = NameAndType        #47:#48       // getLog:()Lorg/apache/maven/plugin/logging/Log;
│ │ +   #50 = Methodref          #2.#49        // io/fabric8/maven/docker/HelpMojo.getLog:()Lorg/apache/maven/plugin/logging/Log;
│ │ +   #51 = Utf8               load plugin-help.xml: /META-INF/maven/io.fabric8/docker-maven-plugin/plugin-help.xml
│ │ +   #52 = String             #51           // load plugin-help.xml: /META-INF/maven/io.fabric8/docker-maven-plugin/plugin-help.xml
│ │ +   #53 = Utf8               org/apache/maven/plugin/logging/Log
│ │ +   #54 = Class              #53           // org/apache/maven/plugin/logging/Log
│ │ +   #55 = Utf8               debug
│ │ +   #56 = Utf8               (Ljava/lang/CharSequence;)V
│ │ +   #57 = NameAndType        #55:#56       // debug:(Ljava/lang/CharSequence;)V
│ │ +   #58 = InterfaceMethodref #54.#57       // org/apache/maven/plugin/logging/Log.debug:(Ljava/lang/CharSequence;)V
│ │ +   #59 = Utf8               java/lang/Object
│ │ +   #60 = Class              #59           // java/lang/Object
│ │ +   #61 = Utf8               getClass
│ │ +   #62 = Utf8               ()Ljava/lang/Class;
│ │ +   #63 = NameAndType        #61:#62       // getClass:()Ljava/lang/Class;
│ │ +   #64 = Methodref          #60.#63       // java/lang/Object.getClass:()Ljava/lang/Class;
│ │ +   #65 = Utf8               java/lang/Class
│ │ +   #66 = Class              #65           // java/lang/Class
│ │ +   #67 = Utf8               getResourceAsStream
│ │ +   #68 = Utf8               (Ljava/lang/String;)Ljava/io/InputStream;
│ │ +   #69 = NameAndType        #67:#68       // getResourceAsStream:(Ljava/lang/String;)Ljava/io/InputStream;
│ │ +   #70 = Methodref          #66.#69       // java/lang/Class.getResourceAsStream:(Ljava/lang/String;)Ljava/io/InputStream;
│ │ +   #71 = Utf8               javax/xml/parsers/DocumentBuilderFactory
│ │ +   #72 = Class              #71           // javax/xml/parsers/DocumentBuilderFactory
│ │ +   #73 = Utf8               newInstance
│ │ +   #74 = Utf8               ()Ljavax/xml/parsers/DocumentBuilderFactory;
│ │ +   #75 = NameAndType        #73:#74       // newInstance:()Ljavax/xml/parsers/DocumentBuilderFactory;
│ │ +   #76 = Methodref          #72.#75       // javax/xml/parsers/DocumentBuilderFactory.newInstance:()Ljavax/xml/parsers/DocumentBuilderFactory;
│ │ +   #77 = Utf8               newDocumentBuilder
│ │ +   #78 = Utf8               ()Ljavax/xml/parsers/DocumentBuilder;
│ │ +   #79 = NameAndType        #77:#78       // newDocumentBuilder:()Ljavax/xml/parsers/DocumentBuilder;
│ │ +   #80 = Methodref          #72.#79       // javax/xml/parsers/DocumentBuilderFactory.newDocumentBuilder:()Ljavax/xml/parsers/DocumentBuilder;
│ │ +   #81 = Utf8               javax/xml/parsers/DocumentBuilder
│ │ +   #82 = Class              #81           // javax/xml/parsers/DocumentBuilder
│ │ +   #83 = Utf8               parse
│ │ +   #84 = Utf8               (Ljava/io/InputStream;)Lorg/w3c/dom/Document;
│ │ +   #85 = NameAndType        #83:#84       // parse:(Ljava/io/InputStream;)Lorg/w3c/dom/Document;
│ │ +   #86 = Methodref          #82.#85       // javax/xml/parsers/DocumentBuilder.parse:(Ljava/io/InputStream;)Lorg/w3c/dom/Document;
│ │ +   #87 = Utf8               java/io/InputStream
│ │ +   #88 = Class              #87           // java/io/InputStream
│ │ +   #89 = Utf8               close
│ │ +   #90 = NameAndType        #89:#32       // close:()V
│ │ +   #91 = Methodref          #88.#90       // java/io/InputStream.close:()V
│ │ +   #92 = Utf8               org/w3c/dom/Document
│ │ +   #93 = Class              #92           // org/w3c/dom/Document
│ │ +   #94 = Utf8               getMessage
│ │ +   #95 = Utf8               ()Ljava/lang/String;
│ │ +   #96 = NameAndType        #94:#95       // getMessage:()Ljava/lang/String;
│ │ +   #97 = Methodref          #42.#96       // java/io/IOException.getMessage:()Ljava/lang/String;
│ │ +   #98 = Utf8               (Ljava/lang/String;Ljava/lang/Exception;)V
│ │ +   #99 = NameAndType        #31:#98       // "<init>":(Ljava/lang/String;Ljava/lang/Exception;)V
│ │ +  #100 = Methodref          #40.#99       // org/apache/maven/plugin/MojoExecutionException."<init>":(Ljava/lang/String;Ljava/lang/Exception;)V
│ │ +  #101 = Methodref          #44.#96       // javax/xml/parsers/ParserConfigurationException.getMessage:()Ljava/lang/String;
│ │ +  #102 = Methodref          #46.#96       // org/xml/sax/SAXException.getMessage:()Ljava/lang/String;
│ │ +  #103 = Utf8               java/lang/Throwable
│ │ +  #104 = Class              #103          // java/lang/Throwable
│ │ +  #105 = Utf8               e
│ │ +  #106 = Utf8               Ljava/io/IOException;
│ │ +  #107 = Utf8               dbFactory
│ │ +  #108 = Utf8               Ljavax/xml/parsers/DocumentBuilderFactory;
│ │ +  #109 = Utf8               dBuilder
│ │ +  #110 = Utf8               Ljavax/xml/parsers/DocumentBuilder;
│ │ +  #111 = Utf8               Ljavax/xml/parsers/ParserConfigurationException;
│ │ +  #112 = Utf8               Lorg/xml/sax/SAXException;
│ │ +  #113 = Utf8               is
│ │ +  #114 = Utf8               Ljava/io/InputStream;
│ │ +  #115 = Utf8               execute
│ │ +  #116 = NameAndType        #21:#22       // lineLength:I
│ │ +  #117 = Fieldref           #2.#116       // io/fabric8/maven/docker/HelpMojo.lineLength:I
│ │ +  #118 = Utf8               The parameter \'lineLength\' should be positive, using \'80\' as default.
│ │ +  #119 = String             #118          // The parameter \'lineLength\' should be positive, using \'80\' as default.
│ │ +  #120 = Utf8               warn
│ │ +  #121 = NameAndType        #120:#56      // warn:(Ljava/lang/CharSequence;)V
│ │ +  #122 = InterfaceMethodref #54.#121      // org/apache/maven/plugin/logging/Log.warn:(Ljava/lang/CharSequence;)V
│ │ +  #123 = NameAndType        #24:#22       // indentSize:I
│ │ +  #124 = Fieldref           #2.#123       // io/fabric8/maven/docker/HelpMojo.indentSize:I
│ │ +  #125 = Utf8               The parameter \'indentSize\' should be positive, using \'2\' as default.
│ │ +  #126 = String             #125          // The parameter \'indentSize\' should be positive, using \'2\' as default.
│ │ +  #127 = NameAndType        #37:#38       // build:()Lorg/w3c/dom/Document;
│ │ +  #128 = Methodref          #2.#127       // io/fabric8/maven/docker/HelpMojo.build:()Lorg/w3c/dom/Document;
│ │ +  #129 = Utf8               java/lang/StringBuilder
│ │ +  #130 = Class              #129          // java/lang/StringBuilder
│ │ +  #131 = Methodref          #130.#33      // java/lang/StringBuilder."<init>":()V
│ │ +  #132 = Utf8               plugin
│ │ +  #133 = String             #132          // plugin
│ │ +  #134 = Utf8               getSingleChild
│ │ +  #135 = Utf8               (Lorg/w3c/dom/Node;Ljava/lang/String;)Lorg/w3c/dom/Node;
│ │ +  #136 = NameAndType        #134:#135     // getSingleChild:(Lorg/w3c/dom/Node;Ljava/lang/String;)Lorg/w3c/dom/Node;
│ │ +  #137 = Methodref          #2.#136       // io/fabric8/maven/docker/HelpMojo.getSingleChild:(Lorg/w3c/dom/Node;Ljava/lang/String;)Lorg/w3c/dom/Node;
│ │ +  #138 = String             #7            // name
│ │ +  #139 = Utf8               getValue
│ │ +  #140 = Utf8               (Lorg/w3c/dom/Node;Ljava/lang/String;)Ljava/lang/String;
│ │ +  #141 = NameAndType        #139:#140     // getValue:(Lorg/w3c/dom/Node;Ljava/lang/String;)Ljava/lang/String;
│ │ +  #142 = Methodref          #2.#141       // io/fabric8/maven/docker/HelpMojo.getValue:(Lorg/w3c/dom/Node;Ljava/lang/String;)Ljava/lang/String;
│ │ +  #143 = Utf8               version
│ │ +  #144 = String             #143          // version
│ │ +  #145 = Utf8               groupId
│ │ +  #146 = String             #145          // groupId
│ │ +  #147 = Utf8               append
│ │ +  #148 = Utf8               (Ljava/lang/String;)Ljava/lang/StringBuilder;
│ │ +  #149 = NameAndType        #147:#148     // append:(Ljava/lang/String;)Ljava/lang/StringBuilder;
│ │ +  #150 = Methodref          #130.#149     // java/lang/StringBuilder.append:(Ljava/lang/String;)Ljava/lang/StringBuilder;
│ │ +  #151 = Utf8               :
│ │ +  #152 = String             #151          // :
│ │ +  #153 = Utf8               artifactId
│ │ +  #154 = String             #153          // artifactId
│ │ +  #155 = Utf8               toString
│ │ +  #156 = NameAndType        #155:#95      // toString:()Ljava/lang/String;
│ │ +  #157 = Methodref          #130.#156     // java/lang/StringBuilder.toString:()Ljava/lang/String;
│ │ +  #158 = Utf8               isNotEmpty
│ │ +  #159 = Utf8               (Ljava/lang/String;)Z
│ │ +  #160 = NameAndType        #158:#159     // isNotEmpty:(Ljava/lang/String;)Z
│ │ +  #161 = Methodref          #2.#160       // io/fabric8/maven/docker/HelpMojo.isNotEmpty:(Ljava/lang/String;)Z
│ │ +  #162 = Utf8               java/lang/String
│ │ +  #163 = Class              #162          // java/lang/String
│ │ +  #164 = Utf8               contains
│ │ +  #165 = Utf8               (Ljava/lang/CharSequence;)Z
│ │ +  #166 = NameAndType        #164:#165     // contains:(Ljava/lang/CharSequence;)Z
│ │ +  #167 = Methodref          #163.#166     // java/lang/String.contains:(Ljava/lang/CharSequence;)Z
│ │ +  #168 = Utf8
│ │ +  #169 = String             #168          //
│ │ +  #170 = Utf8               (Ljava/lang/StringBuilder;Ljava/lang/String;I)V
│ │ +  #171 = NameAndType        #147:#170     // append:(Ljava/lang/StringBuilder;Ljava/lang/String;I)V
│ │ +  #172 = Methodref          #2.#171       // io/fabric8/maven/docker/HelpMojo.append:(Ljava/lang/StringBuilder;Ljava/lang/String;I)V
│ │ +  #173 = Utf8               org/w3c/dom/Node
│ │ +  #174 = Class              #173          // org/w3c/dom/Node
│ │ +  #175 = Utf8               description
│ │ +  #176 = String             #175          // description
│ │ +  #177 = Utf8
│ │ +  #178 = String             #177          //
│ │ +  #179 = Utf8               goalPrefix
│ │ +  #180 = String             #179          // goalPrefix
│ │ +  #181 = Utf8               mojos
│ │ +  #182 = String             #181          // mojos
│ │ +  #183 = Utf8               mojo
│ │ +  #184 = String             #183          // mojo
│ │ +  #185 = Utf8               findNamedChild
│ │ +  #186 = Utf8               (Lorg/w3c/dom/Node;Ljava/lang/String;)Ljava/util/List;
│ │ +  #187 = NameAndType        #185:#186     // findNamedChild:(Lorg/w3c/dom/Node;Ljava/lang/String;)Ljava/util/List;
│ │ +  #188 = Methodref          #2.#187       // io/fabric8/maven/docker/HelpMojo.findNamedChild:(Lorg/w3c/dom/Node;Ljava/lang/String;)Ljava/util/List;
│ │ +  #189 = NameAndType        #19:#20       // goal:Ljava/lang/String;
│ │ +  #190 = Fieldref           #2.#189       // io/fabric8/maven/docker/HelpMojo.goal:Ljava/lang/String;
│ │ +  #191 = Utf8               length
│ │ +  #192 = Utf8               ()I
│ │ +  #193 = NameAndType        #191:#192     // length:()I
│ │ +  #194 = Methodref          #163.#193     // java/lang/String.length:()I
│ │ +  #195 = Utf8               java/util/List
│ │ +  #196 = Class              #195          // java/util/List
│ │ +  #197 = Utf8               This plugin has
│ │ +  #198 = String             #197          // This plugin has
│ │ +  #199 = Utf8               size
│ │ +  #200 = NameAndType        #199:#192     // size:()I
│ │ +  #201 = InterfaceMethodref #196.#200     // java/util/List.size:()I
│ │ +  #202 = Utf8               (I)Ljava/lang/StringBuilder;
│ │ +  #203 = NameAndType        #147:#202     // append:(I)Ljava/lang/StringBuilder;
│ │ +  #204 = Methodref          #130.#203     // java/lang/StringBuilder.append:(I)Ljava/lang/StringBuilder;
│ │ +  #205 = Utf8                goals:
│ │ +  #206 = String             #205          //  goals:
│ │ +  #207 = Utf8                goal:
│ │ +  #208 = String             #207          //  goal:
│ │ +  #209 = Utf8               iterator
│ │ +  #210 = Utf8               ()Ljava/util/Iterator;
│ │ +  #211 = NameAndType        #209:#210     // iterator:()Ljava/util/Iterator;
│ │ +  #212 = InterfaceMethodref #196.#211     // java/util/List.iterator:()Ljava/util/Iterator;
│ │ +  #213 = Utf8               java/util/Iterator
│ │ +  #214 = Class              #213          // java/util/Iterator
│ │ +  #215 = Utf8               hasNext
│ │ +  #216 = Utf8               ()Z
│ │ +  #217 = NameAndType        #215:#216     // hasNext:()Z
│ │ +  #218 = InterfaceMethodref #214.#217     // java/util/Iterator.hasNext:()Z
│ │ +  #219 = Utf8               next
│ │ +  #220 = Utf8               ()Ljava/lang/Object;
│ │ +  #221 = NameAndType        #219:#220     // next:()Ljava/lang/Object;
│ │ +  #222 = InterfaceMethodref #214.#221     // java/util/Iterator.next:()Ljava/lang/Object;
│ │ +  #223 = Utf8               org/w3c/dom/Element
│ │ +  #224 = Class              #223          // org/w3c/dom/Element
│ │ +  #225 = Utf8               writeGoal
│ │ +  #226 = Utf8               (Ljava/lang/StringBuilder;Ljava/lang/String;Lorg/w3c/dom/Element;)V
│ │ +  #227 = NameAndType        #225:#226     // writeGoal:(Ljava/lang/StringBuilder;Ljava/lang/String;Lorg/w3c/dom/Element;)V
│ │ +  #228 = Methodref          #2.#227       // io/fabric8/maven/docker/HelpMojo.writeGoal:(Ljava/lang/StringBuilder;Ljava/lang/String;Lorg/w3c/dom/Element;)V
│ │ +  #229 = Utf8               isInfoEnabled
│ │ +  #230 = NameAndType        #229:#216     // isInfoEnabled:()Z
│ │ +  #231 = InterfaceMethodref #54.#230      // org/apache/maven/plugin/logging/Log.isInfoEnabled:()Z
│ │ +  #232 = Utf8               info
│ │ +  #233 = NameAndType        #232:#56      // info:(Ljava/lang/CharSequence;)V
│ │ +  #234 = InterfaceMethodref #54.#233      // org/apache/maven/plugin/logging/Log.info:(Ljava/lang/CharSequence;)V
│ │ +  #235 = Utf8               Lorg/w3c/dom/Node;
│ │ +  #236 = Utf8               doc
│ │ +  #237 = Utf8               Lorg/w3c/dom/Document;
│ │ +  #238 = Utf8               sb
│ │ +  #239 = Utf8               Ljava/lang/StringBuilder;
│ │ +  #240 = Utf8               id
│ │ +  #241 = Utf8               mojos1
│ │ +  #242 = Utf8               Ljava/util/List<Lorg/w3c/dom/Node;>;
│ │ +  #243 = Utf8               Ljava/util/List;
│ │ +  #244 = Utf8               string
│ │ +  #245 = Utf8               getTextContent
│ │ +  #246 = NameAndType        #245:#95      // getTextContent:()Ljava/lang/String;
│ │ +  #247 = InterfaceMethodref #174.#246     // org/w3c/dom/Node.getTextContent:()Ljava/lang/String;
│ │ +  #248 = Utf8               node
│ │ +  #249 = Utf8               elementName
│ │ +  #250 = Utf8               isEmpty
│ │ +  #251 = NameAndType        #250:#216     // isEmpty:()Z
│ │ +  #252 = InterfaceMethodref #196.#251     // java/util/List.isEmpty:()Z
│ │ +  #253 = Utf8               Could not find
│ │ +  #254 = String             #253          // Could not find
│ │ +  #255 = Utf8                in plugin-help.xml
│ │ +  #256 = String             #255          //  in plugin-help.xml
│ │ +  #257 = Utf8               (Ljava/lang/String;)V
│ │ +  #258 = NameAndType        #31:#257      // "<init>":(Ljava/lang/String;)V
│ │ +  #259 = Methodref          #40.#258      // org/apache/maven/plugin/MojoExecutionException."<init>":(Ljava/lang/String;)V
│ │ +  #260 = Utf8               Multiple
│ │ +  #261 = String             #260          // Multiple
│ │ +  #262 = Utf8               get
│ │ +  #263 = Utf8               (I)Ljava/lang/Object;
│ │ +  #264 = NameAndType        #262:#263     // get:(I)Ljava/lang/Object;
│ │ +  #265 = InterfaceMethodref #196.#264     // java/util/List.get:(I)Ljava/lang/Object;
│ │ +  #266 = Utf8               namedChild
│ │ +  #267 = Utf8               (Lorg/w3c/dom/Node;Ljava/lang/String;)Ljava/util/List<Lorg/w3c/dom/Node;>;
│ │ +  #268 = Utf8               java/util/ArrayList
│ │ +  #269 = Class              #268          // java/util/ArrayList
│ │ +  #270 = Methodref          #269.#33      // java/util/ArrayList."<init>":()V
│ │ +  #271 = Utf8               getChildNodes
│ │ +  #272 = Utf8               ()Lorg/w3c/dom/NodeList;
│ │ +  #273 = NameAndType        #271:#272     // getChildNodes:()Lorg/w3c/dom/NodeList;
│ │ +  #274 = InterfaceMethodref #174.#273     // org/w3c/dom/Node.getChildNodes:()Lorg/w3c/dom/NodeList;
│ │ +  #275 = Utf8               org/w3c/dom/NodeList
│ │ +  #276 = Class              #275          // org/w3c/dom/NodeList
│ │ +  #277 = Utf8               getLength
│ │ +  #278 = NameAndType        #277:#192     // getLength:()I
│ │ +  #279 = InterfaceMethodref #276.#278     // org/w3c/dom/NodeList.getLength:()I
│ │ +  #280 = Utf8               item
│ │ +  #281 = Utf8               (I)Lorg/w3c/dom/Node;
│ │ +  #282 = NameAndType        #280:#281     // item:(I)Lorg/w3c/dom/Node;
│ │ +  #283 = InterfaceMethodref #276.#282     // org/w3c/dom/NodeList.item:(I)Lorg/w3c/dom/Node;
│ │ +  #284 = Utf8               getNodeName
│ │ +  #285 = NameAndType        #284:#95      // getNodeName:()Ljava/lang/String;
│ │ +  #286 = InterfaceMethodref #174.#285     // org/w3c/dom/Node.getNodeName:()Ljava/lang/String;
│ │ +  #287 = Utf8               equals
│ │ +  #288 = Utf8               (Ljava/lang/Object;)Z
│ │ +  #289 = NameAndType        #287:#288     // equals:(Ljava/lang/Object;)Z
│ │ +  #290 = Methodref          #163.#289     // java/lang/String.equals:(Ljava/lang/Object;)Z
│ │ +  #291 = Utf8               add
│ │ +  #292 = NameAndType        #291:#288     // add:(Ljava/lang/Object;)Z
│ │ +  #293 = InterfaceMethodref #196.#292     // java/util/List.add:(Ljava/lang/Object;)Z
│ │ +  #294 = Utf8               i
│ │ +  #295 = Utf8               result
│ │ +  #296 = Utf8               childNodes
│ │ +  #297 = Utf8               Lorg/w3c/dom/NodeList;
│ │ +  #298 = Utf8               findSingleChild
│ │ +  #299 = Utf8               in plugin-help.xml
│ │ +  #300 = String             #299          // in plugin-help.xml
│ │ +  #301 = Utf8               elementsByTagName
│ │ +  #302 = String             #19           // goal
│ │ +  #303 = Utf8               configuration
│ │ +  #304 = String             #303          // configuration
│ │ +  #305 = NameAndType        #298:#135     // findSingleChild:(Lorg/w3c/dom/Node;Ljava/lang/String;)Lorg/w3c/dom/Node;
│ │ +  #306 = Methodref          #2.#305       // io/fabric8/maven/docker/HelpMojo.findSingleChild:(Lorg/w3c/dom/Node;Ljava/lang/String;)Lorg/w3c/dom/Node;
│ │ +  #307 = Utf8               deprecated
│ │ +  #308 = String             #307          // deprecated
│ │ +  #309 = Utf8               Deprecated.
│ │ +  #310 = String             #309          // Deprecated.
│ │ +  #311 = NameAndType        #13:#14       // detail:Z
│ │ +  #312 = Fieldref           #2.#311       // io/fabric8/maven/docker/HelpMojo.detail:Z
│ │ +  #313 = Utf8               parameters
│ │ +  #314 = String             #313          // parameters
│ │ +  #315 = Utf8               parameter
│ │ +  #316 = String             #315          // parameter
│ │ +  #317 = Utf8               Available parameters:
│ │ +  #318 = String             #317          // Available parameters:
│ │ +  #319 = Utf8               writeParameter
│ │ +  #320 = Utf8               (Ljava/lang/StringBuilder;Lorg/w3c/dom/Node;Lorg/w3c/dom/Node;)V
│ │ +  #321 = NameAndType        #319:#320     // writeParameter:(Ljava/lang/StringBuilder;Lorg/w3c/dom/Node;Lorg/w3c/dom/Node;)V
│ │ +  #322 = Methodref          #2.#321       // io/fabric8/maven/docker/HelpMojo.writeParameter:(Ljava/lang/StringBuilder;Lorg/w3c/dom/Node;Lorg/w3c/dom/Node;)V
│ │ +  #323 = Utf8               parametersNode
│ │ +  #324 = Utf8               Lorg/w3c/dom/Element;
│ │ +  #325 = Utf8               mojoGoal
│ │ +  #326 = Utf8               configurationElement
│ │ +  #327 = Utf8               default-value
│ │ +  #328 = String             #327          // default-value
│ │ +  #329 = Utf8               hasAttribute
│ │ +  #330 = NameAndType        #329:#159     // hasAttribute:(Ljava/lang/String;)Z
│ │ +  #331 = InterfaceMethodref #224.#330     // org/w3c/dom/Element.hasAttribute:(Ljava/lang/String;)Z
│ │ +  #332 = Utf8                (Default:
│ │ +  #333 = String             #332          //  (Default:
│ │ +  #334 = Utf8               getAttribute
│ │ +  #335 = Utf8               (Ljava/lang/String;)Ljava/lang/String;
│ │ +  #336 = NameAndType        #334:#335     // getAttribute:(Ljava/lang/String;)Ljava/lang/String;
│ │ +  #337 = InterfaceMethodref #224.#336     // org/w3c/dom/Element.getAttribute:(Ljava/lang/String;)Ljava/lang/String;
│ │ +  #338 = Utf8               )
│ │ +  #339 = String             #338          // )
│ │ +  #340 = Utf8               true
│ │ +  #341 = String             #340          // true
│ │ +  #342 = Utf8               required
│ │ +  #343 = String             #342          // required
│ │ +  #344 = Utf8               Required: Yes
│ │ +  #345 = String             #344          // Required: Yes
│ │ +  #346 = InterfaceMethodref #224.#246     // org/w3c/dom/Element.getTextContent:()Ljava/lang/String;
│ │ +  #347 = Utf8               getPropertyFromExpression
│ │ +  #348 = NameAndType        #347:#335     // getPropertyFromExpression:(Ljava/lang/String;)Ljava/lang/String;
│ │ +  #349 = Methodref          #2.#348       // io/fabric8/maven/docker/HelpMojo.getPropertyFromExpression:(Ljava/lang/String;)Ljava/lang/String;
│ │ +  #350 = Utf8               User property:
│ │ +  #351 = String             #350          // User property:
│ │ +  #352 = Utf8               parameterName
│ │ +  #353 = Utf8               parameterDescription
│ │ +  #354 = Utf8               fieldConfigurationElement
│ │ +  #355 = Utf8               parameterDefaultValue
│ │ +  #356 = Utf8               repeat
│ │ +  #357 = Utf8               (Ljava/lang/String;I)Ljava/lang/String;
│ │ +  #358 = Utf8               (I)V
│ │ +  #359 = NameAndType        #31:#358      // "<init>":(I)V
│ │ +  #360 = Methodref          #130.#359     // java/lang/StringBuilder."<init>":(I)V
│ │ +  #361 = Utf8               str
│ │ +  #362 = Utf8               buffer
│ │ +  #363 = Utf8               toLines
│ │ +  #364 = Utf8               (Ljava/lang/String;III)Ljava/util/List;
│ │ +  #365 = NameAndType        #363:#364     // toLines:(Ljava/lang/String;III)Ljava/util/List;
│ │ +  #366 = Methodref          #2.#365       // io/fabric8/maven/docker/HelpMojo.toLines:(Ljava/lang/String;III)Ljava/util/List;
│ │ +  #367 = Utf8               (C)Ljava/lang/StringBuilder;
│ │ +  #368 = NameAndType        #147:#367     // append:(C)Ljava/lang/StringBuilder;
│ │ +  #369 = Methodref          #130.#368     // java/lang/StringBuilder.append:(C)Ljava/lang/StringBuilder;
│ │ +  #370 = Utf8               line
│ │ +  #371 = Utf8               indent
│ │ +  #372 = Utf8               (Ljava/lang/String;III)Ljava/util/List<Ljava/lang/String;>;
│ │ +  #373 = Utf8               \t
│ │ +  #374 = String             #373          // \t
│ │ +  #375 = NameAndType        #356:#357     // repeat:(Ljava/lang/String;I)Ljava/lang/String;
│ │ +  #376 = Methodref          #2.#375       // io/fabric8/maven/docker/HelpMojo.repeat:(Ljava/lang/String;I)Ljava/lang/String;
│ │ +  #377 = Utf8               (\r\n)|(\r)|(\n)
│ │ +  #378 = String             #377          // (\r\n)|(\r)|(\n)
│ │ +  #379 = Utf8               split
│ │ +  #380 = Utf8               (Ljava/lang/String;)[Ljava/lang/String;
│ │ +  #381 = NameAndType        #379:#380     // split:(Ljava/lang/String;)[Ljava/lang/String;
│ │ +  #382 = Methodref          #163.#381     // java/lang/String.split:(Ljava/lang/String;)[Ljava/lang/String;
│ │ +  #383 = Utf8               [Ljava/lang/String;
│ │ +  #384 = Class              #383          // "[Ljava/lang/String;"
│ │ +  #385 = Utf8               (Ljava/util/List;Ljava/lang/String;II)V
│ │ +  #386 = NameAndType        #363:#385     // toLines:(Ljava/util/List;Ljava/lang/String;II)V
│ │ +  #387 = Methodref          #2.#386       // io/fabric8/maven/docker/HelpMojo.toLines:(Ljava/util/List;Ljava/lang/String;II)V
│ │ +  #388 = Utf8               plainLine
│ │ +  #389 = Utf8               text
│ │ +  #390 = Utf8               lines
│ │ +  #391 = Utf8               Ljava/util/List<Ljava/lang/String;>;
│ │ +  #392 = Utf8               ind
│ │ +  #393 = Utf8               plainLines
│ │ +  #394 = Utf8               (Ljava/util/List<Ljava/lang/String;>;Ljava/lang/String;II)V
│ │ +  #395 = Utf8               getIndentLevel
│ │ +  #396 = Utf8               (Ljava/lang/String;)I
│ │ +  #397 = NameAndType        #395:#396     // getIndentLevel:(Ljava/lang/String;)I
│ │ +  #398 = Methodref          #2.#397       // io/fabric8/maven/docker/HelpMojo.getIndentLevel:(Ljava/lang/String;)I
│ │ +  #399 = Utf8                +
│ │ +  #400 = String             #399          //  +
│ │ +  #401 = Methodref          #130.#193     // java/lang/StringBuilder.length:()I
│ │ +  #402 = Utf8               setLength
│ │ +  #403 = NameAndType        #402:#358     // setLength:(I)V
│ │ +  #404 = Methodref          #130.#403     // java/lang/StringBuilder.setLength:(I)V
│ │ +  #405 = Utf8               charAt
│ │ +  #406 = Utf8               (I)C
│ │ +  #407 = NameAndType        #405:#406     // charAt:(I)C
│ │ +  #408 = Methodref          #163.#407     // java/lang/String.charAt:(I)C
│ │ +  #409 = Utf8               c
│ │ +  #410 = Utf8               C
│ │ +  #411 = Utf8               j
│ │ +  #412 = Utf8               token
│ │ +  #413 = Utf8               lineIndent
│ │ +  #414 = Utf8               buf
│ │ +  #415 = Utf8               tokens
│ │ +  #416 = Utf8               level
│ │ +  #417 = Utf8               ${
│ │ +  #418 = String             #417          // ${
│ │ +  #419 = Utf8               startsWith
│ │ +  #420 = NameAndType        #419:#159     // startsWith:(Ljava/lang/String;)Z
│ │ +  #421 = Methodref          #163.#420     // java/lang/String.startsWith:(Ljava/lang/String;)Z
│ │ +  #422 = Utf8               }
│ │ +  #423 = String             #422          // }
│ │ +  #424 = Utf8               endsWith
│ │ +  #425 = NameAndType        #424:#159     // endsWith:(Ljava/lang/String;)Z
│ │ +  #426 = Methodref          #163.#425     // java/lang/String.endsWith:(Ljava/lang/String;)Z
│ │ +  #427 = Utf8               substring
│ │ +  #428 = Utf8               (I)Ljava/lang/String;
│ │ +  #429 = NameAndType        #427:#428     // substring:(I)Ljava/lang/String;
│ │ +  #430 = Methodref          #163.#429     // java/lang/String.substring:(I)Ljava/lang/String;
│ │ +  #431 = Utf8               (II)Ljava/lang/String;
│ │ +  #432 = NameAndType        #427:#431     // substring:(II)Ljava/lang/String;
│ │ +  #433 = Methodref          #163.#432     // java/lang/String.substring:(II)Ljava/lang/String;
│ │ +  #434 = Utf8               expression
│ │ +  #435 = Utf8               RuntimeInvisibleAnnotations
│ │ +  #436 = Utf8               ConstantValue
│ │ +  #437 = Utf8               Code
│ │ +  #438 = Utf8               LineNumberTable
│ │ +  #439 = Utf8               LocalVariableTable
│ │ +  #440 = Utf8               StackMapTable
│ │ +  #441 = Utf8               Exceptions
│ │ +  #442 = Utf8               LocalVariableTypeTable
│ │ +  #443 = Utf8               Signature
│ │ +  #444 = Utf8               SourceFile
│ │  {
│ │    private boolean detail;
│ │      descriptor: Z
│ │      flags: (0x0002) ACC_PRIVATE
│ │      RuntimeInvisibleAnnotations:
│ │ -      0: #125(#126=s#122,#127=s#128)
│ │ +      0: #15(#16=s#13,#17=s#18)
│ │          org.apache.maven.plugins.annotations.Parameter(
│ │            property="detail"
│ │            defaultValue="false"
│ │          )
│ │  
│ │    private java.lang.String goal;
│ │      descriptor: Ljava/lang/String;
│ │      flags: (0x0002) ACC_PRIVATE
│ │      RuntimeInvisibleAnnotations:
│ │ -      0: #125(#126=s#129)
│ │ +      0: #15(#16=s#19)
│ │          org.apache.maven.plugins.annotations.Parameter(
│ │            property="goal"
│ │          )
│ │  
│ │    private int lineLength;
│ │      descriptor: I
│ │      flags: (0x0002) ACC_PRIVATE
│ │      RuntimeInvisibleAnnotations:
│ │ -      0: #125(#126=s#131,#127=s#133)
│ │ +      0: #15(#16=s#21,#17=s#23)
│ │          org.apache.maven.plugins.annotations.Parameter(
│ │            property="lineLength"
│ │            defaultValue="80"
│ │          )
│ │  
│ │    private int indentSize;
│ │      descriptor: I
│ │      flags: (0x0002) ACC_PRIVATE
│ │      RuntimeInvisibleAnnotations:
│ │ -      0: #125(#126=s#134,#127=s#135)
│ │ +      0: #15(#16=s#24,#17=s#25)
│ │          org.apache.maven.plugins.annotations.Parameter(
│ │            property="indentSize"
│ │            defaultValue="2"
│ │          )
│ │  
│ │    private static final java.lang.String PLUGIN_HELP_PATH = "/META-INF/maven/io.fabric8/docker-maven-plugin/plugin-help.xml";
│ │      descriptor: Ljava/lang/String;
│ │ @@ -503,147 +503,111 @@
│ │  
│ │    public io.fabric8.maven.docker.HelpMojo();
│ │      descriptor: ()V
│ │      flags: (0x0001) ACC_PUBLIC
│ │      Code:
│ │        stack=1, locals=1, args_size=1
│ │           0: aload_0
│ │ -         1: invokespecial #1                  // Method org/apache/maven/plugin/AbstractMojo."<init>":()V
│ │ +         1: invokespecial #34                 // Method org/apache/maven/plugin/AbstractMojo."<init>":()V
│ │           4: return
│ │        LineNumberTable:
│ │ -        line 29: 0
│ │ +        line 28: 0
│ │        LocalVariableTable:
│ │          Start  Length  Slot  Name   Signature
│ │              0       5     0  this   Lio/fabric8/maven/docker/HelpMojo;
│ │  
│ │    private org.w3c.dom.Document build() throws org.apache.maven.plugin.MojoExecutionException;
│ │      descriptor: ()Lorg/w3c/dom/Document;
│ │      flags: (0x0002) ACC_PRIVATE
│ │      Code:
│ │        stack=4, locals=8, args_size=1
│ │           0: aload_0
│ │ -         1: invokevirtual #2                  // Method getLog:()Lorg/apache/maven/plugin/logging/Log;
│ │ -         4: ldc           #4                  // String load plugin-help.xml: /META-INF/maven/io.fabric8/docker-maven-plugin/plugin-help.xml
│ │ -         6: invokeinterface #5,  2            // InterfaceMethod org/apache/maven/plugin/logging/Log.debug:(Ljava/lang/CharSequence;)V
│ │ +         1: invokevirtual #50                 // Method getLog:()Lorg/apache/maven/plugin/logging/Log;
│ │ +         4: ldc           #52                 // String load plugin-help.xml: /META-INF/maven/io.fabric8/docker-maven-plugin/plugin-help.xml
│ │ +         6: invokeinterface #58,  2           // InterfaceMethod org/apache/maven/plugin/logging/Log.debug:(Ljava/lang/CharSequence;)V
│ │          11: aconst_null
│ │          12: astore_1
│ │          13: aload_0
│ │ -        14: invokevirtual #6                  // Method java/lang/Object.getClass:()Ljava/lang/Class;
│ │ -        17: ldc           #7                  // String /META-INF/maven/io.fabric8/docker-maven-plugin/plugin-help.xml
│ │ -        19: invokevirtual #8                  // Method java/lang/Class.getResourceAsStream:(Ljava/lang/String;)Ljava/io/InputStream;
│ │ +        14: invokevirtual #64                 // Method java/lang/Object.getClass:()Ljava/lang/Class;
│ │ +        17: ldc           #28                 // String /META-INF/maven/io.fabric8/docker-maven-plugin/plugin-help.xml
│ │ +        19: invokevirtual #70                 // Method java/lang/Class.getResourceAsStream:(Ljava/lang/String;)Ljava/io/InputStream;
│ │          22: astore_1
│ │ -        23: invokestatic  #9                  // Method javax/xml/parsers/DocumentBuilderFactory.newInstance:()Ljavax/xml/parsers/DocumentBuilderFactory;
│ │ +        23: invokestatic  #76                 // Method javax/xml/parsers/DocumentBuilderFactory.newInstance:()Ljavax/xml/parsers/DocumentBuilderFactory;
│ │          26: astore_2
│ │          27: aload_2
│ │ -        28: invokevirtual #10                 // Method javax/xml/parsers/DocumentBuilderFactory.newDocumentBuilder:()Ljavax/xml/parsers/DocumentBuilder;
│ │ +        28: invokevirtual #80                 // Method javax/xml/parsers/DocumentBuilderFactory.newDocumentBuilder:()Ljavax/xml/parsers/DocumentBuilder;
│ │          31: astore_3
│ │          32: aload_3
│ │          33: aload_1
│ │ -        34: invokevirtual #11                 // Method javax/xml/parsers/DocumentBuilder.parse:(Ljava/io/InputStream;)Lorg/w3c/dom/Document;
│ │ +        34: invokevirtual #86                 // Method javax/xml/parsers/DocumentBuilder.parse:(Ljava/io/InputStream;)Lorg/w3c/dom/Document;
│ │          37: astore        4
│ │          39: aload_1
│ │          40: ifnull        67
│ │          43: aload_1
│ │ -        44: invokevirtual #12                 // Method java/io/InputStream.close:()V
│ │ +        44: invokevirtual #91                 // Method java/io/InputStream.close:()V
│ │          47: goto          67
│ │          50: astore        5
│ │ -        52: new           #14                 // class org/apache/maven/plugin/MojoExecutionException
│ │ +        52: new           #40                 // class org/apache/maven/plugin/MojoExecutionException
│ │          55: dup
│ │          56: aload         5
│ │ -        58: invokevirtual #15                 // Method java/io/IOException.getMessage:()Ljava/lang/String;
│ │ +        58: invokevirtual #97                 // Method java/io/IOException.getMessage:()Ljava/lang/String;
│ │          61: aload         5
│ │ -        63: invokespecial #16                 // Method org/apache/maven/plugin/MojoExecutionException."<init>":(Ljava/lang/String;Ljava/lang/Exception;)V
│ │ +        63: invokespecial #100                // Method org/apache/maven/plugin/MojoExecutionException."<init>":(Ljava/lang/String;Ljava/lang/Exception;)V
│ │          66: athrow
│ │          67: aload         4
│ │          69: areturn
│ │          70: astore_2
│ │ -        71: new           #14                 // class org/apache/maven/plugin/MojoExecutionException
│ │ +        71: new           #40                 // class org/apache/maven/plugin/MojoExecutionException
│ │          74: dup
│ │          75: aload_2
│ │ -        76: invokevirtual #15                 // Method java/io/IOException.getMessage:()Ljava/lang/String;
│ │ +        76: invokevirtual #97                 // Method java/io/IOException.getMessage:()Ljava/lang/String;
│ │          79: aload_2
│ │ -        80: invokespecial #16                 // Method org/apache/maven/plugin/MojoExecutionException."<init>":(Ljava/lang/String;Ljava/lang/Exception;)V
│ │ +        80: invokespecial #100                // Method org/apache/maven/plugin/MojoExecutionException."<init>":(Ljava/lang/String;Ljava/lang/Exception;)V
│ │          83: athrow
│ │          84: astore_2
│ │ -        85: new           #14                 // class org/apache/maven/plugin/MojoExecutionException
│ │ +        85: new           #40                 // class org/apache/maven/plugin/MojoExecutionException
│ │          88: dup
│ │          89: aload_2
│ │ -        90: invokevirtual #18                 // Method javax/xml/parsers/ParserConfigurationException.getMessage:()Ljava/lang/String;
│ │ +        90: invokevirtual #101                // Method javax/xml/parsers/ParserConfigurationException.getMessage:()Ljava/lang/String;
│ │          93: aload_2
│ │ -        94: invokespecial #16                 // Method org/apache/maven/plugin/MojoExecutionException."<init>":(Ljava/lang/String;Ljava/lang/Exception;)V
│ │ +        94: invokespecial #100                // Method org/apache/maven/plugin/MojoExecutionException."<init>":(Ljava/lang/String;Ljava/lang/Exception;)V
│ │          97: athrow
│ │          98: astore_2
│ │ -        99: new           #14                 // class org/apache/maven/plugin/MojoExecutionException
│ │ +        99: new           #40                 // class org/apache/maven/plugin/MojoExecutionException
│ │         102: dup
│ │         103: aload_2
│ │ -       104: invokevirtual #20                 // Method org/xml/sax/SAXException.getMessage:()Ljava/lang/String;
│ │ +       104: invokevirtual #102                // Method org/xml/sax/SAXException.getMessage:()Ljava/lang/String;
│ │         107: aload_2
│ │ -       108: invokespecial #16                 // Method org/apache/maven/plugin/MojoExecutionException."<init>":(Ljava/lang/String;Ljava/lang/Exception;)V
│ │ +       108: invokespecial #100                // Method org/apache/maven/plugin/MojoExecutionException."<init>":(Ljava/lang/String;Ljava/lang/Exception;)V
│ │         111: athrow
│ │         112: astore        6
│ │         114: aload_1
│ │         115: ifnull        142
│ │         118: aload_1
│ │ -       119: invokevirtual #12                 // Method java/io/InputStream.close:()V
│ │ +       119: invokevirtual #91                 // Method java/io/InputStream.close:()V
│ │         122: goto          142
│ │         125: astore        7
│ │ -       127: new           #14                 // class org/apache/maven/plugin/MojoExecutionException
│ │ +       127: new           #40                 // class org/apache/maven/plugin/MojoExecutionException
│ │         130: dup
│ │         131: aload         7
│ │ -       133: invokevirtual #15                 // Method java/io/IOException.getMessage:()Ljava/lang/String;
│ │ +       133: invokevirtual #97                 // Method java/io/IOException.getMessage:()Ljava/lang/String;
│ │         136: aload         7
│ │ -       138: invokespecial #16                 // Method org/apache/maven/plugin/MojoExecutionException."<init>":(Ljava/lang/String;Ljava/lang/Exception;)V
│ │ +       138: invokespecial #100                // Method org/apache/maven/plugin/MojoExecutionException."<init>":(Ljava/lang/String;Ljava/lang/Exception;)V
│ │         141: athrow
│ │         142: aload         6
│ │         144: athrow
│ │        Exception table:
│ │           from    to  target type
│ │              43    47    50   Class java/io/IOException
│ │              13    39    70   Class java/io/IOException
│ │              13    39    84   Class javax/xml/parsers/ParserConfigurationException
│ │              13    39    98   Class org/xml/sax/SAXException
│ │              13    39   112   any
│ │             118   122   125   Class java/io/IOException
│ │              70   114   112   any
│ │ -      LineNumberTable:
│ │ -        line 69: 0
│ │ -        line 70: 11
│ │ -        line 73: 13
│ │ -        line 74: 23
│ │ -        line 75: 27
│ │ -        line 76: 32
│ │ -        line 92: 39
│ │ -        line 96: 43
│ │ -        line 101: 47
│ │ -        line 98: 50
│ │ -        line 100: 52
│ │ -        line 76: 67
│ │ -        line 78: 70
│ │ -        line 80: 71
│ │ -        line 82: 84
│ │ -        line 84: 85
│ │ -        line 86: 98
│ │ -        line 88: 99
│ │ -        line 92: 112
│ │ -        line 96: 118
│ │ -        line 101: 122
│ │ -        line 98: 125
│ │ -        line 100: 127
│ │ -        line 103: 142
│ │ -      LocalVariableTable:
│ │ -        Start  Length  Slot  Name   Signature
│ │ -           52      15     5     e   Ljava/io/IOException;
│ │ -           27      43     2 dbFactory   Ljavax/xml/parsers/DocumentBuilderFactory;
│ │ -           32      38     3 dBuilder   Ljavax/xml/parsers/DocumentBuilder;
│ │ -           71      13     2     e   Ljava/io/IOException;
│ │ -           85      13     2     e   Ljavax/xml/parsers/ParserConfigurationException;
│ │ -           99      13     2     e   Lorg/xml/sax/SAXException;
│ │ -          127      15     7     e   Ljava/io/IOException;
│ │ -            0     145     0  this   Lio/fabric8/maven/docker/HelpMojo;
│ │ -           13     132     1    is   Ljava/io/InputStream;
│ │        StackMapTable: number_of_entries = 8
│ │          frame_type = 255 /* full_frame */
│ │            offset_delta = 50
│ │            locals = [ class io/fabric8/maven/docker/HelpMojo, class java/io/InputStream, class javax/xml/parsers/DocumentBuilderFactory, class javax/xml/parsers/DocumentBuilder, class org/w3c/dom/Document ]
│ │            stack = [ class java/io/IOException ]
│ │          frame_type = 16 /* same */
│ │          frame_type = 255 /* full_frame */
│ │ @@ -657,257 +621,245 @@
│ │          frame_type = 77 /* same_locals_1_stack_item */
│ │            stack = [ class java/lang/Throwable ]
│ │          frame_type = 255 /* full_frame */
│ │            offset_delta = 12
│ │            locals = [ class io/fabric8/maven/docker/HelpMojo, class java/io/InputStream, top, top, top, top, class java/lang/Throwable ]
│ │            stack = [ class java/io/IOException ]
│ │          frame_type = 16 /* same */
│ │ +      LineNumberTable:
│ │ +        line 68: 0
│ │ +        line 69: 11
│ │ +        line 72: 13
│ │ +        line 73: 23
│ │ +        line 74: 27
│ │ +        line 75: 32
│ │ +        line 91: 39
│ │ +        line 95: 43
│ │ +        line 100: 47
│ │ +        line 97: 50
│ │ +        line 99: 52
│ │ +        line 75: 67
│ │ +        line 77: 70
│ │ +        line 79: 71
│ │ +        line 81: 84
│ │ +        line 83: 85
│ │ +        line 85: 98
│ │ +        line 87: 99
│ │ +        line 91: 112
│ │ +        line 95: 118
│ │ +        line 100: 122
│ │ +        line 97: 125
│ │ +        line 99: 127
│ │ +        line 102: 142
│ │ +      LocalVariableTable:
│ │ +        Start  Length  Slot  Name   Signature
│ │ +           52      15     5     e   Ljava/io/IOException;
│ │ +           27      43     2 dbFactory   Ljavax/xml/parsers/DocumentBuilderFactory;
│ │ +           32      38     3 dBuilder   Ljavax/xml/parsers/DocumentBuilder;
│ │ +           71      13     2     e   Ljava/io/IOException;
│ │ +           85      13     2     e   Ljavax/xml/parsers/ParserConfigurationException;
│ │ +           99      13     2     e   Lorg/xml/sax/SAXException;
│ │ +          127      15     7     e   Ljava/io/IOException;
│ │ +            0     145     0  this   Lio/fabric8/maven/docker/HelpMojo;
│ │ +           13     132     1    is   Ljava/io/InputStream;
│ │      Exceptions:
│ │        throws org.apache.maven.plugin.MojoExecutionException
│ │  
│ │    public void execute() throws org.apache.maven.plugin.MojoExecutionException;
│ │      descriptor: ()V
│ │      flags: (0x0001) ACC_PUBLIC
│ │      Code:
│ │        stack=5, locals=12, args_size=1
│ │           0: aload_0
│ │ -         1: getfield      #21                 // Field lineLength:I
│ │ +         1: getfield      #117                // Field lineLength:I
│ │           4: ifgt          24
│ │           7: aload_0
│ │ -         8: invokevirtual #2                  // Method getLog:()Lorg/apache/maven/plugin/logging/Log;
│ │ -        11: ldc           #22                 // String The parameter \'lineLength\' should be positive, using \'80\' as default.
│ │ -        13: invokeinterface #23,  2           // InterfaceMethod org/apache/maven/plugin/logging/Log.warn:(Ljava/lang/CharSequence;)V
│ │ +         8: invokevirtual #50                 // Method getLog:()Lorg/apache/maven/plugin/logging/Log;
│ │ +        11: ldc           #119                // String The parameter \'lineLength\' should be positive, using \'80\' as default.
│ │ +        13: invokeinterface #122,  2          // InterfaceMethod org/apache/maven/plugin/logging/Log.warn:(Ljava/lang/CharSequence;)V
│ │          18: aload_0
│ │          19: bipush        80
│ │ -        21: putfield      #21                 // Field lineLength:I
│ │ +        21: putfield      #117                // Field lineLength:I
│ │          24: aload_0
│ │ -        25: getfield      #24                 // Field indentSize:I
│ │ +        25: getfield      #124                // Field indentSize:I
│ │          28: ifgt          47
│ │          31: aload_0
│ │ -        32: invokevirtual #2                  // Method getLog:()Lorg/apache/maven/plugin/logging/Log;
│ │ -        35: ldc           #25                 // String The parameter \'indentSize\' should be positive, using \'2\' as default.
│ │ -        37: invokeinterface #23,  2           // InterfaceMethod org/apache/maven/plugin/logging/Log.warn:(Ljava/lang/CharSequence;)V
│ │ +        32: invokevirtual #50                 // Method getLog:()Lorg/apache/maven/plugin/logging/Log;
│ │ +        35: ldc           #126                // String The parameter \'indentSize\' should be positive, using \'2\' as default.
│ │ +        37: invokeinterface #122,  2          // InterfaceMethod org/apache/maven/plugin/logging/Log.warn:(Ljava/lang/CharSequence;)V
│ │          42: aload_0
│ │          43: iconst_2
│ │ -        44: putfield      #24                 // Field indentSize:I
│ │ +        44: putfield      #124                // Field indentSize:I
│ │          47: aload_0
│ │ -        48: invokespecial #26                 // Method build:()Lorg/w3c/dom/Document;
│ │ +        48: invokespecial #128                // Method build:()Lorg/w3c/dom/Document;
│ │          51: astore_1
│ │ -        52: new           #27                 // class java/lang/StringBuilder
│ │ +        52: new           #130                // class java/lang/StringBuilder
│ │          55: dup
│ │ -        56: invokespecial #28                 // Method java/lang/StringBuilder."<init>":()V
│ │ +        56: invokespecial #131                // Method java/lang/StringBuilder."<init>":()V
│ │          59: astore_2
│ │          60: aload_0
│ │          61: aload_1
│ │ -        62: ldc           #29                 // String plugin
│ │ -        64: invokespecial #30                 // Method getSingleChild:(Lorg/w3c/dom/Node;Ljava/lang/String;)Lorg/w3c/dom/Node;
│ │ +        62: ldc           #133                // String plugin
│ │ +        64: invokespecial #137                // Method getSingleChild:(Lorg/w3c/dom/Node;Ljava/lang/String;)Lorg/w3c/dom/Node;
│ │          67: astore_3
│ │          68: aload_0
│ │          69: aload_3
│ │ -        70: ldc           #31                 // String name
│ │ -        72: invokespecial #32                 // Method getValue:(Lorg/w3c/dom/Node;Ljava/lang/String;)Ljava/lang/String;
│ │ +        70: ldc           #138                // String name
│ │ +        72: invokespecial #142                // Method getValue:(Lorg/w3c/dom/Node;Ljava/lang/String;)Ljava/lang/String;
│ │          75: astore        4
│ │          77: aload_0
│ │          78: aload_3
│ │ -        79: ldc           #33                 // String version
│ │ -        81: invokespecial #32                 // Method getValue:(Lorg/w3c/dom/Node;Ljava/lang/String;)Ljava/lang/String;
│ │ +        79: ldc           #144                // String version
│ │ +        81: invokespecial #142                // Method getValue:(Lorg/w3c/dom/Node;Ljava/lang/String;)Ljava/lang/String;
│ │          84: astore        5
│ │ -        86: new           #27                 // class java/lang/StringBuilder
│ │ +        86: new           #130                // class java/lang/StringBuilder
│ │          89: dup
│ │ -        90: invokespecial #28                 // Method java/lang/StringBuilder."<init>":()V
│ │ +        90: invokespecial #131                // Method java/lang/StringBuilder."<init>":()V
│ │          93: aload_0
│ │          94: aload_3
│ │ -        95: ldc           #34                 // String groupId
│ │ -        97: invokespecial #32                 // Method getValue:(Lorg/w3c/dom/Node;Ljava/lang/String;)Ljava/lang/String;
│ │ -       100: invokevirtual #35                 // Method java/lang/StringBuilder.append:(Ljava/lang/String;)Ljava/lang/StringBuilder;
│ │ -       103: ldc           #36                 // String :
│ │ -       105: invokevirtual #35                 // Method java/lang/StringBuilder.append:(Ljava/lang/String;)Ljava/lang/StringBuilder;
│ │ +        95: ldc           #146                // String groupId
│ │ +        97: invokespecial #142                // Method getValue:(Lorg/w3c/dom/Node;Ljava/lang/String;)Ljava/lang/String;
│ │ +       100: invokevirtual #150                // Method java/lang/StringBuilder.append:(Ljava/lang/String;)Ljava/lang/StringBuilder;
│ │ +       103: ldc           #152                // String :
│ │ +       105: invokevirtual #150                // Method java/lang/StringBuilder.append:(Ljava/lang/String;)Ljava/lang/StringBuilder;
│ │         108: aload_0
│ │         109: aload_3
│ │ -       110: ldc           #37                 // String artifactId
│ │ -       112: invokespecial #32                 // Method getValue:(Lorg/w3c/dom/Node;Ljava/lang/String;)Ljava/lang/String;
│ │ -       115: invokevirtual #35                 // Method java/lang/StringBuilder.append:(Ljava/lang/String;)Ljava/lang/StringBuilder;
│ │ -       118: ldc           #36                 // String :
│ │ -       120: invokevirtual #35                 // Method java/lang/StringBuilder.append:(Ljava/lang/String;)Ljava/lang/StringBuilder;
│ │ +       110: ldc           #154                // String artifactId
│ │ +       112: invokespecial #142                // Method getValue:(Lorg/w3c/dom/Node;Ljava/lang/String;)Ljava/lang/String;
│ │ +       115: invokevirtual #150                // Method java/lang/StringBuilder.append:(Ljava/lang/String;)Ljava/lang/StringBuilder;
│ │ +       118: ldc           #152                // String :
│ │ +       120: invokevirtual #150                // Method java/lang/StringBuilder.append:(Ljava/lang/String;)Ljava/lang/StringBuilder;
│ │         123: aload         5
│ │ -       125: invokevirtual #35                 // Method java/lang/StringBuilder.append:(Ljava/lang/String;)Ljava/lang/StringBuilder;
│ │ -       128: invokevirtual #38                 // Method java/lang/StringBuilder.toString:()Ljava/lang/String;
│ │ +       125: invokevirtual #150                // Method java/lang/StringBuilder.append:(Ljava/lang/String;)Ljava/lang/StringBuilder;
│ │ +       128: invokevirtual #157                // Method java/lang/StringBuilder.toString:()Ljava/lang/String;
│ │         131: astore        6
│ │         133: aload         4
│ │ -       135: invokestatic  #39                 // Method isNotEmpty:(Ljava/lang/String;)Z
│ │ +       135: invokestatic  #161                // Method isNotEmpty:(Ljava/lang/String;)Z
│ │         138: ifeq          185
│ │         141: aload         4
│ │         143: aload         6
│ │ -       145: invokevirtual #40                 // Method java/lang/String.contains:(Ljava/lang/CharSequence;)Z
│ │ +       145: invokevirtual #167                // Method java/lang/String.contains:(Ljava/lang/CharSequence;)Z
│ │         148: ifne          185
│ │         151: aload_0
│ │         152: aload_2
│ │ -       153: new           #27                 // class java/lang/StringBuilder
│ │ +       153: new           #130                // class java/lang/StringBuilder
│ │         156: dup
│ │ -       157: invokespecial #28                 // Method java/lang/StringBuilder."<init>":()V
│ │ +       157: invokespecial #131                // Method java/lang/StringBuilder."<init>":()V
│ │         160: aload         4
│ │ -       162: invokevirtual #35                 // Method java/lang/StringBuilder.append:(Ljava/lang/String;)Ljava/lang/StringBuilder;
│ │ -       165: ldc           #41                 // String
│ │ -       167: invokevirtual #35                 // Method java/lang/StringBuilder.append:(Ljava/lang/String;)Ljava/lang/StringBuilder;
│ │ +       162: invokevirtual #150                // Method java/lang/StringBuilder.append:(Ljava/lang/String;)Ljava/lang/StringBuilder;
│ │ +       165: ldc           #169                // String
│ │ +       167: invokevirtual #150                // Method java/lang/StringBuilder.append:(Ljava/lang/String;)Ljava/lang/StringBuilder;
│ │         170: aload         5
│ │ -       172: invokevirtual #35                 // Method java/lang/StringBuilder.append:(Ljava/lang/String;)Ljava/lang/StringBuilder;
│ │ -       175: invokevirtual #38                 // Method java/lang/StringBuilder.toString:()Ljava/lang/String;
│ │ +       172: invokevirtual #150                // Method java/lang/StringBuilder.append:(Ljava/lang/String;)Ljava/lang/StringBuilder;
│ │ +       175: invokevirtual #157                // Method java/lang/StringBuilder.toString:()Ljava/lang/String;
│ │         178: iconst_0
│ │ -       179: invokespecial #42                 // Method append:(Ljava/lang/StringBuilder;Ljava/lang/String;I)V
│ │ +       179: invokespecial #172                // Method append:(Ljava/lang/StringBuilder;Ljava/lang/String;I)V
│ │         182: goto          212
│ │         185: aload         4
│ │ -       187: invokestatic  #39                 // Method isNotEmpty:(Ljava/lang/String;)Z
│ │ +       187: invokestatic  #161                // Method isNotEmpty:(Ljava/lang/String;)Z
│ │         190: ifeq          204
│ │         193: aload_0
│ │         194: aload_2
│ │         195: aload         4
│ │         197: iconst_0
│ │ -       198: invokespecial #42                 // Method append:(Ljava/lang/StringBuilder;Ljava/lang/String;I)V
│ │ +       198: invokespecial #172                // Method append:(Ljava/lang/StringBuilder;Ljava/lang/String;I)V
│ │         201: goto          212
│ │         204: aload_0
│ │         205: aload_2
│ │         206: aload         6
│ │         208: iconst_0
│ │ -       209: invokespecial #42                 // Method append:(Ljava/lang/StringBuilder;Ljava/lang/String;I)V
│ │ +       209: invokespecial #172                // Method append:(Ljava/lang/StringBuilder;Ljava/lang/String;I)V
│ │         212: aload_0
│ │         213: aload_2
│ │         214: aload_0
│ │         215: aload_3
│ │ -       216: ldc           #43                 // String description
│ │ -       218: invokespecial #32                 // Method getValue:(Lorg/w3c/dom/Node;Ljava/lang/String;)Ljava/lang/String;
│ │ +       216: ldc           #176                // String description
│ │ +       218: invokespecial #142                // Method getValue:(Lorg/w3c/dom/Node;Ljava/lang/String;)Ljava/lang/String;
│ │         221: iconst_1
│ │ -       222: invokespecial #42                 // Method append:(Ljava/lang/StringBuilder;Ljava/lang/String;I)V
│ │ +       222: invokespecial #172                // Method append:(Ljava/lang/StringBuilder;Ljava/lang/String;I)V
│ │         225: aload_0
│ │         226: aload_2
│ │ -       227: ldc           #44                 // String
│ │ +       227: ldc           #178                // String
│ │         229: iconst_0
│ │ -       230: invokespecial #42                 // Method append:(Ljava/lang/StringBuilder;Ljava/lang/String;I)V
│ │ +       230: invokespecial #172                // Method append:(Ljava/lang/StringBuilder;Ljava/lang/String;I)V
│ │         233: aload_0
│ │         234: aload_3
│ │ -       235: ldc           #45                 // String goalPrefix
│ │ -       237: invokespecial #32                 // Method getValue:(Lorg/w3c/dom/Node;Ljava/lang/String;)Ljava/lang/String;
│ │ +       235: ldc           #180                // String goalPrefix
│ │ +       237: invokespecial #142                // Method getValue:(Lorg/w3c/dom/Node;Ljava/lang/String;)Ljava/lang/String;
│ │         240: astore        7
│ │         242: aload_0
│ │         243: aload_3
│ │ -       244: ldc           #46                 // String mojos
│ │ -       246: invokespecial #30                 // Method getSingleChild:(Lorg/w3c/dom/Node;Ljava/lang/String;)Lorg/w3c/dom/Node;
│ │ +       244: ldc           #182                // String mojos
│ │ +       246: invokespecial #137                // Method getSingleChild:(Lorg/w3c/dom/Node;Ljava/lang/String;)Lorg/w3c/dom/Node;
│ │         249: astore        8
│ │         251: aload_0
│ │         252: aload         8
│ │ -       254: ldc           #47                 // String mojo
│ │ -       256: invokespecial #48                 // Method findNamedChild:(Lorg/w3c/dom/Node;Ljava/lang/String;)Ljava/util/List;
│ │ +       254: ldc           #184                // String mojo
│ │ +       256: invokespecial #188                // Method findNamedChild:(Lorg/w3c/dom/Node;Ljava/lang/String;)Ljava/util/List;
│ │         259: astore        9
│ │         261: aload_0
│ │ -       262: getfield      #49                 // Field goal:Ljava/lang/String;
│ │ +       262: getfield      #190                // Field goal:Ljava/lang/String;
│ │         265: ifnull        278
│ │         268: aload_0
│ │ -       269: getfield      #49                 // Field goal:Ljava/lang/String;
│ │ -       272: invokevirtual #50                 // Method java/lang/String.length:()I
│ │ +       269: getfield      #190                // Field goal:Ljava/lang/String;
│ │ +       272: invokevirtual #194                // Method java/lang/String.length:()I
│ │         275: ifgt          338
│ │         278: aload_0
│ │         279: aload_2
│ │ -       280: new           #27                 // class java/lang/StringBuilder
│ │ +       280: new           #130                // class java/lang/StringBuilder
│ │         283: dup
│ │ -       284: invokespecial #28                 // Method java/lang/StringBuilder."<init>":()V
│ │ -       287: ldc           #51                 // String This plugin has
│ │ -       289: invokevirtual #35                 // Method java/lang/StringBuilder.append:(Ljava/lang/String;)Ljava/lang/StringBuilder;
│ │ +       284: invokespecial #131                // Method java/lang/StringBuilder."<init>":()V
│ │ +       287: ldc           #198                // String This plugin has
│ │ +       289: invokevirtual #150                // Method java/lang/StringBuilder.append:(Ljava/lang/String;)Ljava/lang/StringBuilder;
│ │         292: aload         9
│ │ -       294: invokeinterface #52,  1           // InterfaceMethod java/util/List.size:()I
│ │ -       299: invokevirtual #53                 // Method java/lang/StringBuilder.append:(I)Ljava/lang/StringBuilder;
│ │ +       294: invokeinterface #201,  1          // InterfaceMethod java/util/List.size:()I
│ │ +       299: invokevirtual #204                // Method java/lang/StringBuilder.append:(I)Ljava/lang/StringBuilder;
│ │         302: aload         9
│ │ -       304: invokeinterface #52,  1           // InterfaceMethod java/util/List.size:()I
│ │ +       304: invokeinterface #201,  1          // InterfaceMethod java/util/List.size:()I
│ │         309: iconst_1
│ │         310: if_icmple     318
│ │ -       313: ldc           #54                 // String  goals:
│ │ +       313: ldc           #206                // String  goals:
│ │         315: goto          320
│ │ -       318: ldc           #55                 // String  goal:
│ │ -       320: invokevirtual #35                 // Method java/lang/StringBuilder.append:(Ljava/lang/String;)Ljava/lang/StringBuilder;
│ │ -       323: invokevirtual #38                 // Method java/lang/StringBuilder.toString:()Ljava/lang/String;
│ │ +       318: ldc           #208                // String  goal:
│ │ +       320: invokevirtual #150                // Method java/lang/StringBuilder.append:(Ljava/lang/String;)Ljava/lang/StringBuilder;
│ │ +       323: invokevirtual #157                // Method java/lang/StringBuilder.toString:()Ljava/lang/String;
│ │         326: iconst_0
│ │ -       327: invokespecial #42                 // Method append:(Ljava/lang/StringBuilder;Ljava/lang/String;I)V
│ │ +       327: invokespecial #172                // Method append:(Ljava/lang/StringBuilder;Ljava/lang/String;I)V
│ │         330: aload_0
│ │         331: aload_2
│ │ -       332: ldc           #44                 // String
│ │ +       332: ldc           #178                // String
│ │         334: iconst_0
│ │ -       335: invokespecial #42                 // Method append:(Ljava/lang/StringBuilder;Ljava/lang/String;I)V
│ │ +       335: invokespecial #172                // Method append:(Ljava/lang/StringBuilder;Ljava/lang/String;I)V
│ │         338: aload         9
│ │ -       340: invokeinterface #56,  1           // InterfaceMethod java/util/List.iterator:()Ljava/util/Iterator;
│ │ +       340: invokeinterface #212,  1          // InterfaceMethod java/util/List.iterator:()Ljava/util/Iterator;
│ │         345: astore        10
│ │         347: aload         10
│ │ -       349: invokeinterface #57,  1           // InterfaceMethod java/util/Iterator.hasNext:()Z
│ │ +       349: invokeinterface #218,  1          // InterfaceMethod java/util/Iterator.hasNext:()Z
│ │         354: ifeq          384
│ │         357: aload         10
│ │ -       359: invokeinterface #58,  1           // InterfaceMethod java/util/Iterator.next:()Ljava/lang/Object;
│ │ -       364: checkcast     #59                 // class org/w3c/dom/Node
│ │ +       359: invokeinterface #222,  1          // InterfaceMethod java/util/Iterator.next:()Ljava/lang/Object;
│ │ +       364: checkcast     #174                // class org/w3c/dom/Node
│ │         367: astore        11
│ │         369: aload_0
│ │         370: aload_2
│ │         371: aload         7
│ │         373: aload         11
│ │ -       375: checkcast     #60                 // class org/w3c/dom/Element
│ │ -       378: invokespecial #61                 // Method writeGoal:(Ljava/lang/StringBuilder;Ljava/lang/String;Lorg/w3c/dom/Element;)V
│ │ +       375: checkcast     #224                // class org/w3c/dom/Element
│ │ +       378: invokespecial #228                // Method writeGoal:(Ljava/lang/StringBuilder;Ljava/lang/String;Lorg/w3c/dom/Element;)V
│ │         381: goto          347
│ │         384: aload_0
│ │ -       385: invokevirtual #2                  // Method getLog:()Lorg/apache/maven/plugin/logging/Log;
│ │ -       388: invokeinterface #62,  1           // InterfaceMethod org/apache/maven/plugin/logging/Log.isInfoEnabled:()Z
│ │ +       385: invokevirtual #50                 // Method getLog:()Lorg/apache/maven/plugin/logging/Log;
│ │ +       388: invokeinterface #231,  1          // InterfaceMethod org/apache/maven/plugin/logging/Log.isInfoEnabled:()Z
│ │         393: ifeq          409
│ │         396: aload_0
│ │ -       397: invokevirtual #2                  // Method getLog:()Lorg/apache/maven/plugin/logging/Log;
│ │ +       397: invokevirtual #50                 // Method getLog:()Lorg/apache/maven/plugin/logging/Log;
│ │         400: aload_2
│ │ -       401: invokevirtual #38                 // Method java/lang/StringBuilder.toString:()Ljava/lang/String;
│ │ -       404: invokeinterface #63,  2           // InterfaceMethod org/apache/maven/plugin/logging/Log.info:(Ljava/lang/CharSequence;)V
│ │ +       401: invokevirtual #157                // Method java/lang/StringBuilder.toString:()Ljava/lang/String;
│ │ +       404: invokeinterface #234,  2          // InterfaceMethod org/apache/maven/plugin/logging/Log.info:(Ljava/lang/CharSequence;)V
│ │         409: return
│ │ -      LineNumberTable:
│ │ -        line 112: 0
│ │ -        line 114: 7
│ │ -        line 115: 18
│ │ -        line 117: 24
│ │ -        line 119: 31
│ │ -        line 120: 42
│ │ -        line 123: 47
│ │ -        line 125: 52
│ │ -        line 126: 60
│ │ -        line 129: 68
│ │ -        line 130: 77
│ │ -        line 131: 86
│ │ -        line 132: 133
│ │ -        line 134: 151
│ │ -        line 138: 185
│ │ -        line 140: 193
│ │ -        line 144: 204
│ │ -        line 147: 212
│ │ -        line 148: 225
│ │ -        line 151: 233
│ │ -        line 153: 242
│ │ -        line 155: 251
│ │ -        line 157: 261
│ │ -        line 159: 278
│ │ -        line 160: 330
│ │ -        line 163: 338
│ │ -        line 165: 369
│ │ -        line 166: 381
│ │ -        line 168: 384
│ │ -        line 170: 396
│ │ -        line 172: 409
│ │ -      LocalVariableTable:
│ │ -        Start  Length  Slot  Name   Signature
│ │ -          369      12    11  mojo   Lorg/w3c/dom/Node;
│ │ -            0     410     0  this   Lio/fabric8/maven/docker/HelpMojo;
│ │ -           52     358     1   doc   Lorg/w3c/dom/Document;
│ │ -           60     350     2    sb   Ljava/lang/StringBuilder;
│ │ -           68     342     3 plugin   Lorg/w3c/dom/Node;
│ │ -           77     333     4  name   Ljava/lang/String;
│ │ -           86     324     5 version   Ljava/lang/String;
│ │ -          133     277     6    id   Ljava/lang/String;
│ │ -          242     168     7 goalPrefix   Ljava/lang/String;
│ │ -          251     159     8 mojos1   Lorg/w3c/dom/Node;
│ │ -          261     149     9 mojos   Ljava/util/List;
│ │ -      LocalVariableTypeTable:
│ │ -        Start  Length  Slot  Name   Signature
│ │ -          261     149     9 mojos   Ljava/util/List<Lorg/w3c/dom/Node;>;
│ │        StackMapTable: number_of_entries = 12
│ │          frame_type = 24 /* same */
│ │          frame_type = 22 /* same */
│ │          frame_type = 255 /* full_frame */
│ │            offset_delta = 137
│ │            locals = [ class io/fabric8/maven/docker/HelpMojo, class org/w3c/dom/Document, class java/lang/StringBuilder, class org/w3c/dom/Node, class java/lang/String, class java/lang/String, class java/lang/String ]
│ │            stack = []
│ │ @@ -927,54 +879,102 @@
│ │          frame_type = 17 /* same */
│ │          frame_type = 252 /* append */
│ │            offset_delta = 8
│ │            locals = [ class java/util/Iterator ]
│ │          frame_type = 250 /* chop */
│ │            offset_delta = 36
│ │          frame_type = 24 /* same */
│ │ +      LineNumberTable:
│ │ +        line 111: 0
│ │ +        line 113: 7
│ │ +        line 114: 18
│ │ +        line 116: 24
│ │ +        line 118: 31
│ │ +        line 119: 42
│ │ +        line 122: 47
│ │ +        line 124: 52
│ │ +        line 125: 60
│ │ +        line 128: 68
│ │ +        line 129: 77
│ │ +        line 130: 86
│ │ +        line 131: 133
│ │ +        line 133: 151
│ │ +        line 137: 185
│ │ +        line 139: 193
│ │ +        line 143: 204
│ │ +        line 146: 212
│ │ +        line 147: 225
│ │ +        line 150: 233
│ │ +        line 152: 242
│ │ +        line 154: 251
│ │ +        line 156: 261
│ │ +        line 158: 278
│ │ +        line 159: 330
│ │ +        line 162: 338
│ │ +        line 164: 369
│ │ +        line 165: 381
│ │ +        line 167: 384
│ │ +        line 169: 396
│ │ +        line 171: 409
│ │ +      LocalVariableTable:
│ │ +        Start  Length  Slot  Name   Signature
│ │ +          369      12    11  mojo   Lorg/w3c/dom/Node;
│ │ +            0     410     0  this   Lio/fabric8/maven/docker/HelpMojo;
│ │ +           52     358     1   doc   Lorg/w3c/dom/Document;
│ │ +           60     350     2    sb   Ljava/lang/StringBuilder;
│ │ +           68     342     3 plugin   Lorg/w3c/dom/Node;
│ │ +           77     333     4  name   Ljava/lang/String;
│ │ +           86     324     5 version   Ljava/lang/String;
│ │ +          133     277     6    id   Ljava/lang/String;
│ │ +          242     168     7 goalPrefix   Ljava/lang/String;
│ │ +          251     159     8 mojos1   Lorg/w3c/dom/Node;
│ │ +          261     149     9 mojos   Ljava/util/List;
│ │ +      LocalVariableTypeTable:
│ │ +        Start  Length  Slot  Name   Signature
│ │ +          261     149     9 mojos   Ljava/util/List<Lorg/w3c/dom/Node;>;
│ │      Exceptions:
│ │        throws org.apache.maven.plugin.MojoExecutionException
│ │  
│ │    private static boolean isNotEmpty(java.lang.String);
│ │      descriptor: (Ljava/lang/String;)Z
│ │      flags: (0x000a) ACC_PRIVATE, ACC_STATIC
│ │      Code:
│ │        stack=1, locals=1, args_size=1
│ │           0: aload_0
│ │           1: ifnull        15
│ │           4: aload_0
│ │ -         5: invokevirtual #50                 // Method java/lang/String.length:()I
│ │ +         5: invokevirtual #194                // Method java/lang/String.length:()I
│ │           8: ifle          15
│ │          11: iconst_1
│ │          12: goto          16
│ │          15: iconst_0
│ │          16: ireturn
│ │ -      LineNumberTable:
│ │ -        line 177: 0
│ │ -      LocalVariableTable:
│ │ -        Start  Length  Slot  Name   Signature
│ │ -            0      17     0 string   Ljava/lang/String;
│ │        StackMapTable: number_of_entries = 2
│ │          frame_type = 15 /* same */
│ │          frame_type = 64 /* same_locals_1_stack_item */
│ │            stack = [ int ]
│ │ +      LineNumberTable:
│ │ +        line 176: 0
│ │ +      LocalVariableTable:
│ │ +        Start  Length  Slot  Name   Signature
│ │ +            0      17     0 string   Ljava/lang/String;
│ │  
│ │    private java.lang.String getValue(org.w3c.dom.Node, java.lang.String) throws org.apache.maven.plugin.MojoExecutionException;
│ │      descriptor: (Lorg/w3c/dom/Node;Ljava/lang/String;)Ljava/lang/String;
│ │      flags: (0x0002) ACC_PRIVATE
│ │      Code:
│ │        stack=3, locals=3, args_size=3
│ │           0: aload_0
│ │           1: aload_1
│ │           2: aload_2
│ │ -         3: invokespecial #30                 // Method getSingleChild:(Lorg/w3c/dom/Node;Ljava/lang/String;)Lorg/w3c/dom/Node;
│ │ -         6: invokeinterface #64,  1           // InterfaceMethod org/w3c/dom/Node.getTextContent:()Ljava/lang/String;
│ │ +         3: invokespecial #137                // Method getSingleChild:(Lorg/w3c/dom/Node;Ljava/lang/String;)Lorg/w3c/dom/Node;
│ │ +         6: invokeinterface #247,  1          // InterfaceMethod org/w3c/dom/Node.getTextContent:()Ljava/lang/String;
│ │          11: areturn
│ │        LineNumberTable:
│ │ -        line 183: 0
│ │ +        line 182: 0
│ │        LocalVariableTable:
│ │          Start  Length  Slot  Name   Signature
│ │              0      12     0  this   Lio/fabric8/maven/docker/HelpMojo;
│ │              0      12     1  node   Lorg/w3c/dom/Node;
│ │              0      12     2 elementName   Ljava/lang/String;
│ │      Exceptions:
│ │        throws org.apache.maven.plugin.MojoExecutionException
│ │ @@ -983,907 +983,870 @@
│ │      descriptor: (Lorg/w3c/dom/Node;Ljava/lang/String;)Lorg/w3c/dom/Node;
│ │      flags: (0x0002) ACC_PRIVATE
│ │      Code:
│ │        stack=4, locals=4, args_size=3
│ │           0: aload_0
│ │           1: aload_1
│ │           2: aload_2
│ │ -         3: invokespecial #48                 // Method findNamedChild:(Lorg/w3c/dom/Node;Ljava/lang/String;)Ljava/util/List;
│ │ +         3: invokespecial #188                // Method findNamedChild:(Lorg/w3c/dom/Node;Ljava/lang/String;)Ljava/util/List;
│ │           6: astore_3
│ │           7: aload_3
│ │ -         8: invokeinterface #65,  1           // InterfaceMethod java/util/List.isEmpty:()Z
│ │ -        13: ifeq          48
│ │ -        16: new           #14                 // class org/apache/maven/plugin/MojoExecutionException
│ │ +         8: invokeinterface #252,  1          // InterfaceMethod java/util/List.isEmpty:()Z
│ │ +        13: ifeq          49
│ │ +        16: new           #40                 // class org/apache/maven/plugin/MojoExecutionException
│ │          19: dup
│ │ -        20: new           #27                 // class java/lang/StringBuilder
│ │ +        20: new           #130                // class java/lang/StringBuilder
│ │          23: dup
│ │ -        24: invokespecial #28                 // Method java/lang/StringBuilder."<init>":()V
│ │ -        27: ldc           #66                 // String Could not find
│ │ -        29: invokevirtual #35                 // Method java/lang/StringBuilder.append:(Ljava/lang/String;)Ljava/lang/StringBuilder;
│ │ +        24: invokespecial #131                // Method java/lang/StringBuilder."<init>":()V
│ │ +        27: ldc           #254                // String Could not find
│ │ +        29: invokevirtual #150                // Method java/lang/StringBuilder.append:(Ljava/lang/String;)Ljava/lang/StringBuilder;
│ │          32: aload_2
│ │ -        33: invokevirtual #35                 // Method java/lang/StringBuilder.append:(Ljava/lang/String;)Ljava/lang/StringBuilder;
│ │ -        36: ldc           #67                 // String  in plugin-help.xml
│ │ -        38: invokevirtual #35                 // Method java/lang/StringBuilder.append:(Ljava/lang/String;)Ljava/lang/StringBuilder;
│ │ -        41: invokevirtual #38                 // Method java/lang/StringBuilder.toString:()Ljava/lang/String;
│ │ -        44: invokespecial #68                 // Method org/apache/maven/plugin/MojoExecutionException."<init>":(Ljava/lang/String;)V
│ │ -        47: athrow
│ │ -        48: aload_3
│ │ -        49: invokeinterface #52,  1           // InterfaceMethod java/util/List.size:()I
│ │ -        54: iconst_1
│ │ -        55: if_icmple     90
│ │ -        58: new           #14                 // class org/apache/maven/plugin/MojoExecutionException
│ │ -        61: dup
│ │ -        62: new           #27                 // class java/lang/StringBuilder
│ │ -        65: dup
│ │ -        66: invokespecial #28                 // Method java/lang/StringBuilder."<init>":()V
│ │ -        69: ldc           #69                 // String Multiple
│ │ -        71: invokevirtual #35                 // Method java/lang/StringBuilder.append:(Ljava/lang/String;)Ljava/lang/StringBuilder;
│ │ -        74: aload_2
│ │ -        75: invokevirtual #35                 // Method java/lang/StringBuilder.append:(Ljava/lang/String;)Ljava/lang/StringBuilder;
│ │ -        78: ldc           #67                 // String  in plugin-help.xml
│ │ -        80: invokevirtual #35                 // Method java/lang/StringBuilder.append:(Ljava/lang/String;)Ljava/lang/StringBuilder;
│ │ -        83: invokevirtual #38                 // Method java/lang/StringBuilder.toString:()Ljava/lang/String;
│ │ -        86: invokespecial #68                 // Method org/apache/maven/plugin/MojoExecutionException."<init>":(Ljava/lang/String;)V
│ │ -        89: athrow
│ │ -        90: aload_3
│ │ -        91: iconst_0
│ │ -        92: invokeinterface #70,  2           // InterfaceMethod java/util/List.get:(I)Ljava/lang/Object;
│ │ -        97: checkcast     #59                 // class org/w3c/dom/Node
│ │ -       100: areturn
│ │ +        33: invokevirtual #150                // Method java/lang/StringBuilder.append:(Ljava/lang/String;)Ljava/lang/StringBuilder;
│ │ +        36: ldc_w         #256                // String  in plugin-help.xml
│ │ +        39: invokevirtual #150                // Method java/lang/StringBuilder.append:(Ljava/lang/String;)Ljava/lang/StringBuilder;
│ │ +        42: invokevirtual #157                // Method java/lang/StringBuilder.toString:()Ljava/lang/String;
│ │ +        45: invokespecial #259                // Method org/apache/maven/plugin/MojoExecutionException."<init>":(Ljava/lang/String;)V
│ │ +        48: athrow
│ │ +        49: aload_3
│ │ +        50: invokeinterface #201,  1          // InterfaceMethod java/util/List.size:()I
│ │ +        55: iconst_1
│ │ +        56: if_icmple     93
│ │ +        59: new           #40                 // class org/apache/maven/plugin/MojoExecutionException
│ │ +        62: dup
│ │ +        63: new           #130                // class java/lang/StringBuilder
│ │ +        66: dup
│ │ +        67: invokespecial #131                // Method java/lang/StringBuilder."<init>":()V
│ │ +        70: ldc_w         #261                // String Multiple
│ │ +        73: invokevirtual #150                // Method java/lang/StringBuilder.append:(Ljava/lang/String;)Ljava/lang/StringBuilder;
│ │ +        76: aload_2
│ │ +        77: invokevirtual #150                // Method java/lang/StringBuilder.append:(Ljava/lang/String;)Ljava/lang/StringBuilder;
│ │ +        80: ldc_w         #256                // String  in plugin-help.xml
│ │ +        83: invokevirtual #150                // Method java/lang/StringBuilder.append:(Ljava/lang/String;)Ljava/lang/StringBuilder;
│ │ +        86: invokevirtual #157                // Method java/lang/StringBuilder.toString:()Ljava/lang/String;
│ │ +        89: invokespecial #259                // Method org/apache/maven/plugin/MojoExecutionException."<init>":(Ljava/lang/String;)V
│ │ +        92: athrow
│ │ +        93: aload_3
│ │ +        94: iconst_0
│ │ +        95: invokeinterface #265,  2          // InterfaceMethod java/util/List.get:(I)Ljava/lang/Object;
│ │ +       100: checkcast     #174                // class org/w3c/dom/Node
│ │ +       103: areturn
│ │ +      StackMapTable: number_of_entries = 2
│ │ +        frame_type = 252 /* append */
│ │ +          offset_delta = 49
│ │ +          locals = [ class java/util/List ]
│ │ +        frame_type = 43 /* same */
│ │        LineNumberTable:
│ │ -        line 189: 0
│ │ -        line 190: 7
│ │ -        line 192: 16
│ │ -        line 194: 48
│ │ -        line 196: 58
│ │ -        line 198: 90
│ │ +        line 188: 0
│ │ +        line 189: 7
│ │ +        line 191: 16
│ │ +        line 193: 49
│ │ +        line 195: 59
│ │ +        line 197: 93
│ │        LocalVariableTable:
│ │          Start  Length  Slot  Name   Signature
│ │ -            0     101     0  this   Lio/fabric8/maven/docker/HelpMojo;
│ │ -            0     101     1  node   Lorg/w3c/dom/Node;
│ │ -            0     101     2 elementName   Ljava/lang/String;
│ │ -            7      94     3 namedChild   Ljava/util/List;
│ │ +            0     104     0  this   Lio/fabric8/maven/docker/HelpMojo;
│ │ +            0     104     1  node   Lorg/w3c/dom/Node;
│ │ +            0     104     2 elementName   Ljava/lang/String;
│ │ +            7      97     3 namedChild   Ljava/util/List;
│ │        LocalVariableTypeTable:
│ │          Start  Length  Slot  Name   Signature
│ │ -            7      94     3 namedChild   Ljava/util/List<Lorg/w3c/dom/Node;>;
│ │ -      StackMapTable: number_of_entries = 2
│ │ -        frame_type = 252 /* append */
│ │ -          offset_delta = 48
│ │ -          locals = [ class java/util/List ]
│ │ -        frame_type = 41 /* same */
│ │ +            7      97     3 namedChild   Ljava/util/List<Lorg/w3c/dom/Node;>;
│ │      Exceptions:
│ │        throws org.apache.maven.plugin.MojoExecutionException
│ │  
│ │    private java.util.List<org.w3c.dom.Node> findNamedChild(org.w3c.dom.Node, java.lang.String);
│ │      descriptor: (Lorg/w3c/dom/Node;Ljava/lang/String;)Ljava/util/List;
│ │      flags: (0x0002) ACC_PRIVATE
│ │      Code:
│ │        stack=2, locals=7, args_size=3
│ │ -         0: new           #71                 // class java/util/ArrayList
│ │ +         0: new           #269                // class java/util/ArrayList
│ │           3: dup
│ │ -         4: invokespecial #72                 // Method java/util/ArrayList."<init>":()V
│ │ +         4: invokespecial #270                // Method java/util/ArrayList."<init>":()V
│ │           7: astore_3
│ │           8: aload_1
│ │ -         9: invokeinterface #73,  1           // InterfaceMethod org/w3c/dom/Node.getChildNodes:()Lorg/w3c/dom/NodeList;
│ │ +         9: invokeinterface #274,  1          // InterfaceMethod org/w3c/dom/Node.getChildNodes:()Lorg/w3c/dom/NodeList;
│ │          14: astore        4
│ │          16: iconst_0
│ │          17: istore        5
│ │          19: iload         5
│ │          21: aload         4
│ │ -        23: invokeinterface #74,  1           // InterfaceMethod org/w3c/dom/NodeList.getLength:()I
│ │ +        23: invokeinterface #279,  1          // InterfaceMethod org/w3c/dom/NodeList.getLength:()I
│ │          28: if_icmpge     71
│ │          31: aload         4
│ │          33: iload         5
│ │ -        35: invokeinterface #75,  2           // InterfaceMethod org/w3c/dom/NodeList.item:(I)Lorg/w3c/dom/Node;
│ │ +        35: invokeinterface #283,  2          // InterfaceMethod org/w3c/dom/NodeList.item:(I)Lorg/w3c/dom/Node;
│ │          40: astore        6
│ │          42: aload_2
│ │          43: aload         6
│ │ -        45: invokeinterface #76,  1           // InterfaceMethod org/w3c/dom/Node.getNodeName:()Ljava/lang/String;
│ │ -        50: invokevirtual #77                 // Method java/lang/String.equals:(Ljava/lang/Object;)Z
│ │ +        45: invokeinterface #286,  1          // InterfaceMethod org/w3c/dom/Node.getNodeName:()Ljava/lang/String;
│ │ +        50: invokevirtual #290                // Method java/lang/String.equals:(Ljava/lang/Object;)Z
│ │          53: ifeq          65
│ │          56: aload_3
│ │          57: aload         6
│ │ -        59: invokeinterface #78,  2           // InterfaceMethod java/util/List.add:(Ljava/lang/Object;)Z
│ │ +        59: invokeinterface #293,  2          // InterfaceMethod java/util/List.add:(Ljava/lang/Object;)Z
│ │          64: pop
│ │          65: iinc          5, 1
│ │          68: goto          19
│ │          71: aload_3
│ │          72: areturn
│ │ +      StackMapTable: number_of_entries = 3
│ │ +        frame_type = 254 /* append */
│ │ +          offset_delta = 19
│ │ +          locals = [ class java/util/List, class org/w3c/dom/NodeList, int ]
│ │ +        frame_type = 45 /* same */
│ │ +        frame_type = 250 /* chop */
│ │ +          offset_delta = 5
│ │        LineNumberTable:
│ │ -        line 203: 0
│ │ -        line 204: 8
│ │ -        line 205: 16
│ │ -        line 207: 31
│ │ -        line 208: 42
│ │ -        line 210: 56
│ │ -        line 205: 65
│ │ -        line 213: 71
│ │ +        line 202: 0
│ │ +        line 203: 8
│ │ +        line 204: 16
│ │ +        line 206: 31
│ │ +        line 207: 42
│ │ +        line 209: 56
│ │ +        line 204: 65
│ │ +        line 212: 71
│ │        LocalVariableTable:
│ │          Start  Length  Slot  Name   Signature
│ │             42      23     6  item   Lorg/w3c/dom/Node;
│ │             19      52     5     i   I
│ │              0      73     0  this   Lio/fabric8/maven/docker/HelpMojo;
│ │              0      73     1  node   Lorg/w3c/dom/Node;
│ │              0      73     2 elementName   Ljava/lang/String;
│ │              8      65     3 result   Ljava/util/List;
│ │             16      57     4 childNodes   Lorg/w3c/dom/NodeList;
│ │        LocalVariableTypeTable:
│ │          Start  Length  Slot  Name   Signature
│ │              8      65     3 result   Ljava/util/List<Lorg/w3c/dom/Node;>;
│ │ -      StackMapTable: number_of_entries = 3
│ │ -        frame_type = 254 /* append */
│ │ -          offset_delta = 19
│ │ -          locals = [ class java/util/List, class org/w3c/dom/NodeList, int ]
│ │ -        frame_type = 45 /* same */
│ │ -        frame_type = 250 /* chop */
│ │ -          offset_delta = 5
│ │ -    Signature: #204                         // (Lorg/w3c/dom/Node;Ljava/lang/String;)Ljava/util/List<Lorg/w3c/dom/Node;>;
│ │ +    Signature: #267                         // (Lorg/w3c/dom/Node;Ljava/lang/String;)Ljava/util/List<Lorg/w3c/dom/Node;>;
│ │  
│ │    private org.w3c.dom.Node findSingleChild(org.w3c.dom.Node, java.lang.String) throws org.apache.maven.plugin.MojoExecutionException;
│ │      descriptor: (Lorg/w3c/dom/Node;Ljava/lang/String;)Lorg/w3c/dom/Node;
│ │      flags: (0x0002) ACC_PRIVATE
│ │      Code:
│ │        stack=4, locals=4, args_size=3
│ │           0: aload_0
│ │           1: aload_1
│ │           2: aload_2
│ │ -         3: invokespecial #48                 // Method findNamedChild:(Lorg/w3c/dom/Node;Ljava/lang/String;)Ljava/util/List;
│ │ +         3: invokespecial #188                // Method findNamedChild:(Lorg/w3c/dom/Node;Ljava/lang/String;)Ljava/util/List;
│ │           6: astore_3
│ │           7: aload_3
│ │ -         8: invokeinterface #65,  1           // InterfaceMethod java/util/List.isEmpty:()Z
│ │ +         8: invokeinterface #252,  1          // InterfaceMethod java/util/List.isEmpty:()Z
│ │          13: ifeq          18
│ │          16: aconst_null
│ │          17: areturn
│ │          18: aload_3
│ │ -        19: invokeinterface #52,  1           // InterfaceMethod java/util/List.size:()I
│ │ +        19: invokeinterface #201,  1          // InterfaceMethod java/util/List.size:()I
│ │          24: iconst_1
│ │ -        25: if_icmple     60
│ │ -        28: new           #14                 // class org/apache/maven/plugin/MojoExecutionException
│ │ +        25: if_icmple     62
│ │ +        28: new           #40                 // class org/apache/maven/plugin/MojoExecutionException
│ │          31: dup
│ │ -        32: new           #27                 // class java/lang/StringBuilder
│ │ +        32: new           #130                // class java/lang/StringBuilder
│ │          35: dup
│ │ -        36: invokespecial #28                 // Method java/lang/StringBuilder."<init>":()V
│ │ -        39: ldc           #69                 // String Multiple
│ │ -        41: invokevirtual #35                 // Method java/lang/StringBuilder.append:(Ljava/lang/String;)Ljava/lang/StringBuilder;
│ │ -        44: aload_2
│ │ -        45: invokevirtual #35                 // Method java/lang/StringBuilder.append:(Ljava/lang/String;)Ljava/lang/StringBuilder;
│ │ -        48: ldc           #79                 // String in plugin-help.xml
│ │ -        50: invokevirtual #35                 // Method java/lang/StringBuilder.append:(Ljava/lang/String;)Ljava/lang/StringBuilder;
│ │ -        53: invokevirtual #38                 // Method java/lang/StringBuilder.toString:()Ljava/lang/String;
│ │ -        56: invokespecial #68                 // Method org/apache/maven/plugin/MojoExecutionException."<init>":(Ljava/lang/String;)V
│ │ -        59: athrow
│ │ -        60: aload_3
│ │ -        61: iconst_0
│ │ -        62: invokeinterface #70,  2           // InterfaceMethod java/util/List.get:(I)Ljava/lang/Object;
│ │ -        67: checkcast     #59                 // class org/w3c/dom/Node
│ │ -        70: areturn
│ │ +        36: invokespecial #131                // Method java/lang/StringBuilder."<init>":()V
│ │ +        39: ldc_w         #261                // String Multiple
│ │ +        42: invokevirtual #150                // Method java/lang/StringBuilder.append:(Ljava/lang/String;)Ljava/lang/StringBuilder;
│ │ +        45: aload_2
│ │ +        46: invokevirtual #150                // Method java/lang/StringBuilder.append:(Ljava/lang/String;)Ljava/lang/StringBuilder;
│ │ +        49: ldc_w         #300                // String in plugin-help.xml
│ │ +        52: invokevirtual #150                // Method java/lang/StringBuilder.append:(Ljava/lang/String;)Ljava/lang/StringBuilder;
│ │ +        55: invokevirtual #157                // Method java/lang/StringBuilder.toString:()Ljava/lang/String;
│ │ +        58: invokespecial #259                // Method org/apache/maven/plugin/MojoExecutionException."<init>":(Ljava/lang/String;)V
│ │ +        61: athrow
│ │ +        62: aload_3
│ │ +        63: iconst_0
│ │ +        64: invokeinterface #265,  2          // InterfaceMethod java/util/List.get:(I)Ljava/lang/Object;
│ │ +        69: checkcast     #174                // class org/w3c/dom/Node
│ │ +        72: areturn
│ │ +      StackMapTable: number_of_entries = 2
│ │ +        frame_type = 252 /* append */
│ │ +          offset_delta = 18
│ │ +          locals = [ class java/util/List ]
│ │ +        frame_type = 43 /* same */
│ │        LineNumberTable:
│ │ -        line 219: 0
│ │ -        line 220: 7
│ │ -        line 222: 16
│ │ -        line 224: 18
│ │ -        line 226: 28
│ │ -        line 228: 60
│ │ +        line 218: 0
│ │ +        line 219: 7
│ │ +        line 221: 16
│ │ +        line 223: 18
│ │ +        line 225: 28
│ │ +        line 227: 62
│ │        LocalVariableTable:
│ │          Start  Length  Slot  Name   Signature
│ │ -            0      71     0  this   Lio/fabric8/maven/docker/HelpMojo;
│ │ -            0      71     1  node   Lorg/w3c/dom/Node;
│ │ -            0      71     2 elementName   Ljava/lang/String;
│ │ -            7      64     3 elementsByTagName   Ljava/util/List;
│ │ +            0      73     0  this   Lio/fabric8/maven/docker/HelpMojo;
│ │ +            0      73     1  node   Lorg/w3c/dom/Node;
│ │ +            0      73     2 elementName   Ljava/lang/String;
│ │ +            7      66     3 elementsByTagName   Ljava/util/List;
│ │        LocalVariableTypeTable:
│ │          Start  Length  Slot  Name   Signature
│ │ -            7      64     3 elementsByTagName   Ljava/util/List<Lorg/w3c/dom/Node;>;
│ │ -      StackMapTable: number_of_entries = 2
│ │ -        frame_type = 252 /* append */
│ │ -          offset_delta = 18
│ │ -          locals = [ class java/util/List ]
│ │ -        frame_type = 41 /* same */
│ │ +            7      66     3 elementsByTagName   Ljava/util/List<Lorg/w3c/dom/Node;>;
│ │      Exceptions:
│ │        throws org.apache.maven.plugin.MojoExecutionException
│ │  
│ │    private void writeGoal(java.lang.StringBuilder, java.lang.String, org.w3c.dom.Element) throws org.apache.maven.plugin.MojoExecutionException;
│ │      descriptor: (Ljava/lang/StringBuilder;Ljava/lang/String;Lorg/w3c/dom/Element;)V
│ │      flags: (0x0002) ACC_PRIVATE
│ │      Code:
│ │        stack=4, locals=12, args_size=4
│ │           0: aload_0
│ │           1: aload_3
│ │ -         2: ldc           #80                 // String goal
│ │ -         4: invokespecial #32                 // Method getValue:(Lorg/w3c/dom/Node;Ljava/lang/String;)Ljava/lang/String;
│ │ -         7: astore        4
│ │ -         9: aload_0
│ │ -        10: aload_3
│ │ -        11: ldc           #81                 // String configuration
│ │ -        13: invokespecial #82                 // Method findSingleChild:(Lorg/w3c/dom/Node;Ljava/lang/String;)Lorg/w3c/dom/Node;
│ │ -        16: astore        5
│ │ -        18: aload_0
│ │ -        19: aload_3
│ │ -        20: ldc           #43                 // String description
│ │ -        22: invokespecial #82                 // Method findSingleChild:(Lorg/w3c/dom/Node;Ljava/lang/String;)Lorg/w3c/dom/Node;
│ │ -        25: astore        6
│ │ -        27: aload_0
│ │ -        28: getfield      #49                 // Field goal:Ljava/lang/String;
│ │ -        31: ifnull        56
│ │ -        34: aload_0
│ │ -        35: getfield      #49                 // Field goal:Ljava/lang/String;
│ │ -        38: invokevirtual #50                 // Method java/lang/String.length:()I
│ │ -        41: ifle          56
│ │ -        44: aload         4
│ │ -        46: aload_0
│ │ -        47: getfield      #49                 // Field goal:Ljava/lang/String;
│ │ -        50: invokevirtual #77                 // Method java/lang/String.equals:(Ljava/lang/Object;)Z
│ │ -        53: ifeq          291
│ │ -        56: aload_0
│ │ -        57: aload_1
│ │ -        58: new           #27                 // class java/lang/StringBuilder
│ │ -        61: dup
│ │ -        62: invokespecial #28                 // Method java/lang/StringBuilder."<init>":()V
│ │ -        65: aload_2
│ │ -        66: invokevirtual #35                 // Method java/lang/StringBuilder.append:(Ljava/lang/String;)Ljava/lang/StringBuilder;
│ │ -        69: ldc           #36                 // String :
│ │ -        71: invokevirtual #35                 // Method java/lang/StringBuilder.append:(Ljava/lang/String;)Ljava/lang/StringBuilder;
│ │ -        74: aload         4
│ │ -        76: invokevirtual #35                 // Method java/lang/StringBuilder.append:(Ljava/lang/String;)Ljava/lang/StringBuilder;
│ │ -        79: invokevirtual #38                 // Method java/lang/StringBuilder.toString:()Ljava/lang/String;
│ │ -        82: iconst_0
│ │ -        83: invokespecial #42                 // Method append:(Ljava/lang/StringBuilder;Ljava/lang/String;I)V
│ │ -        86: aload_0
│ │ -        87: aload_3
│ │ -        88: ldc           #83                 // String deprecated
│ │ -        90: invokespecial #82                 // Method findSingleChild:(Lorg/w3c/dom/Node;Ljava/lang/String;)Lorg/w3c/dom/Node;
│ │ -        93: astore        7
│ │ -        95: aload         7
│ │ -        97: ifnull        180
│ │ -       100: aload         7
│ │ -       102: invokeinterface #64,  1           // InterfaceMethod org/w3c/dom/Node.getTextContent:()Ljava/lang/String;
│ │ -       107: invokestatic  #39                 // Method isNotEmpty:(Ljava/lang/String;)Z
│ │ -       110: ifeq          180
│ │ -       113: aload_0
│ │ -       114: aload_1
│ │ -       115: new           #27                 // class java/lang/StringBuilder
│ │ -       118: dup
│ │ -       119: invokespecial #28                 // Method java/lang/StringBuilder."<init>":()V
│ │ -       122: ldc           #84                 // String Deprecated.
│ │ -       124: invokevirtual #35                 // Method java/lang/StringBuilder.append:(Ljava/lang/String;)Ljava/lang/StringBuilder;
│ │ -       127: aload         7
│ │ -       129: invokeinterface #64,  1           // InterfaceMethod org/w3c/dom/Node.getTextContent:()Ljava/lang/String;
│ │ -       134: invokevirtual #35                 // Method java/lang/StringBuilder.append:(Ljava/lang/String;)Ljava/lang/StringBuilder;
│ │ -       137: invokevirtual #38                 // Method java/lang/StringBuilder.toString:()Ljava/lang/String;
│ │ -       140: iconst_1
│ │ -       141: invokespecial #42                 // Method append:(Ljava/lang/StringBuilder;Ljava/lang/String;I)V
│ │ -       144: aload_0
│ │ -       145: getfield      #85                 // Field detail:Z
│ │ -       148: ifeq          198
│ │ -       151: aload         6
│ │ -       153: ifnull        198
│ │ -       156: aload_0
│ │ -       157: aload_1
│ │ -       158: ldc           #44                 // String
│ │ -       160: iconst_0
│ │ -       161: invokespecial #42                 // Method append:(Ljava/lang/StringBuilder;Ljava/lang/String;I)V
│ │ -       164: aload_0
│ │ -       165: aload_1
│ │ -       166: aload         6
│ │ -       168: invokeinterface #64,  1           // InterfaceMethod org/w3c/dom/Node.getTextContent:()Ljava/lang/String;
│ │ -       173: iconst_1
│ │ -       174: invokespecial #42                 // Method append:(Ljava/lang/StringBuilder;Ljava/lang/String;I)V
│ │ -       177: goto          198
│ │ -       180: aload         6
│ │ -       182: ifnull        198
│ │ -       185: aload_0
│ │ -       186: aload_1
│ │ -       187: aload         6
│ │ -       189: invokeinterface #64,  1           // InterfaceMethod org/w3c/dom/Node.getTextContent:()Ljava/lang/String;
│ │ -       194: iconst_1
│ │ -       195: invokespecial #42                 // Method append:(Ljava/lang/StringBuilder;Ljava/lang/String;I)V
│ │ -       198: aload_0
│ │ -       199: aload_1
│ │ -       200: ldc           #44                 // String
│ │ -       202: iconst_0
│ │ -       203: invokespecial #42                 // Method append:(Ljava/lang/StringBuilder;Ljava/lang/String;I)V
│ │ -       206: aload_0
│ │ -       207: getfield      #85                 // Field detail:Z
│ │ -       210: ifeq          291
│ │ -       213: aload_0
│ │ -       214: aload_3
│ │ -       215: ldc           #86                 // String parameters
│ │ -       217: invokespecial #30                 // Method getSingleChild:(Lorg/w3c/dom/Node;Ljava/lang/String;)Lorg/w3c/dom/Node;
│ │ -       220: astore        8
│ │ -       222: aload_0
│ │ -       223: aload         8
│ │ -       225: ldc           #87                 // String parameter
│ │ -       227: invokespecial #48                 // Method findNamedChild:(Lorg/w3c/dom/Node;Ljava/lang/String;)Ljava/util/List;
│ │ -       230: astore        9
│ │ -       232: aload_0
│ │ -       233: aload_1
│ │ -       234: ldc           #88                 // String Available parameters:
│ │ -       236: iconst_1
│ │ -       237: invokespecial #42                 // Method append:(Ljava/lang/StringBuilder;Ljava/lang/String;I)V
│ │ -       240: aload_0
│ │ -       241: aload_1
│ │ -       242: ldc           #44                 // String
│ │ -       244: iconst_0
│ │ -       245: invokespecial #42                 // Method append:(Ljava/lang/StringBuilder;Ljava/lang/String;I)V
│ │ -       248: aload         9
│ │ -       250: invokeinterface #56,  1           // InterfaceMethod java/util/List.iterator:()Ljava/util/Iterator;
│ │ -       255: astore        10
│ │ -       257: aload         10
│ │ -       259: invokeinterface #57,  1           // InterfaceMethod java/util/Iterator.hasNext:()Z
│ │ -       264: ifeq          291
│ │ -       267: aload         10
│ │ -       269: invokeinterface #58,  1           // InterfaceMethod java/util/Iterator.next:()Ljava/lang/Object;
│ │ -       274: checkcast     #59                 // class org/w3c/dom/Node
│ │ -       277: astore        11
│ │ -       279: aload_0
│ │ -       280: aload_1
│ │ -       281: aload         11
│ │ -       283: aload         5
│ │ -       285: invokespecial #89                 // Method writeParameter:(Ljava/lang/StringBuilder;Lorg/w3c/dom/Node;Lorg/w3c/dom/Node;)V
│ │ -       288: goto          257
│ │ -       291: return
│ │ -      LineNumberTable:
│ │ -        line 234: 0
│ │ -        line 235: 9
│ │ -        line 236: 18
│ │ -        line 237: 27
│ │ -        line 239: 56
│ │ -        line 240: 86
│ │ -        line 241: 95
│ │ -        line 243: 113
│ │ -        line 244: 144
│ │ -        line 246: 156
│ │ -        line 247: 164
│ │ -        line 250: 180
│ │ -        line 252: 185
│ │ -        line 254: 198
│ │ -        line 256: 206
│ │ -        line 258: 213
│ │ -        line 259: 222
│ │ -        line 260: 232
│ │ -        line 261: 240
│ │ -        line 263: 248
│ │ -        line 265: 279
│ │ -        line 266: 288
│ │ -        line 269: 291
│ │ -      LocalVariableTable:
│ │ -        Start  Length  Slot  Name   Signature
│ │ -          279       9    11 parameter   Lorg/w3c/dom/Node;
│ │ -          222      69     8 parametersNode   Lorg/w3c/dom/Node;
│ │ -          232      59     9 parameters   Ljava/util/List;
│ │ -           95     196     7 deprecated   Lorg/w3c/dom/Node;
│ │ -            0     292     0  this   Lio/fabric8/maven/docker/HelpMojo;
│ │ -            0     292     1    sb   Ljava/lang/StringBuilder;
│ │ -            0     292     2 goalPrefix   Ljava/lang/String;
│ │ -            0     292     3  mojo   Lorg/w3c/dom/Element;
│ │ -            9     283     4 mojoGoal   Ljava/lang/String;
│ │ -           18     274     5 configurationElement   Lorg/w3c/dom/Node;
│ │ -           27     265     6 description   Lorg/w3c/dom/Node;
│ │ -      LocalVariableTypeTable:
│ │ -        Start  Length  Slot  Name   Signature
│ │ -          232      59     9 parameters   Ljava/util/List<Lorg/w3c/dom/Node;>;
│ │ +         2: ldc_w         #302                // String goal
│ │ +         5: invokespecial #142                // Method getValue:(Lorg/w3c/dom/Node;Ljava/lang/String;)Ljava/lang/String;
│ │ +         8: astore        4
│ │ +        10: aload_0
│ │ +        11: aload_3
│ │ +        12: ldc_w         #304                // String configuration
│ │ +        15: invokespecial #306                // Method findSingleChild:(Lorg/w3c/dom/Node;Ljava/lang/String;)Lorg/w3c/dom/Node;
│ │ +        18: astore        5
│ │ +        20: aload_0
│ │ +        21: aload_3
│ │ +        22: ldc           #176                // String description
│ │ +        24: invokespecial #306                // Method findSingleChild:(Lorg/w3c/dom/Node;Ljava/lang/String;)Lorg/w3c/dom/Node;
│ │ +        27: astore        6
│ │ +        29: aload_0
│ │ +        30: getfield      #190                // Field goal:Ljava/lang/String;
│ │ +        33: ifnull        58
│ │ +        36: aload_0
│ │ +        37: getfield      #190                // Field goal:Ljava/lang/String;
│ │ +        40: invokevirtual #194                // Method java/lang/String.length:()I
│ │ +        43: ifle          58
│ │ +        46: aload         4
│ │ +        48: aload_0
│ │ +        49: getfield      #190                // Field goal:Ljava/lang/String;
│ │ +        52: invokevirtual #290                // Method java/lang/String.equals:(Ljava/lang/Object;)Z
│ │ +        55: ifeq          298
│ │ +        58: aload_0
│ │ +        59: aload_1
│ │ +        60: new           #130                // class java/lang/StringBuilder
│ │ +        63: dup
│ │ +        64: invokespecial #131                // Method java/lang/StringBuilder."<init>":()V
│ │ +        67: aload_2
│ │ +        68: invokevirtual #150                // Method java/lang/StringBuilder.append:(Ljava/lang/String;)Ljava/lang/StringBuilder;
│ │ +        71: ldc           #152                // String :
│ │ +        73: invokevirtual #150                // Method java/lang/StringBuilder.append:(Ljava/lang/String;)Ljava/lang/StringBuilder;
│ │ +        76: aload         4
│ │ +        78: invokevirtual #150                // Method java/lang/StringBuilder.append:(Ljava/lang/String;)Ljava/lang/StringBuilder;
│ │ +        81: invokevirtual #157                // Method java/lang/StringBuilder.toString:()Ljava/lang/String;
│ │ +        84: iconst_0
│ │ +        85: invokespecial #172                // Method append:(Ljava/lang/StringBuilder;Ljava/lang/String;I)V
│ │ +        88: aload_0
│ │ +        89: aload_3
│ │ +        90: ldc_w         #308                // String deprecated
│ │ +        93: invokespecial #306                // Method findSingleChild:(Lorg/w3c/dom/Node;Ljava/lang/String;)Lorg/w3c/dom/Node;
│ │ +        96: astore        7
│ │ +        98: aload         7
│ │ +       100: ifnull        184
│ │ +       103: aload         7
│ │ +       105: invokeinterface #247,  1          // InterfaceMethod org/w3c/dom/Node.getTextContent:()Ljava/lang/String;
│ │ +       110: invokestatic  #161                // Method isNotEmpty:(Ljava/lang/String;)Z
│ │ +       113: ifeq          184
│ │ +       116: aload_0
│ │ +       117: aload_1
│ │ +       118: new           #130                // class java/lang/StringBuilder
│ │ +       121: dup
│ │ +       122: invokespecial #131                // Method java/lang/StringBuilder."<init>":()V
│ │ +       125: ldc_w         #310                // String Deprecated.
│ │ +       128: invokevirtual #150                // Method java/lang/StringBuilder.append:(Ljava/lang/String;)Ljava/lang/StringBuilder;
│ │ +       131: aload         7
│ │ +       133: invokeinterface #247,  1          // InterfaceMethod org/w3c/dom/Node.getTextContent:()Ljava/lang/String;
│ │ +       138: invokevirtual #150                // Method java/lang/StringBuilder.append:(Ljava/lang/String;)Ljava/lang/StringBuilder;
│ │ +       141: invokevirtual #157                // Method java/lang/StringBuilder.toString:()Ljava/lang/String;
│ │ +       144: iconst_1
│ │ +       145: invokespecial #172                // Method append:(Ljava/lang/StringBuilder;Ljava/lang/String;I)V
│ │ +       148: aload_0
│ │ +       149: getfield      #312                // Field detail:Z
│ │ +       152: ifeq          202
│ │ +       155: aload         6
│ │ +       157: ifnull        202
│ │ +       160: aload_0
│ │ +       161: aload_1
│ │ +       162: ldc           #178                // String
│ │ +       164: iconst_0
│ │ +       165: invokespecial #172                // Method append:(Ljava/lang/StringBuilder;Ljava/lang/String;I)V
│ │ +       168: aload_0
│ │ +       169: aload_1
│ │ +       170: aload         6
│ │ +       172: invokeinterface #247,  1          // InterfaceMethod org/w3c/dom/Node.getTextContent:()Ljava/lang/String;
│ │ +       177: iconst_1
│ │ +       178: invokespecial #172                // Method append:(Ljava/lang/StringBuilder;Ljava/lang/String;I)V
│ │ +       181: goto          202
│ │ +       184: aload         6
│ │ +       186: ifnull        202
│ │ +       189: aload_0
│ │ +       190: aload_1
│ │ +       191: aload         6
│ │ +       193: invokeinterface #247,  1          // InterfaceMethod org/w3c/dom/Node.getTextContent:()Ljava/lang/String;
│ │ +       198: iconst_1
│ │ +       199: invokespecial #172                // Method append:(Ljava/lang/StringBuilder;Ljava/lang/String;I)V
│ │ +       202: aload_0
│ │ +       203: aload_1
│ │ +       204: ldc           #178                // String
│ │ +       206: iconst_0
│ │ +       207: invokespecial #172                // Method append:(Ljava/lang/StringBuilder;Ljava/lang/String;I)V
│ │ +       210: aload_0
│ │ +       211: getfield      #312                // Field detail:Z
│ │ +       214: ifeq          298
│ │ +       217: aload_0
│ │ +       218: aload_3
│ │ +       219: ldc_w         #314                // String parameters
│ │ +       222: invokespecial #137                // Method getSingleChild:(Lorg/w3c/dom/Node;Ljava/lang/String;)Lorg/w3c/dom/Node;
│ │ +       225: astore        8
│ │ +       227: aload_0
│ │ +       228: aload         8
│ │ +       230: ldc_w         #316                // String parameter
│ │ +       233: invokespecial #188                // Method findNamedChild:(Lorg/w3c/dom/Node;Ljava/lang/String;)Ljava/util/List;
│ │ +       236: astore        9
│ │ +       238: aload_0
│ │ +       239: aload_1
│ │ +       240: ldc_w         #318                // String Available parameters:
│ │ +       243: iconst_1
│ │ +       244: invokespecial #172                // Method append:(Ljava/lang/StringBuilder;Ljava/lang/String;I)V
│ │ +       247: aload_0
│ │ +       248: aload_1
│ │ +       249: ldc           #178                // String
│ │ +       251: iconst_0
│ │ +       252: invokespecial #172                // Method append:(Ljava/lang/StringBuilder;Ljava/lang/String;I)V
│ │ +       255: aload         9
│ │ +       257: invokeinterface #212,  1          // InterfaceMethod java/util/List.iterator:()Ljava/util/Iterator;
│ │ +       262: astore        10
│ │ +       264: aload         10
│ │ +       266: invokeinterface #218,  1          // InterfaceMethod java/util/Iterator.hasNext:()Z
│ │ +       271: ifeq          298
│ │ +       274: aload         10
│ │ +       276: invokeinterface #222,  1          // InterfaceMethod java/util/Iterator.next:()Ljava/lang/Object;
│ │ +       281: checkcast     #174                // class org/w3c/dom/Node
│ │ +       284: astore        11
│ │ +       286: aload_0
│ │ +       287: aload_1
│ │ +       288: aload         11
│ │ +       290: aload         5
│ │ +       292: invokespecial #322                // Method writeParameter:(Ljava/lang/StringBuilder;Lorg/w3c/dom/Node;Lorg/w3c/dom/Node;)V
│ │ +       295: goto          264
│ │ +       298: return
│ │        StackMapTable: number_of_entries = 5
│ │          frame_type = 254 /* append */
│ │ -          offset_delta = 56
│ │ +          offset_delta = 58
│ │            locals = [ class java/lang/String, class org/w3c/dom/Node, class org/w3c/dom/Node ]
│ │          frame_type = 252 /* append */
│ │ -          offset_delta = 123
│ │ +          offset_delta = 125
│ │            locals = [ class org/w3c/dom/Node ]
│ │          frame_type = 17 /* same */
│ │          frame_type = 254 /* append */
│ │ -          offset_delta = 58
│ │ +          offset_delta = 61
│ │            locals = [ class org/w3c/dom/Node, class java/util/List, class java/util/Iterator ]
│ │          frame_type = 255 /* full_frame */
│ │            offset_delta = 33
│ │            locals = [ class io/fabric8/maven/docker/HelpMojo, class java/lang/StringBuilder, class java/lang/String, class org/w3c/dom/Element, class java/lang/String, class org/w3c/dom/Node, class org/w3c/dom/Node ]
│ │            stack = []
│ │ +      LineNumberTable:
│ │ +        line 233: 0
│ │ +        line 234: 10
│ │ +        line 235: 20
│ │ +        line 236: 29
│ │ +        line 238: 58
│ │ +        line 239: 88
│ │ +        line 240: 98
│ │ +        line 242: 116
│ │ +        line 243: 148
│ │ +        line 245: 160
│ │ +        line 246: 168
│ │ +        line 249: 184
│ │ +        line 251: 189
│ │ +        line 253: 202
│ │ +        line 255: 210
│ │ +        line 257: 217
│ │ +        line 258: 227
│ │ +        line 259: 238
│ │ +        line 260: 247
│ │ +        line 262: 255
│ │ +        line 264: 286
│ │ +        line 265: 295
│ │ +        line 268: 298
│ │ +      LocalVariableTable:
│ │ +        Start  Length  Slot  Name   Signature
│ │ +          286       9    11 parameter   Lorg/w3c/dom/Node;
│ │ +          227      71     8 parametersNode   Lorg/w3c/dom/Node;
│ │ +          238      60     9 parameters   Ljava/util/List;
│ │ +           98     200     7 deprecated   Lorg/w3c/dom/Node;
│ │ +            0     299     0  this   Lio/fabric8/maven/docker/HelpMojo;
│ │ +            0     299     1    sb   Ljava/lang/StringBuilder;
│ │ +            0     299     2 goalPrefix   Ljava/lang/String;
│ │ +            0     299     3  mojo   Lorg/w3c/dom/Element;
│ │ +           10     289     4 mojoGoal   Ljava/lang/String;
│ │ +           20     279     5 configurationElement   Lorg/w3c/dom/Node;
│ │ +           29     270     6 description   Lorg/w3c/dom/Node;
│ │ +      LocalVariableTypeTable:
│ │ +        Start  Length  Slot  Name   Signature
│ │ +          238      60     9 parameters   Ljava/util/List<Lorg/w3c/dom/Node;>;
│ │      Exceptions:
│ │        throws org.apache.maven.plugin.MojoExecutionException
│ │  
│ │    private void writeParameter(java.lang.StringBuilder, org.w3c.dom.Node, org.w3c.dom.Node) throws org.apache.maven.plugin.MojoExecutionException;
│ │      descriptor: (Ljava/lang/StringBuilder;Lorg/w3c/dom/Node;Lorg/w3c/dom/Node;)V
│ │      flags: (0x0002) ACC_PRIVATE
│ │      Code:
│ │        stack=4, locals=10, args_size=4
│ │           0: aload_0
│ │           1: aload_2
│ │ -         2: ldc           #31                 // String name
│ │ -         4: invokespecial #32                 // Method getValue:(Lorg/w3c/dom/Node;Ljava/lang/String;)Ljava/lang/String;
│ │ +         2: ldc           #138                // String name
│ │ +         4: invokespecial #142                // Method getValue:(Lorg/w3c/dom/Node;Ljava/lang/String;)Ljava/lang/String;
│ │           7: astore        4
│ │           9: aload_0
│ │          10: aload_2
│ │ -        11: ldc           #43                 // String description
│ │ -        13: invokespecial #32                 // Method getValue:(Lorg/w3c/dom/Node;Ljava/lang/String;)Ljava/lang/String;
│ │ +        11: ldc           #176                // String description
│ │ +        13: invokespecial #142                // Method getValue:(Lorg/w3c/dom/Node;Ljava/lang/String;)Ljava/lang/String;
│ │          16: astore        5
│ │          18: aconst_null
│ │          19: astore        6
│ │          21: aload_3
│ │          22: ifnull        37
│ │          25: aload_0
│ │          26: aload_3
│ │          27: aload         4
│ │ -        29: invokespecial #82                 // Method findSingleChild:(Lorg/w3c/dom/Node;Ljava/lang/String;)Lorg/w3c/dom/Node;
│ │ -        32: checkcast     #60                 // class org/w3c/dom/Element
│ │ +        29: invokespecial #306                // Method findSingleChild:(Lorg/w3c/dom/Node;Ljava/lang/String;)Lorg/w3c/dom/Node;
│ │ +        32: checkcast     #224                // class org/w3c/dom/Element
│ │          35: astore        6
│ │ -        37: ldc           #44                 // String
│ │ +        37: ldc           #178                // String
│ │          39: astore        7
│ │          41: aload         6
│ │ -        43: ifnull        92
│ │ +        43: ifnull        96
│ │          46: aload         6
│ │ -        48: ldc           #90                 // String default-value
│ │ -        50: invokeinterface #91,  2           // InterfaceMethod org/w3c/dom/Element.hasAttribute:(Ljava/lang/String;)Z
│ │ -        55: ifeq          92
│ │ -        58: new           #27                 // class java/lang/StringBuilder
│ │ -        61: dup
│ │ -        62: invokespecial #28                 // Method java/lang/StringBuilder."<init>":()V
│ │ -        65: ldc           #92                 // String  (Default:
│ │ -        67: invokevirtual #35                 // Method java/lang/StringBuilder.append:(Ljava/lang/String;)Ljava/lang/StringBuilder;
│ │ -        70: aload         6
│ │ -        72: ldc           #90                 // String default-value
│ │ -        74: invokeinterface #93,  2           // InterfaceMethod org/w3c/dom/Element.getAttribute:(Ljava/lang/String;)Ljava/lang/String;
│ │ -        79: invokevirtual #35                 // Method java/lang/StringBuilder.append:(Ljava/lang/String;)Ljava/lang/StringBuilder;
│ │ -        82: ldc           #94                 // String )
│ │ -        84: invokevirtual #35                 // Method java/lang/StringBuilder.append:(Ljava/lang/String;)Ljava/lang/StringBuilder;
│ │ -        87: invokevirtual #38                 // Method java/lang/StringBuilder.toString:()Ljava/lang/String;
│ │ -        90: astore        7
│ │ -        92: aload_0
│ │ -        93: aload_1
│ │ -        94: new           #27                 // class java/lang/StringBuilder
│ │ -        97: dup
│ │ -        98: invokespecial #28                 // Method java/lang/StringBuilder."<init>":()V
│ │ -       101: aload         4
│ │ -       103: invokevirtual #35                 // Method java/lang/StringBuilder.append:(Ljava/lang/String;)Ljava/lang/StringBuilder;
│ │ -       106: aload         7
│ │ -       108: invokevirtual #35                 // Method java/lang/StringBuilder.append:(Ljava/lang/String;)Ljava/lang/StringBuilder;
│ │ -       111: invokevirtual #38                 // Method java/lang/StringBuilder.toString:()Ljava/lang/String;
│ │ -       114: iconst_2
│ │ -       115: invokespecial #42                 // Method append:(Ljava/lang/StringBuilder;Ljava/lang/String;I)V
│ │ -       118: aload_0
│ │ -       119: aload_2
│ │ -       120: ldc           #83                 // String deprecated
│ │ -       122: invokespecial #82                 // Method findSingleChild:(Lorg/w3c/dom/Node;Ljava/lang/String;)Lorg/w3c/dom/Node;
│ │ -       125: astore        8
│ │ -       127: aload         8
│ │ -       129: ifnull        184
│ │ +        48: ldc_w         #328                // String default-value
│ │ +        51: invokeinterface #331,  2          // InterfaceMethod org/w3c/dom/Element.hasAttribute:(Ljava/lang/String;)Z
│ │ +        56: ifeq          96
│ │ +        59: new           #130                // class java/lang/StringBuilder
│ │ +        62: dup
│ │ +        63: invokespecial #131                // Method java/lang/StringBuilder."<init>":()V
│ │ +        66: ldc_w         #333                // String  (Default:
│ │ +        69: invokevirtual #150                // Method java/lang/StringBuilder.append:(Ljava/lang/String;)Ljava/lang/StringBuilder;
│ │ +        72: aload         6
│ │ +        74: ldc_w         #328                // String default-value
│ │ +        77: invokeinterface #337,  2          // InterfaceMethod org/w3c/dom/Element.getAttribute:(Ljava/lang/String;)Ljava/lang/String;
│ │ +        82: invokevirtual #150                // Method java/lang/StringBuilder.append:(Ljava/lang/String;)Ljava/lang/StringBuilder;
│ │ +        85: ldc_w         #339                // String )
│ │ +        88: invokevirtual #150                // Method java/lang/StringBuilder.append:(Ljava/lang/String;)Ljava/lang/StringBuilder;
│ │ +        91: invokevirtual #157                // Method java/lang/StringBuilder.toString:()Ljava/lang/String;
│ │ +        94: astore        7
│ │ +        96: aload_0
│ │ +        97: aload_1
│ │ +        98: new           #130                // class java/lang/StringBuilder
│ │ +       101: dup
│ │ +       102: invokespecial #131                // Method java/lang/StringBuilder."<init>":()V
│ │ +       105: aload         4
│ │ +       107: invokevirtual #150                // Method java/lang/StringBuilder.append:(Ljava/lang/String;)Ljava/lang/StringBuilder;
│ │ +       110: aload         7
│ │ +       112: invokevirtual #150                // Method java/lang/StringBuilder.append:(Ljava/lang/String;)Ljava/lang/StringBuilder;
│ │ +       115: invokevirtual #157                // Method java/lang/StringBuilder.toString:()Ljava/lang/String;
│ │ +       118: iconst_2
│ │ +       119: invokespecial #172                // Method append:(Ljava/lang/StringBuilder;Ljava/lang/String;I)V
│ │ +       122: aload_0
│ │ +       123: aload_2
│ │ +       124: ldc_w         #308                // String deprecated
│ │ +       127: invokespecial #306                // Method findSingleChild:(Lorg/w3c/dom/Node;Ljava/lang/String;)Lorg/w3c/dom/Node;
│ │ +       130: astore        8
│ │         132: aload         8
│ │ -       134: invokeinterface #64,  1           // InterfaceMethod org/w3c/dom/Node.getTextContent:()Ljava/lang/String;
│ │ -       139: invokestatic  #39                 // Method isNotEmpty:(Ljava/lang/String;)Z
│ │ -       142: ifeq          184
│ │ -       145: aload_0
│ │ -       146: aload_1
│ │ -       147: new           #27                 // class java/lang/StringBuilder
│ │ -       150: dup
│ │ -       151: invokespecial #28                 // Method java/lang/StringBuilder."<init>":()V
│ │ -       154: ldc           #84                 // String Deprecated.
│ │ -       156: invokevirtual #35                 // Method java/lang/StringBuilder.append:(Ljava/lang/String;)Ljava/lang/StringBuilder;
│ │ -       159: aload         8
│ │ -       161: invokeinterface #64,  1           // InterfaceMethod org/w3c/dom/Node.getTextContent:()Ljava/lang/String;
│ │ -       166: invokevirtual #35                 // Method java/lang/StringBuilder.append:(Ljava/lang/String;)Ljava/lang/StringBuilder;
│ │ -       169: invokevirtual #38                 // Method java/lang/StringBuilder.toString:()Ljava/lang/String;
│ │ -       172: iconst_3
│ │ -       173: invokespecial #42                 // Method append:(Ljava/lang/StringBuilder;Ljava/lang/String;I)V
│ │ -       176: aload_0
│ │ -       177: aload_1
│ │ -       178: ldc           #44                 // String
│ │ -       180: iconst_0
│ │ -       181: invokespecial #42                 // Method append:(Ljava/lang/StringBuilder;Ljava/lang/String;I)V
│ │ -       184: aload_0
│ │ -       185: aload_1
│ │ -       186: aload         5
│ │ -       188: iconst_3
│ │ -       189: invokespecial #42                 // Method append:(Ljava/lang/StringBuilder;Ljava/lang/String;I)V
│ │ -       192: ldc           #95                 // String true
│ │ -       194: aload_0
│ │ -       195: aload_2
│ │ -       196: ldc           #96                 // String required
│ │ -       198: invokespecial #32                 // Method getValue:(Lorg/w3c/dom/Node;Ljava/lang/String;)Ljava/lang/String;
│ │ -       201: invokevirtual #77                 // Method java/lang/String.equals:(Ljava/lang/Object;)Z
│ │ -       204: ifeq          215
│ │ -       207: aload_0
│ │ -       208: aload_1
│ │ -       209: ldc           #97                 // String Required: Yes
│ │ -       211: iconst_3
│ │ -       212: invokespecial #42                 // Method append:(Ljava/lang/StringBuilder;Ljava/lang/String;I)V
│ │ -       215: aload         6
│ │ -       217: ifnull        272
│ │ -       220: aload         6
│ │ -       222: invokeinterface #98,  1           // InterfaceMethod org/w3c/dom/Element.getTextContent:()Ljava/lang/String;
│ │ -       227: invokestatic  #39                 // Method isNotEmpty:(Ljava/lang/String;)Z
│ │ -       230: ifeq          272
│ │ -       233: aload_0
│ │ -       234: aload         6
│ │ -       236: invokeinterface #98,  1           // InterfaceMethod org/w3c/dom/Element.getTextContent:()Ljava/lang/String;
│ │ -       241: invokespecial #99                 // Method getPropertyFromExpression:(Ljava/lang/String;)Ljava/lang/String;
│ │ -       244: astore        9
│ │ -       246: aload_0
│ │ -       247: aload_1
│ │ -       248: new           #27                 // class java/lang/StringBuilder
│ │ -       251: dup
│ │ -       252: invokespecial #28                 // Method java/lang/StringBuilder."<init>":()V
│ │ -       255: ldc           #100                // String User property:
│ │ -       257: invokevirtual #35                 // Method java/lang/StringBuilder.append:(Ljava/lang/String;)Ljava/lang/StringBuilder;
│ │ -       260: aload         9
│ │ -       262: invokevirtual #35                 // Method java/lang/StringBuilder.append:(Ljava/lang/String;)Ljava/lang/StringBuilder;
│ │ -       265: invokevirtual #38                 // Method java/lang/StringBuilder.toString:()Ljava/lang/String;
│ │ -       268: iconst_3
│ │ -       269: invokespecial #42                 // Method append:(Ljava/lang/StringBuilder;Ljava/lang/String;I)V
│ │ -       272: aload_0
│ │ -       273: aload_1
│ │ -       274: ldc           #44                 // String
│ │ -       276: iconst_0
│ │ -       277: invokespecial #42                 // Method append:(Ljava/lang/StringBuilder;Ljava/lang/String;I)V
│ │ -       280: return
│ │ -      LineNumberTable:
│ │ -        line 274: 0
│ │ -        line 275: 9
│ │ -        line 277: 18
│ │ -        line 278: 21
│ │ -        line 280: 25
│ │ -        line 283: 37
│ │ -        line 284: 41
│ │ -        line 286: 58
│ │ -        line 288: 92
│ │ -        line 289: 118
│ │ -        line 290: 127
│ │ -        line 292: 145
│ │ -        line 293: 176
│ │ -        line 295: 184
│ │ -        line 296: 192
│ │ -        line 298: 207
│ │ -        line 300: 215
│ │ -        line 302: 233
│ │ -        line 303: 246
│ │ -        line 306: 272
│ │ -        line 307: 280
│ │ -      LocalVariableTable:
│ │ -        Start  Length  Slot  Name   Signature
│ │ -          246      26     9 property   Ljava/lang/String;
│ │ -            0     281     0  this   Lio/fabric8/maven/docker/HelpMojo;
│ │ -            0     281     1    sb   Ljava/lang/StringBuilder;
│ │ -            0     281     2 parameter   Lorg/w3c/dom/Node;
│ │ -            0     281     3 configurationElement   Lorg/w3c/dom/Node;
│ │ -            9     272     4 parameterName   Ljava/lang/String;
│ │ -           18     263     5 parameterDescription   Ljava/lang/String;
│ │ -           21     260     6 fieldConfigurationElement   Lorg/w3c/dom/Element;
│ │ -           41     240     7 parameterDefaultValue   Ljava/lang/String;
│ │ -          127     154     8 deprecated   Lorg/w3c/dom/Node;
│ │ +       134: ifnull        190
│ │ +       137: aload         8
│ │ +       139: invokeinterface #247,  1          // InterfaceMethod org/w3c/dom/Node.getTextContent:()Ljava/lang/String;
│ │ +       144: invokestatic  #161                // Method isNotEmpty:(Ljava/lang/String;)Z
│ │ +       147: ifeq          190
│ │ +       150: aload_0
│ │ +       151: aload_1
│ │ +       152: new           #130                // class java/lang/StringBuilder
│ │ +       155: dup
│ │ +       156: invokespecial #131                // Method java/lang/StringBuilder."<init>":()V
│ │ +       159: ldc_w         #310                // String Deprecated.
│ │ +       162: invokevirtual #150                // Method java/lang/StringBuilder.append:(Ljava/lang/String;)Ljava/lang/StringBuilder;
│ │ +       165: aload         8
│ │ +       167: invokeinterface #247,  1          // InterfaceMethod org/w3c/dom/Node.getTextContent:()Ljava/lang/String;
│ │ +       172: invokevirtual #150                // Method java/lang/StringBuilder.append:(Ljava/lang/String;)Ljava/lang/StringBuilder;
│ │ +       175: invokevirtual #157                // Method java/lang/StringBuilder.toString:()Ljava/lang/String;
│ │ +       178: iconst_3
│ │ +       179: invokespecial #172                // Method append:(Ljava/lang/StringBuilder;Ljava/lang/String;I)V
│ │ +       182: aload_0
│ │ +       183: aload_1
│ │ +       184: ldc           #178                // String
│ │ +       186: iconst_0
│ │ +       187: invokespecial #172                // Method append:(Ljava/lang/StringBuilder;Ljava/lang/String;I)V
│ │ +       190: aload_0
│ │ +       191: aload_1
│ │ +       192: aload         5
│ │ +       194: iconst_3
│ │ +       195: invokespecial #172                // Method append:(Ljava/lang/StringBuilder;Ljava/lang/String;I)V
│ │ +       198: ldc_w         #341                // String true
│ │ +       201: aload_0
│ │ +       202: aload_2
│ │ +       203: ldc_w         #343                // String required
│ │ +       206: invokespecial #142                // Method getValue:(Lorg/w3c/dom/Node;Ljava/lang/String;)Ljava/lang/String;
│ │ +       209: invokevirtual #290                // Method java/lang/String.equals:(Ljava/lang/Object;)Z
│ │ +       212: ifeq          224
│ │ +       215: aload_0
│ │ +       216: aload_1
│ │ +       217: ldc_w         #345                // String Required: Yes
│ │ +       220: iconst_3
│ │ +       221: invokespecial #172                // Method append:(Ljava/lang/StringBuilder;Ljava/lang/String;I)V
│ │ +       224: aload         6
│ │ +       226: ifnull        282
│ │ +       229: aload         6
│ │ +       231: invokeinterface #346,  1          // InterfaceMethod org/w3c/dom/Element.getTextContent:()Ljava/lang/String;
│ │ +       236: invokestatic  #161                // Method isNotEmpty:(Ljava/lang/String;)Z
│ │ +       239: ifeq          282
│ │ +       242: aload_0
│ │ +       243: aload         6
│ │ +       245: invokeinterface #346,  1          // InterfaceMethod org/w3c/dom/Element.getTextContent:()Ljava/lang/String;
│ │ +       250: invokespecial #349                // Method getPropertyFromExpression:(Ljava/lang/String;)Ljava/lang/String;
│ │ +       253: astore        9
│ │ +       255: aload_0
│ │ +       256: aload_1
│ │ +       257: new           #130                // class java/lang/StringBuilder
│ │ +       260: dup
│ │ +       261: invokespecial #131                // Method java/lang/StringBuilder."<init>":()V
│ │ +       264: ldc_w         #351                // String User property:
│ │ +       267: invokevirtual #150                // Method java/lang/StringBuilder.append:(Ljava/lang/String;)Ljava/lang/StringBuilder;
│ │ +       270: aload         9
│ │ +       272: invokevirtual #150                // Method java/lang/StringBuilder.append:(Ljava/lang/String;)Ljava/lang/StringBuilder;
│ │ +       275: invokevirtual #157                // Method java/lang/StringBuilder.toString:()Ljava/lang/String;
│ │ +       278: iconst_3
│ │ +       279: invokespecial #172                // Method append:(Ljava/lang/StringBuilder;Ljava/lang/String;I)V
│ │ +       282: aload_0
│ │ +       283: aload_1
│ │ +       284: ldc           #178                // String
│ │ +       286: iconst_0
│ │ +       287: invokespecial #172                // Method append:(Ljava/lang/StringBuilder;Ljava/lang/String;I)V
│ │ +       290: return
│ │        StackMapTable: number_of_entries = 5
│ │          frame_type = 254 /* append */
│ │            offset_delta = 37
│ │            locals = [ class java/lang/String, class java/lang/String, class org/w3c/dom/Element ]
│ │          frame_type = 252 /* append */
│ │ -          offset_delta = 54
│ │ +          offset_delta = 58
│ │            locals = [ class java/lang/String ]
│ │          frame_type = 252 /* append */
│ │ -          offset_delta = 91
│ │ +          offset_delta = 93
│ │            locals = [ class org/w3c/dom/Node ]
│ │ -        frame_type = 30 /* same */
│ │ -        frame_type = 56 /* same */
│ │ +        frame_type = 33 /* same */
│ │ +        frame_type = 57 /* same */
│ │ +      LineNumberTable:
│ │ +        line 273: 0
│ │ +        line 274: 9
│ │ +        line 276: 18
│ │ +        line 277: 21
│ │ +        line 279: 25
│ │ +        line 282: 37
│ │ +        line 283: 41
│ │ +        line 285: 59
│ │ +        line 287: 96
│ │ +        line 288: 122
│ │ +        line 289: 132
│ │ +        line 291: 150
│ │ +        line 292: 182
│ │ +        line 294: 190
│ │ +        line 295: 198
│ │ +        line 297: 215
│ │ +        line 299: 224
│ │ +        line 301: 242
│ │ +        line 302: 255
│ │ +        line 305: 282
│ │ +        line 306: 290
│ │ +      LocalVariableTable:
│ │ +        Start  Length  Slot  Name   Signature
│ │ +          255      27     9 property   Ljava/lang/String;
│ │ +            0     291     0  this   Lio/fabric8/maven/docker/HelpMojo;
│ │ +            0     291     1    sb   Ljava/lang/StringBuilder;
│ │ +            0     291     2 parameter   Lorg/w3c/dom/Node;
│ │ +            0     291     3 configurationElement   Lorg/w3c/dom/Node;
│ │ +            9     282     4 parameterName   Ljava/lang/String;
│ │ +           18     273     5 parameterDescription   Ljava/lang/String;
│ │ +           21     270     6 fieldConfigurationElement   Lorg/w3c/dom/Element;
│ │ +           41     250     7 parameterDefaultValue   Ljava/lang/String;
│ │ +          132     159     8 deprecated   Lorg/w3c/dom/Node;
│ │      Exceptions:
│ │        throws org.apache.maven.plugin.MojoExecutionException
│ │  
│ │    private static java.lang.String repeat(java.lang.String, int);
│ │      descriptor: (Ljava/lang/String;I)Ljava/lang/String;
│ │      flags: (0x000a) ACC_PRIVATE, ACC_STATIC
│ │      Code:
│ │        stack=4, locals=4, args_size=2
│ │ -         0: new           #27                 // class java/lang/StringBuilder
│ │ +         0: new           #130                // class java/lang/StringBuilder
│ │           3: dup
│ │           4: iload_1
│ │           5: aload_0
│ │ -         6: invokevirtual #50                 // Method java/lang/String.length:()I
│ │ +         6: invokevirtual #194                // Method java/lang/String.length:()I
│ │           9: imul
│ │ -        10: invokespecial #101                // Method java/lang/StringBuilder."<init>":(I)V
│ │ +        10: invokespecial #360                // Method java/lang/StringBuilder."<init>":(I)V
│ │          13: astore_2
│ │          14: iconst_0
│ │          15: istore_3
│ │          16: iload_3
│ │          17: iload_1
│ │          18: if_icmpge     33
│ │          21: aload_2
│ │          22: aload_0
│ │ -        23: invokevirtual #35                 // Method java/lang/StringBuilder.append:(Ljava/lang/String;)Ljava/lang/StringBuilder;
│ │ +        23: invokevirtual #150                // Method java/lang/StringBuilder.append:(Ljava/lang/String;)Ljava/lang/StringBuilder;
│ │          26: pop
│ │          27: iinc          3, 1
│ │          30: goto          16
│ │          33: aload_2
│ │ -        34: invokevirtual #38                 // Method java/lang/StringBuilder.toString:()Ljava/lang/String;
│ │ +        34: invokevirtual #157                // Method java/lang/StringBuilder.toString:()Ljava/lang/String;
│ │          37: areturn
│ │ +      StackMapTable: number_of_entries = 2
│ │ +        frame_type = 253 /* append */
│ │ +          offset_delta = 16
│ │ +          locals = [ class java/lang/StringBuilder, int ]
│ │ +        frame_type = 250 /* chop */
│ │ +          offset_delta = 16
│ │        LineNumberTable:
│ │ -        line 320: 0
│ │ -        line 322: 14
│ │ -        line 324: 21
│ │ -        line 322: 27
│ │ -        line 327: 33
│ │ +        line 319: 0
│ │ +        line 321: 14
│ │ +        line 323: 21
│ │ +        line 321: 27
│ │ +        line 326: 33
│ │        LocalVariableTable:
│ │          Start  Length  Slot  Name   Signature
│ │             16      17     3     i   I
│ │              0      38     0   str   Ljava/lang/String;
│ │              0      38     1 repeat   I
│ │             14      24     2 buffer   Ljava/lang/StringBuilder;
│ │ -      StackMapTable: number_of_entries = 2
│ │ -        frame_type = 253 /* append */
│ │ -          offset_delta = 16
│ │ -          locals = [ class java/lang/StringBuilder, int ]
│ │ -        frame_type = 250 /* chop */
│ │ -          offset_delta = 16
│ │  
│ │    private void append(java.lang.StringBuilder, java.lang.String, int);
│ │      descriptor: (Ljava/lang/StringBuilder;Ljava/lang/String;I)V
│ │      flags: (0x0002) ACC_PRIVATE
│ │      Code:
│ │        stack=4, locals=6, args_size=4
│ │           0: aload_2
│ │           1: iload_3
│ │           2: aload_0
│ │ -         3: getfield      #24                 // Field indentSize:I
│ │ +         3: getfield      #124                // Field indentSize:I
│ │           6: aload_0
│ │ -         7: getfield      #21                 // Field lineLength:I
│ │ -        10: invokestatic  #102                // Method toLines:(Ljava/lang/String;III)Ljava/util/List;
│ │ -        13: invokeinterface #56,  1           // InterfaceMethod java/util/List.iterator:()Ljava/util/Iterator;
│ │ +         7: getfield      #117                // Field lineLength:I
│ │ +        10: invokestatic  #366                // Method toLines:(Ljava/lang/String;III)Ljava/util/List;
│ │ +        13: invokeinterface #212,  1          // InterfaceMethod java/util/List.iterator:()Ljava/util/Iterator;
│ │          18: astore        4
│ │          20: aload         4
│ │ -        22: invokeinterface #57,  1           // InterfaceMethod java/util/Iterator.hasNext:()Z
│ │ +        22: invokeinterface #218,  1          // InterfaceMethod java/util/Iterator.hasNext:()Z
│ │          27: ifeq          57
│ │          30: aload         4
│ │ -        32: invokeinterface #58,  1           // InterfaceMethod java/util/Iterator.next:()Ljava/lang/Object;
│ │ -        37: checkcast     #103                // class java/lang/String
│ │ +        32: invokeinterface #222,  1          // InterfaceMethod java/util/Iterator.next:()Ljava/lang/Object;
│ │ +        37: checkcast     #163                // class java/lang/String
│ │          40: astore        5
│ │          42: aload_1
│ │          43: aload         5
│ │ -        45: invokevirtual #35                 // Method java/lang/StringBuilder.append:(Ljava/lang/String;)Ljava/lang/StringBuilder;
│ │ +        45: invokevirtual #150                // Method java/lang/StringBuilder.append:(Ljava/lang/String;)Ljava/lang/StringBuilder;
│ │          48: bipush        10
│ │ -        50: invokevirtual #104                // Method java/lang/StringBuilder.append:(C)Ljava/lang/StringBuilder;
│ │ +        50: invokevirtual #369                // Method java/lang/StringBuilder.append:(C)Ljava/lang/StringBuilder;
│ │          53: pop
│ │          54: goto          20
│ │          57: return
│ │ +      StackMapTable: number_of_entries = 2
│ │ +        frame_type = 252 /* append */
│ │ +          offset_delta = 20
│ │ +          locals = [ class java/util/Iterator ]
│ │ +        frame_type = 250 /* chop */
│ │ +          offset_delta = 36
│ │        LineNumberTable:
│ │ -        line 340: 0
│ │ -        line 342: 42
│ │ -        line 343: 54
│ │ -        line 344: 57
│ │ +        line 339: 0
│ │ +        line 341: 42
│ │ +        line 342: 54
│ │ +        line 343: 57
│ │        LocalVariableTable:
│ │          Start  Length  Slot  Name   Signature
│ │             42      12     5  line   Ljava/lang/String;
│ │              0      58     0  this   Lio/fabric8/maven/docker/HelpMojo;
│ │              0      58     1    sb   Ljava/lang/StringBuilder;
│ │              0      58     2 description   Ljava/lang/String;
│ │              0      58     3 indent   I
│ │ -      StackMapTable: number_of_entries = 2
│ │ -        frame_type = 252 /* append */
│ │ -          offset_delta = 20
│ │ -          locals = [ class java/util/Iterator ]
│ │ -        frame_type = 250 /* chop */
│ │ -          offset_delta = 36
│ │  
│ │    private static java.util.List<java.lang.String> toLines(java.lang.String, int, int, int);
│ │      descriptor: (Ljava/lang/String;III)Ljava/util/List;
│ │      flags: (0x000a) ACC_PRIVATE, ACC_STATIC
│ │      Code:
│ │        stack=4, locals=11, args_size=4
│ │ -         0: new           #71                 // class java/util/ArrayList
│ │ +         0: new           #269                // class java/util/ArrayList
│ │           3: dup
│ │ -         4: invokespecial #72                 // Method java/util/ArrayList."<init>":()V
│ │ +         4: invokespecial #270                // Method java/util/ArrayList."<init>":()V
│ │           7: astore        4
│ │ -         9: ldc           #105                // String \t
│ │ -        11: iload_1
│ │ -        12: invokestatic  #106                // Method repeat:(Ljava/lang/String;I)Ljava/lang/String;
│ │ -        15: astore        5
│ │ -        17: aload_0
│ │ -        18: ldc           #107                // String (\r\n)|(\r)|(\n)
│ │ -        20: invokevirtual #108                // Method java/lang/String.split:(Ljava/lang/String;)[Ljava/lang/String;
│ │ -        23: astore        6
│ │ -        25: aload         6
│ │ -        27: astore        7
│ │ -        29: aload         7
│ │ -        31: arraylength
│ │ -        32: istore        8
│ │ -        34: iconst_0
│ │ -        35: istore        9
│ │ -        37: iload         9
│ │ -        39: iload         8
│ │ -        41: if_icmpge     84
│ │ -        44: aload         7
│ │ -        46: iload         9
│ │ -        48: aaload
│ │ -        49: astore        10
│ │ -        51: aload         4
│ │ -        53: new           #27                 // class java/lang/StringBuilder
│ │ -        56: dup
│ │ -        57: invokespecial #28                 // Method java/lang/StringBuilder."<init>":()V
│ │ -        60: aload         5
│ │ -        62: invokevirtual #35                 // Method java/lang/StringBuilder.append:(Ljava/lang/String;)Ljava/lang/StringBuilder;
│ │ -        65: aload         10
│ │ -        67: invokevirtual #35                 // Method java/lang/StringBuilder.append:(Ljava/lang/String;)Ljava/lang/StringBuilder;
│ │ -        70: invokevirtual #38                 // Method java/lang/StringBuilder.toString:()Ljava/lang/String;
│ │ -        73: iload_2
│ │ -        74: iload_3
│ │ -        75: invokestatic  #109                // Method toLines:(Ljava/util/List;Ljava/lang/String;II)V
│ │ -        78: iinc          9, 1
│ │ -        81: goto          37
│ │ -        84: aload         4
│ │ -        86: areturn
│ │ -      LineNumberTable:
│ │ -        line 358: 0
│ │ -        line 360: 9
│ │ -        line 362: 17
│ │ -        line 364: 25
│ │ -        line 366: 51
│ │ -        line 364: 78
│ │ -        line 369: 84
│ │ -      LocalVariableTable:
│ │ -        Start  Length  Slot  Name   Signature
│ │ -           51      27    10 plainLine   Ljava/lang/String;
│ │ -            0      87     0  text   Ljava/lang/String;
│ │ -            0      87     1 indent   I
│ │ -            0      87     2 indentSize   I
│ │ -            0      87     3 lineLength   I
│ │ -            9      78     4 lines   Ljava/util/List;
│ │ -           17      70     5   ind   Ljava/lang/String;
│ │ -           25      62     6 plainLines   [Ljava/lang/String;
│ │ -      LocalVariableTypeTable:
│ │ -        Start  Length  Slot  Name   Signature
│ │ -            9      78     4 lines   Ljava/util/List<Ljava/lang/String;>;
│ │ +         9: ldc_w         #374                // String \t
│ │ +        12: iload_1
│ │ +        13: invokestatic  #376                // Method repeat:(Ljava/lang/String;I)Ljava/lang/String;
│ │ +        16: astore        5
│ │ +        18: aload_0
│ │ +        19: ldc_w         #378                // String (\r\n)|(\r)|(\n)
│ │ +        22: invokevirtual #382                // Method java/lang/String.split:(Ljava/lang/String;)[Ljava/lang/String;
│ │ +        25: astore        6
│ │ +        27: aload         6
│ │ +        29: astore        7
│ │ +        31: aload         7
│ │ +        33: arraylength
│ │ +        34: istore        8
│ │ +        36: iconst_0
│ │ +        37: istore        9
│ │ +        39: iload         9
│ │ +        41: iload         8
│ │ +        43: if_icmpge     86
│ │ +        46: aload         7
│ │ +        48: iload         9
│ │ +        50: aaload
│ │ +        51: astore        10
│ │ +        53: aload         4
│ │ +        55: new           #130                // class java/lang/StringBuilder
│ │ +        58: dup
│ │ +        59: invokespecial #131                // Method java/lang/StringBuilder."<init>":()V
│ │ +        62: aload         5
│ │ +        64: invokevirtual #150                // Method java/lang/StringBuilder.append:(Ljava/lang/String;)Ljava/lang/StringBuilder;
│ │ +        67: aload         10
│ │ +        69: invokevirtual #150                // Method java/lang/StringBuilder.append:(Ljava/lang/String;)Ljava/lang/StringBuilder;
│ │ +        72: invokevirtual #157                // Method java/lang/StringBuilder.toString:()Ljava/lang/String;
│ │ +        75: iload_2
│ │ +        76: iload_3
│ │ +        77: invokestatic  #387                // Method toLines:(Ljava/util/List;Ljava/lang/String;II)V
│ │ +        80: iinc          9, 1
│ │ +        83: goto          39
│ │ +        86: aload         4
│ │ +        88: areturn
│ │        StackMapTable: number_of_entries = 2
│ │          frame_type = 255 /* full_frame */
│ │ -          offset_delta = 37
│ │ +          offset_delta = 39
│ │            locals = [ class java/lang/String, int, int, int, class java/util/List, class java/lang/String, class "[Ljava/lang/String;", class "[Ljava/lang/String;", int, int ]
│ │            stack = []
│ │          frame_type = 248 /* chop */
│ │            offset_delta = 46
│ │ -    Signature: #241                         // (Ljava/lang/String;III)Ljava/util/List<Ljava/lang/String;>;
│ │ +      LineNumberTable:
│ │ +        line 357: 0
│ │ +        line 359: 9
│ │ +        line 361: 18
│ │ +        line 363: 27
│ │ +        line 365: 53
│ │ +        line 363: 80
│ │ +        line 368: 86
│ │ +      LocalVariableTable:
│ │ +        Start  Length  Slot  Name   Signature
│ │ +           53      27    10 plainLine   Ljava/lang/String;
│ │ +            0      89     0  text   Ljava/lang/String;
│ │ +            0      89     1 indent   I
│ │ +            0      89     2 indentSize   I
│ │ +            0      89     3 lineLength   I
│ │ +            9      80     4 lines   Ljava/util/List;
│ │ +           18      71     5   ind   Ljava/lang/String;
│ │ +           27      62     6 plainLines   [Ljava/lang/String;
│ │ +      LocalVariableTypeTable:
│ │ +        Start  Length  Slot  Name   Signature
│ │ +            9      80     4 lines   Ljava/util/List<Ljava/lang/String;>;
│ │ +    Signature: #372                         // (Ljava/lang/String;III)Ljava/util/List<Ljava/lang/String;>;
│ │  
│ │    private static void toLines(java.util.List<java.lang.String>, java.lang.String, int, int);
│ │      descriptor: (Ljava/util/List;Ljava/lang/String;II)V
│ │      flags: (0x000a) ACC_PRIVATE, ACC_STATIC
│ │      Code:
│ │        stack=5, locals=13, args_size=4
│ │           0: aload_1
│ │ -         1: invokestatic  #110                // Method getIndentLevel:(Ljava/lang/String;)I
│ │ +         1: invokestatic  #398                // Method getIndentLevel:(Ljava/lang/String;)I
│ │           4: istore        4
│ │ -         6: new           #27                 // class java/lang/StringBuilder
│ │ +         6: new           #130                // class java/lang/StringBuilder
│ │           9: dup
│ │          10: sipush        256
│ │ -        13: invokespecial #101                // Method java/lang/StringBuilder."<init>":(I)V
│ │ +        13: invokespecial #360                // Method java/lang/StringBuilder."<init>":(I)V
│ │          16: astore        5
│ │          18: aload_1
│ │ -        19: ldc           #111                // String  +
│ │ -        21: invokevirtual #108                // Method java/lang/String.split:(Ljava/lang/String;)[Ljava/lang/String;
│ │ -        24: astore        6
│ │ -        26: aload         6
│ │ -        28: astore        7
│ │ -        30: aload         7
│ │ -        32: arraylength
│ │ -        33: istore        8
│ │ -        35: iconst_0
│ │ -        36: istore        9
│ │ -        38: iload         9
│ │ -        40: iload         8
│ │ -        42: if_icmpge     210
│ │ -        45: aload         7
│ │ -        47: iload         9
│ │ -        49: aaload
│ │ -        50: astore        10
│ │ -        52: aload         5
│ │ -        54: invokevirtual #112                // Method java/lang/StringBuilder.length:()I
│ │ -        57: ifle          119
│ │ -        60: aload         5
│ │ -        62: invokevirtual #112                // Method java/lang/StringBuilder.length:()I
│ │ -        65: aload         10
│ │ -        67: invokevirtual #50                 // Method java/lang/String.length:()I
│ │ -        70: iadd
│ │ -        71: iload_3
│ │ -        72: if_icmplt     111
│ │ -        75: aload_0
│ │ -        76: aload         5
│ │ -        78: invokevirtual #38                 // Method java/lang/StringBuilder.toString:()Ljava/lang/String;
│ │ -        81: invokeinterface #78,  2           // InterfaceMethod java/util/List.add:(Ljava/lang/Object;)Z
│ │ -        86: pop
│ │ -        87: aload         5
│ │ -        89: iconst_0
│ │ -        90: invokevirtual #113                // Method java/lang/StringBuilder.setLength:(I)V
│ │ -        93: aload         5
│ │ -        95: ldc           #41                 // String
│ │ -        97: iload         4
│ │ -        99: iload_2
│ │ -       100: imul
│ │ -       101: invokestatic  #106                // Method repeat:(Ljava/lang/String;I)Ljava/lang/String;
│ │ -       104: invokevirtual #35                 // Method java/lang/StringBuilder.append:(Ljava/lang/String;)Ljava/lang/StringBuilder;
│ │ -       107: pop
│ │ -       108: goto          119
│ │ -       111: aload         5
│ │ -       113: bipush        32
│ │ -       115: invokevirtual #104                // Method java/lang/StringBuilder.append:(C)Ljava/lang/StringBuilder;
│ │ -       118: pop
│ │ -       119: iconst_0
│ │ -       120: istore        11
│ │ -       122: iload         11
│ │ -       124: aload         10
│ │ -       126: invokevirtual #50                 // Method java/lang/String.length:()I
│ │ -       129: if_icmpge     204
│ │ -       132: aload         10
│ │ -       134: iload         11
│ │ -       136: invokevirtual #114                // Method java/lang/String.charAt:(I)C
│ │ -       139: istore        12
│ │ -       141: iload         12
│ │ -       143: bipush        9
│ │ -       145: if_icmpne     171
│ │ -       148: aload         5
│ │ -       150: ldc           #41                 // String
│ │ -       152: iload_2
│ │ -       153: aload         5
│ │ -       155: invokevirtual #112                // Method java/lang/StringBuilder.length:()I
│ │ -       158: iload_2
│ │ -       159: irem
│ │ -       160: isub
│ │ -       161: invokestatic  #106                // Method repeat:(Ljava/lang/String;I)Ljava/lang/String;
│ │ -       164: invokevirtual #35                 // Method java/lang/StringBuilder.append:(Ljava/lang/String;)Ljava/lang/StringBuilder;
│ │ -       167: pop
│ │ -       168: goto          198
│ │ -       171: iload         12
│ │ -       173: sipush        160
│ │ -       176: if_icmpne     190
│ │ -       179: aload         5
│ │ -       181: bipush        32
│ │ -       183: invokevirtual #104                // Method java/lang/StringBuilder.append:(C)Ljava/lang/StringBuilder;
│ │ -       186: pop
│ │ -       187: goto          198
│ │ -       190: aload         5
│ │ -       192: iload         12
│ │ -       194: invokevirtual #104                // Method java/lang/StringBuilder.append:(C)Ljava/lang/StringBuilder;
│ │ -       197: pop
│ │ -       198: iinc          11, 1
│ │ -       201: goto          122
│ │ -       204: iinc          9, 1
│ │ -       207: goto          38
│ │ -       210: aload_0
│ │ -       211: aload         5
│ │ -       213: invokevirtual #38                 // Method java/lang/StringBuilder.toString:()Ljava/lang/String;
│ │ -       216: invokeinterface #78,  2           // InterfaceMethod java/util/List.add:(Ljava/lang/Object;)Z
│ │ -       221: pop
│ │ -       222: return
│ │ -      LineNumberTable:
│ │ -        line 382: 0
│ │ -        line 383: 6
│ │ -        line 385: 18
│ │ -        line 387: 26
│ │ -        line 389: 52
│ │ -        line 391: 60
│ │ -        line 393: 75
│ │ -        line 394: 87
│ │ -        line 395: 93
│ │ -        line 399: 111
│ │ -        line 403: 119
│ │ -        line 405: 132
│ │ -        line 406: 141
│ │ -        line 408: 148
│ │ -        line 410: 171
│ │ -        line 412: 179
│ │ -        line 416: 190
│ │ -        line 403: 198
│ │ -        line 387: 204
│ │ -        line 420: 210
│ │ -        line 421: 222
│ │ -      LocalVariableTable:
│ │ -        Start  Length  Slot  Name   Signature
│ │ -          141      57    12     c   C
│ │ -          122      82    11     j   I
│ │ -           52     152    10 token   Ljava/lang/String;
│ │ -            0     223     0 lines   Ljava/util/List;
│ │ -            0     223     1  line   Ljava/lang/String;
│ │ -            0     223     2 indentSize   I
│ │ -            0     223     3 lineLength   I
│ │ -            6     217     4 lineIndent   I
│ │ -           18     205     5   buf   Ljava/lang/StringBuilder;
│ │ -           26     197     6 tokens   [Ljava/lang/String;
│ │ -      LocalVariableTypeTable:
│ │ -        Start  Length  Slot  Name   Signature
│ │ -            0     223     0 lines   Ljava/util/List<Ljava/lang/String;>;
│ │ +        19: ldc_w         #400                // String  +
│ │ +        22: invokevirtual #382                // Method java/lang/String.split:(Ljava/lang/String;)[Ljava/lang/String;
│ │ +        25: astore        6
│ │ +        27: aload         6
│ │ +        29: astore        7
│ │ +        31: aload         7
│ │ +        33: arraylength
│ │ +        34: istore        8
│ │ +        36: iconst_0
│ │ +        37: istore        9
│ │ +        39: iload         9
│ │ +        41: iload         8
│ │ +        43: if_icmpge     211
│ │ +        46: aload         7
│ │ +        48: iload         9
│ │ +        50: aaload
│ │ +        51: astore        10
│ │ +        53: aload         5
│ │ +        55: invokevirtual #401                // Method java/lang/StringBuilder.length:()I
│ │ +        58: ifle          120
│ │ +        61: aload         5
│ │ +        63: invokevirtual #401                // Method java/lang/StringBuilder.length:()I
│ │ +        66: aload         10
│ │ +        68: invokevirtual #194                // Method java/lang/String.length:()I
│ │ +        71: iadd
│ │ +        72: iload_3
│ │ +        73: if_icmplt     112
│ │ +        76: aload_0
│ │ +        77: aload         5
│ │ +        79: invokevirtual #157                // Method java/lang/StringBuilder.toString:()Ljava/lang/String;
│ │ +        82: invokeinterface #293,  2          // InterfaceMethod java/util/List.add:(Ljava/lang/Object;)Z
│ │ +        87: pop
│ │ +        88: aload         5
│ │ +        90: iconst_0
│ │ +        91: invokevirtual #404                // Method java/lang/StringBuilder.setLength:(I)V
│ │ +        94: aload         5
│ │ +        96: ldc           #169                // String
│ │ +        98: iload         4
│ │ +       100: iload_2
│ │ +       101: imul
│ │ +       102: invokestatic  #376                // Method repeat:(Ljava/lang/String;I)Ljava/lang/String;
│ │ +       105: invokevirtual #150                // Method java/lang/StringBuilder.append:(Ljava/lang/String;)Ljava/lang/StringBuilder;
│ │ +       108: pop
│ │ +       109: goto          120
│ │ +       112: aload         5
│ │ +       114: bipush        32
│ │ +       116: invokevirtual #369                // Method java/lang/StringBuilder.append:(C)Ljava/lang/StringBuilder;
│ │ +       119: pop
│ │ +       120: iconst_0
│ │ +       121: istore        11
│ │ +       123: iload         11
│ │ +       125: aload         10
│ │ +       127: invokevirtual #194                // Method java/lang/String.length:()I
│ │ +       130: if_icmpge     205
│ │ +       133: aload         10
│ │ +       135: iload         11
│ │ +       137: invokevirtual #408                // Method java/lang/String.charAt:(I)C
│ │ +       140: istore        12
│ │ +       142: iload         12
│ │ +       144: bipush        9
│ │ +       146: if_icmpne     172
│ │ +       149: aload         5
│ │ +       151: ldc           #169                // String
│ │ +       153: iload_2
│ │ +       154: aload         5
│ │ +       156: invokevirtual #401                // Method java/lang/StringBuilder.length:()I
│ │ +       159: iload_2
│ │ +       160: irem
│ │ +       161: isub
│ │ +       162: invokestatic  #376                // Method repeat:(Ljava/lang/String;I)Ljava/lang/String;
│ │ +       165: invokevirtual #150                // Method java/lang/StringBuilder.append:(Ljava/lang/String;)Ljava/lang/StringBuilder;
│ │ +       168: pop
│ │ +       169: goto          199
│ │ +       172: iload         12
│ │ +       174: sipush        160
│ │ +       177: if_icmpne     191
│ │ +       180: aload         5
│ │ +       182: bipush        32
│ │ +       184: invokevirtual #369                // Method java/lang/StringBuilder.append:(C)Ljava/lang/StringBuilder;
│ │ +       187: pop
│ │ +       188: goto          199
│ │ +       191: aload         5
│ │ +       193: iload         12
│ │ +       195: invokevirtual #369                // Method java/lang/StringBuilder.append:(C)Ljava/lang/StringBuilder;
│ │ +       198: pop
│ │ +       199: iinc          11, 1
│ │ +       202: goto          123
│ │ +       205: iinc          9, 1
│ │ +       208: goto          39
│ │ +       211: aload_0
│ │ +       212: aload         5
│ │ +       214: invokevirtual #157                // Method java/lang/StringBuilder.toString:()Ljava/lang/String;
│ │ +       217: invokeinterface #293,  2          // InterfaceMethod java/util/List.add:(Ljava/lang/Object;)Z
│ │ +       222: pop
│ │ +       223: return
│ │        StackMapTable: number_of_entries = 9
│ │          frame_type = 255 /* full_frame */
│ │ -          offset_delta = 38
│ │ +          offset_delta = 39
│ │            locals = [ class java/util/List, class java/lang/String, int, int, int, class java/lang/StringBuilder, class "[Ljava/lang/String;", class "[Ljava/lang/String;", int, int ]
│ │            stack = []
│ │          frame_type = 252 /* append */
│ │            offset_delta = 72
│ │            locals = [ class java/lang/String ]
│ │          frame_type = 7 /* same */
│ │          frame_type = 252 /* append */
│ │ @@ -1895,32 +1858,69 @@
│ │          frame_type = 18 /* same */
│ │          frame_type = 250 /* chop */
│ │            offset_delta = 7
│ │          frame_type = 249 /* chop */
│ │            offset_delta = 5
│ │          frame_type = 248 /* chop */
│ │            offset_delta = 5
│ │ -    Signature: #250                         // (Ljava/util/List<Ljava/lang/String;>;Ljava/lang/String;II)V
│ │ +      LineNumberTable:
│ │ +        line 381: 0
│ │ +        line 382: 6
│ │ +        line 384: 18
│ │ +        line 386: 27
│ │ +        line 388: 53
│ │ +        line 390: 61
│ │ +        line 392: 76
│ │ +        line 393: 88
│ │ +        line 394: 94
│ │ +        line 398: 112
│ │ +        line 402: 120
│ │ +        line 404: 133
│ │ +        line 405: 142
│ │ +        line 407: 149
│ │ +        line 409: 172
│ │ +        line 411: 180
│ │ +        line 415: 191
│ │ +        line 402: 199
│ │ +        line 386: 205
│ │ +        line 419: 211
│ │ +        line 420: 223
│ │ +      LocalVariableTable:
│ │ +        Start  Length  Slot  Name   Signature
│ │ +          142      57    12     c   C
│ │ +          123      82    11     j   I
│ │ +           53     152    10 token   Ljava/lang/String;
│ │ +            0     224     0 lines   Ljava/util/List;
│ │ +            0     224     1  line   Ljava/lang/String;
│ │ +            0     224     2 indentSize   I
│ │ +            0     224     3 lineLength   I
│ │ +            6     218     4 lineIndent   I
│ │ +           18     206     5   buf   Ljava/lang/StringBuilder;
│ │ +           27     197     6 tokens   [Ljava/lang/String;
│ │ +      LocalVariableTypeTable:
│ │ +        Start  Length  Slot  Name   Signature
│ │ +            0     224     0 lines   Ljava/util/List<Ljava/lang/String;>;
│ │ +    Signature: #394                         // (Ljava/util/List<Ljava/lang/String;>;Ljava/lang/String;II)V
│ │  
│ │    private static int getIndentLevel(java.lang.String);
│ │      descriptor: (Ljava/lang/String;)I
│ │      flags: (0x000a) ACC_PRIVATE, ACC_STATIC
│ │      Code:
│ │        stack=3, locals=3, args_size=1
│ │           0: iconst_0
│ │           1: istore_1
│ │           2: iconst_0
│ │           3: istore_2
│ │           4: iload_2
│ │           5: aload_0
│ │ -         6: invokevirtual #50                 // Method java/lang/String.length:()I
│ │ +         6: invokevirtual #194                // Method java/lang/String.length:()I
│ │           9: if_icmpge     31
│ │          12: aload_0
│ │          13: iload_2
│ │ -        14: invokevirtual #114                // Method java/lang/String.charAt:(I)C
│ │ +        14: invokevirtual #408                // Method java/lang/String.charAt:(I)C
│ │          17: bipush        9
│ │          19: if_icmpne     31
│ │          22: iinc          1, 1
│ │          25: iinc          2, 1
│ │          28: goto          4
│ │          31: iload_1
│ │          32: iconst_1
│ │ @@ -1929,101 +1929,101 @@
│ │          35: iload_2
│ │          36: iload_1
│ │          37: iconst_4
│ │          38: iadd
│ │          39: if_icmpgt     72
│ │          42: iload_2
│ │          43: aload_0
│ │ -        44: invokevirtual #50                 // Method java/lang/String.length:()I
│ │ +        44: invokevirtual #194                // Method java/lang/String.length:()I
│ │          47: if_icmpge     72
│ │          50: aload_0
│ │          51: iload_2
│ │ -        52: invokevirtual #114                // Method java/lang/String.charAt:(I)C
│ │ +        52: invokevirtual #408                // Method java/lang/String.charAt:(I)C
│ │          55: bipush        9
│ │          57: if_icmpne     66
│ │          60: iinc          1, 1
│ │          63: goto          72
│ │          66: iinc          2, 1
│ │          69: goto          35
│ │          72: iload_1
│ │          73: ireturn
│ │ -      LineNumberTable:
│ │ -        line 431: 0
│ │ -        line 432: 2
│ │ -        line 434: 22
│ │ -        line 432: 25
│ │ -        line 436: 31
│ │ -        line 438: 50
│ │ -        line 440: 60
│ │ -        line 441: 63
│ │ -        line 436: 66
│ │ -        line 444: 72
│ │ -      LocalVariableTable:
│ │ -        Start  Length  Slot  Name   Signature
│ │ -            4      27     2     i   I
│ │ -           35      37     2     i   I
│ │ -            0      74     0  line   Ljava/lang/String;
│ │ -            2      72     1 level   I
│ │        StackMapTable: number_of_entries = 5
│ │          frame_type = 253 /* append */
│ │            offset_delta = 4
│ │            locals = [ int, int ]
│ │          frame_type = 250 /* chop */
│ │            offset_delta = 26
│ │          frame_type = 252 /* append */
│ │            offset_delta = 3
│ │            locals = [ int ]
│ │          frame_type = 30 /* same */
│ │          frame_type = 250 /* chop */
│ │            offset_delta = 5
│ │ +      LineNumberTable:
│ │ +        line 430: 0
│ │ +        line 431: 2
│ │ +        line 433: 22
│ │ +        line 431: 25
│ │ +        line 435: 31
│ │ +        line 437: 50
│ │ +        line 439: 60
│ │ +        line 440: 63
│ │ +        line 435: 66
│ │ +        line 443: 72
│ │ +      LocalVariableTable:
│ │ +        Start  Length  Slot  Name   Signature
│ │ +            4      27     2     i   I
│ │ +           35      37     2     i   I
│ │ +            0      74     0  line   Ljava/lang/String;
│ │ +            2      72     1 level   I
│ │  
│ │    private java.lang.String getPropertyFromExpression(java.lang.String);
│ │      descriptor: (Ljava/lang/String;)Ljava/lang/String;
│ │      flags: (0x0002) ACC_PRIVATE
│ │      Code:
│ │        stack=4, locals=2, args_size=2
│ │           0: aload_1
│ │ -         1: ifnull        47
│ │ +         1: ifnull        50
│ │           4: aload_1
│ │ -         5: ldc           #115                // String ${
│ │ -         7: invokevirtual #116                // Method java/lang/String.startsWith:(Ljava/lang/String;)Z
│ │ -        10: ifeq          47
│ │ -        13: aload_1
│ │ -        14: ldc           #117                // String }
│ │ -        16: invokevirtual #118                // Method java/lang/String.endsWith:(Ljava/lang/String;)Z
│ │ -        19: ifeq          47
│ │ -        22: aload_1
│ │ -        23: iconst_2
│ │ -        24: invokevirtual #119                // Method java/lang/String.substring:(I)Ljava/lang/String;
│ │ -        27: ldc           #115                // String ${
│ │ -        29: invokevirtual #40                 // Method java/lang/String.contains:(Ljava/lang/CharSequence;)Z
│ │ -        32: ifne          47
│ │ -        35: aload_1
│ │ -        36: iconst_2
│ │ -        37: aload_1
│ │ -        38: invokevirtual #50                 // Method java/lang/String.length:()I
│ │ -        41: iconst_1
│ │ -        42: isub
│ │ -        43: invokevirtual #120                // Method java/lang/String.substring:(II)Ljava/lang/String;
│ │ -        46: areturn
│ │ -        47: aconst_null
│ │ -        48: areturn
│ │ +         5: ldc_w         #418                // String ${
│ │ +         8: invokevirtual #421                // Method java/lang/String.startsWith:(Ljava/lang/String;)Z
│ │ +        11: ifeq          50
│ │ +        14: aload_1
│ │ +        15: ldc_w         #423                // String }
│ │ +        18: invokevirtual #426                // Method java/lang/String.endsWith:(Ljava/lang/String;)Z
│ │ +        21: ifeq          50
│ │ +        24: aload_1
│ │ +        25: iconst_2
│ │ +        26: invokevirtual #430                // Method java/lang/String.substring:(I)Ljava/lang/String;
│ │ +        29: ldc_w         #418                // String ${
│ │ +        32: invokevirtual #167                // Method java/lang/String.contains:(Ljava/lang/CharSequence;)Z
│ │ +        35: ifne          50
│ │ +        38: aload_1
│ │ +        39: iconst_2
│ │ +        40: aload_1
│ │ +        41: invokevirtual #194                // Method java/lang/String.length:()I
│ │ +        44: iconst_1
│ │ +        45: isub
│ │ +        46: invokevirtual #433                // Method java/lang/String.substring:(II)Ljava/lang/String;
│ │ +        49: areturn
│ │ +        50: aconst_null
│ │ +        51: areturn
│ │ +      StackMapTable: number_of_entries = 1
│ │ +        frame_type = 50 /* same */
│ │        LineNumberTable:
│ │ -        line 449: 0
│ │ -        line 450: 24
│ │ -        line 453: 35
│ │ -        line 456: 47
│ │ +        line 448: 0
│ │ +        line 449: 26
│ │ +        line 452: 38
│ │ +        line 455: 50
│ │        LocalVariableTable:
│ │          Start  Length  Slot  Name   Signature
│ │ -            0      49     0  this   Lio/fabric8/maven/docker/HelpMojo;
│ │ -            0      49     1 expression   Ljava/lang/String;
│ │ -      StackMapTable: number_of_entries = 1
│ │ -        frame_type = 47 /* same */
│ │ +            0      52     0  this   Lio/fabric8/maven/docker/HelpMojo;
│ │ +            0      52     1 expression   Ljava/lang/String;
│ │  }
│ │  SourceFile: "HelpMojo.java"
│ │  RuntimeInvisibleAnnotations:
│ │ -  0: #259(#174=s#260,#261=Z#262,#263=Z#264)
│ │ +  0: #6(#7=s#8,#9=Z#10,#11=Z#12)
│ │      org.apache.maven.plugins.annotations.Mojo(
│ │        name="help"
│ │        requiresProject=false
│ │        threadSafe=true
│ │      )

