1 / 3 central/io/opentelemetry/instrumentation/opentelemetry-instrumentation-api-incubator/2.4.0-alpha/opentelemetry-instrumentation-api-incubator-2.4.0-alpha-sources.jar repository/io/opentelemetry/instrumentation/opentelemetry-instrumentation-api-incubator/2.4.0-alpha/opentelemetry-instrumentation-api-incubator-2.4.0-alpha-sources.jar
--- central/io/opentelemetry/instrumentation/opentelemetry-instrumentation-api-incubator/2.4.0-alpha/opentelemetry-instrumentation-api-incubator-2.4.0-alpha-sources.jar
+++ repository/io/opentelemetry/instrumentation/opentelemetry-instrumentation-api-incubator/2.4.0-alpha/opentelemetry-instrumentation-api-incubator-2.4.0-alpha-sources.jar
├── zipinfo {}
│ @@ -1,8 +1,8 @@
│ -Zip file size: 58816 bytes, number of entries: 62
│ +Zip file size: 58806 bytes, number of entries: 62
│  drwxr-xr-x  2.0 unx        0 b- defN 80-Feb-01 00:00 META-INF/
│  -rw-r--r--  2.0 unx       25 b- defN 80-Feb-01 00:00 META-INF/MANIFEST.MF
│  drwxr-xr-x  2.0 unx        0 b- defN 80-Feb-01 00:00 io/
│  drwxr-xr-x  2.0 unx        0 b- defN 80-Feb-01 00:00 io/opentelemetry/
│  drwxr-xr-x  2.0 unx        0 b- defN 80-Feb-01 00:00 io/opentelemetry/instrumentation/
│  drwxr-xr-x  2.0 unx        0 b- defN 80-Feb-01 00:00 io/opentelemetry/instrumentation/api/
│  drwxr-xr-x  2.0 unx        0 b- defN 80-Feb-01 00:00 io/opentelemetry/instrumentation/api/incubator/
│ @@ -56,9 +56,9 @@
│  -rw-r--r--  2.0 unx     1384 b- defN 80-Feb-01 00:00 io/opentelemetry/instrumentation/api/incubator/semconv/rpc/RpcServerAttributesExtractor.java
│  -rw-r--r--  2.0 unx     3113 b- defN 80-Feb-01 00:00 io/opentelemetry/instrumentation/api/incubator/semconv/rpc/RpcServerMetrics.java
│  -rw-r--r--  2.0 unx     1148 b- defN 80-Feb-01 00:00 io/opentelemetry/instrumentation/api/incubator/semconv/rpc/RpcSpanNameExtractor.java
│  drwxr-xr-x  2.0 unx        0 b- defN 80-Feb-01 00:00 io/opentelemetry/instrumentation/api/incubator/semconv/util/
│  -rw-r--r--  2.0 unx      717 b- defN 80-Feb-01 00:00 io/opentelemetry/instrumentation/api/incubator/semconv/util/ClassAndMethod.java
│  -rw-r--r--  2.0 unx      649 b- defN 80-Feb-01 00:00 io/opentelemetry/instrumentation/api/incubator/semconv/util/ClassAndMethodAttributesGetter.java
│  -rw-r--r--  2.0 unx     1559 b- defN 80-Feb-01 00:00 io/opentelemetry/instrumentation/api/incubator/semconv/util/SpanNames.java
│ --rw-r--r--  2.0 unx    47447 b- defN 80-Feb-01 00:00 io/opentelemetry/instrumentation/api/incubator/semconv/db/AutoSqlSanitizer.java
│ -62 files, 152471 bytes uncompressed, 44596 bytes compressed:  70.8%
│ +-rw-r--r--  2.0 unx    47375 b- defN 80-Feb-01 00:00 io/opentelemetry/instrumentation/api/incubator/semconv/db/AutoSqlSanitizer.java
│ +62 files, 152399 bytes uncompressed, 44586 bytes compressed:  70.7%
├── io/opentelemetry/instrumentation/api/incubator/semconv/db/AutoSqlSanitizer.java
│ @@ -1,10 +1,10 @@
│  // DO NOT EDIT
│  // Generated by JFlex 1.9.1 http://jflex.de/
│ -// source: /home/runner/work/opentelemetry-java-instrumentation/opentelemetry-java-instrumentation/instrumentation-api-incubator/src/main/jflex/SqlSanitizer.jflex
│ +// source: /var/gradle/app/instrumentation-api-incubator/src/main/jflex/SqlSanitizer.jflex
│  
│  /*
│   * Copyright The OpenTelemetry Authors
│   * SPDX-License-Identifier: Apache-2.0
│   */
│  
│  package io.opentelemetry.instrumentation.api.incubator.semconv.db;

2 / 3 central/io/opentelemetry/javaagent/instrumentation/opentelemetry-javaagent-rmi/2.4.0-alpha/opentelemetry-javaagent-rmi-2.4.0-alpha.jar repository/io/opentelemetry/javaagent/instrumentation/opentelemetry-javaagent-rmi/2.4.0-alpha/opentelemetry-javaagent-rmi-2.4.0-alpha.jar
--- central/io/opentelemetry/javaagent/instrumentation/opentelemetry-javaagent-rmi/2.4.0-alpha/opentelemetry-javaagent-rmi-2.4.0-alpha.jar
+++ repository/io/opentelemetry/javaagent/instrumentation/opentelemetry-javaagent-rmi/2.4.0-alpha/opentelemetry-javaagent-rmi-2.4.0-alpha.jar
├── zipinfo {}
│ @@ -1,46 +1,46 @@
│ -Zip file size: 37874 bytes, number of entries: 44
│ +Zip file size: 37698 bytes, number of entries: 44
│  drwxr-xr-x  2.0 unx        0 b- defN 80-Feb-01 00:00 META-INF/
│  -rw-r--r--  2.0 unx      297 b- defN 80-Feb-01 00:00 META-INF/MANIFEST.MF
│  drwxr-xr-x  2.0 unx        0 b- defN 80-Feb-01 00:00 META-INF/services/
│  -rw-r--r--  2.0 unx      357 b- defN 80-Feb-01 00:00 META-INF/services/io.opentelemetry.javaagent.extension.instrumentation.InstrumentationModule
│  drwxr-xr-x  2.0 unx        0 b- defN 80-Feb-01 00:00 io/
│  drwxr-xr-x  2.0 unx        0 b- defN 80-Feb-01 00:00 io/opentelemetry/
│  drwxr-xr-x  2.0 unx        0 b- defN 80-Feb-01 00:00 io/opentelemetry/javaagent/
│  drwxr-xr-x  2.0 unx        0 b- defN 80-Feb-01 00:00 io/opentelemetry/javaagent/instrumentation/
│  drwxr-xr-x  2.0 unx        0 b- defN 80-Feb-01 00:00 io/opentelemetry/javaagent/instrumentation/rmi/
│  drwxr-xr-x  2.0 unx        0 b- defN 80-Feb-01 00:00 io/opentelemetry/javaagent/instrumentation/rmi/client/
│ --rw-r--r--  2.0 unx     2358 b- defN 80-Feb-01 00:00 io/opentelemetry/javaagent/instrumentation/rmi/client/RmiClientAttributesGetter.class
│ +-rw-r--r--  2.0 unx     2280 b- defN 80-Feb-01 00:00 io/opentelemetry/javaagent/instrumentation/rmi/client/RmiClientAttributesGetter.class
│  -rw-r--r--  2.0 unx     1879 b- defN 80-Feb-01 00:00 io/opentelemetry/javaagent/instrumentation/rmi/client/RmiClientInstrumentationModule.class
│  -rw-r--r--  2.0 unx     2734 b- defN 80-Feb-01 00:00 io/opentelemetry/javaagent/instrumentation/rmi/client/RmiClientSingletons.class
│  -rw-r--r--  2.0 unx     2887 b- defN 80-Feb-01 00:00 io/opentelemetry/javaagent/instrumentation/rmi/client/UnicastRefInstrumentation$InvokeAdvice.class
│  -rw-r--r--  2.0 unx     2332 b- defN 80-Feb-01 00:00 io/opentelemetry/javaagent/instrumentation/rmi/client/UnicastRefInstrumentation.class
│  drwxr-xr-x  2.0 unx        0 b- defN 80-Feb-01 00:00 io/opentelemetry/javaagent/instrumentation/rmi/context/
│ --rw-r--r--  2.0 unx     2871 b- defN 80-Feb-01 00:00 io/opentelemetry/javaagent/instrumentation/rmi/context/ContextPayload$ContextPayloadGetter.class
│ --rw-r--r--  2.0 unx     2413 b- defN 80-Feb-01 00:00 io/opentelemetry/javaagent/instrumentation/rmi/context/ContextPayload$ContextPayloadSetter.class
│ +-rw-r--r--  2.0 unx     2800 b- defN 80-Feb-01 00:00 io/opentelemetry/javaagent/instrumentation/rmi/context/ContextPayload$ContextPayloadGetter.class
│ +-rw-r--r--  2.0 unx     2349 b- defN 80-Feb-01 00:00 io/opentelemetry/javaagent/instrumentation/rmi/context/ContextPayload$ContextPayloadSetter.class
│  -rw-r--r--  2.0 unx     3892 b- defN 80-Feb-01 00:00 io/opentelemetry/javaagent/instrumentation/rmi/context/ContextPayload.class
│  -rw-r--r--  2.0 unx     5255 b- defN 80-Feb-01 00:00 io/opentelemetry/javaagent/instrumentation/rmi/context/ContextPropagator.class
│  -rw-r--r--  2.0 unx     7381 b- defN 80-Feb-01 00:00 io/opentelemetry/javaagent/instrumentation/rmi/context/RmiContextPropagationInstrumentationModule.class
│  drwxr-xr-x  2.0 unx        0 b- defN 80-Feb-01 00:00 io/opentelemetry/javaagent/instrumentation/rmi/context/client/
│  -rw-r--r--  2.0 unx     2871 b- defN 80-Feb-01 00:00 io/opentelemetry/javaagent/instrumentation/rmi/context/client/RmiClientContextInstrumentation$StreamRemoteCallConstructorAdvice.class
│  -rw-r--r--  2.0 unx     5077 b- defN 80-Feb-01 00:00 io/opentelemetry/javaagent/instrumentation/rmi/context/client/RmiClientContextInstrumentation.class
│  drwxr-xr-x  2.0 unx        0 b- defN 80-Feb-01 00:00 io/opentelemetry/javaagent/instrumentation/rmi/context/jpms/
│ --rw-r--r--  2.0 unx     1861 b- defN 80-Feb-01 00:00 io/opentelemetry/javaagent/instrumentation/rmi/context/jpms/ExposeRmiModuleInstrumentation$1.class
│ --rw-r--r--  2.0 unx     1606 b- defN 80-Feb-01 00:00 io/opentelemetry/javaagent/instrumentation/rmi/context/jpms/ExposeRmiModuleInstrumentation$2.class
│ +-rw-r--r--  2.0 unx     1820 b- defN 80-Feb-01 00:00 io/opentelemetry/javaagent/instrumentation/rmi/context/jpms/ExposeRmiModuleInstrumentation$1.class
│ +-rw-r--r--  2.0 unx     1565 b- defN 80-Feb-01 00:00 io/opentelemetry/javaagent/instrumentation/rmi/context/jpms/ExposeRmiModuleInstrumentation$2.class
│  -rw-r--r--  2.0 unx     5747 b- defN 80-Feb-01 00:00 io/opentelemetry/javaagent/instrumentation/rmi/context/jpms/ExposeRmiModuleInstrumentation.class
│  -rw-r--r--  2.0 unx     1652 b- defN 80-Feb-01 00:00 io/opentelemetry/javaagent/instrumentation/rmi/context/jpms/RmiJpmsInstrumentationModule.class
│  drwxr-xr-x  2.0 unx        0 b- defN 80-Feb-01 00:00 io/opentelemetry/javaagent/instrumentation/rmi/context/server/
│  -rw-r--r--  2.0 unx      574 b- defN 80-Feb-01 00:00 io/opentelemetry/javaagent/instrumentation/rmi/context/server/ContextDispatcher$NoopRemote.class
│  -rw-r--r--  2.0 unx     3208 b- defN 80-Feb-01 00:00 io/opentelemetry/javaagent/instrumentation/rmi/context/server/ContextDispatcher.class
│  -rw-r--r--  2.0 unx     1795 b- defN 80-Feb-01 00:00 io/opentelemetry/javaagent/instrumentation/rmi/context/server/RmiServerContextInstrumentation$ObjectTableAdvice.class
│  -rw-r--r--  2.0 unx     2327 b- defN 80-Feb-01 00:00 io/opentelemetry/javaagent/instrumentation/rmi/context/server/RmiServerContextInstrumentation.class
│  drwxr-xr-x  2.0 unx        0 b- defN 80-Feb-01 00:00 io/opentelemetry/javaagent/instrumentation/rmi/server/
│  -rw-r--r--  2.0 unx     4387 b- defN 80-Feb-01 00:00 io/opentelemetry/javaagent/instrumentation/rmi/server/RemoteServerInstrumentation$PublicMethodAdvice.class
│  -rw-r--r--  2.0 unx     2306 b- defN 80-Feb-01 00:00 io/opentelemetry/javaagent/instrumentation/rmi/server/RemoteServerInstrumentation.class
│ --rw-r--r--  2.0 unx     2581 b- defN 80-Feb-01 00:00 io/opentelemetry/javaagent/instrumentation/rmi/server/RmiServerAttributesGetter.class
│ +-rw-r--r--  2.0 unx     2503 b- defN 80-Feb-01 00:00 io/opentelemetry/javaagent/instrumentation/rmi/server/RmiServerAttributesGetter.class
│  -rw-r--r--  2.0 unx     1881 b- defN 80-Feb-01 00:00 io/opentelemetry/javaagent/instrumentation/rmi/server/RmiServerInstrumentationModule.class
│  -rw-r--r--  2.0 unx     2834 b- defN 80-Feb-01 00:00 io/opentelemetry/javaagent/instrumentation/rmi/server/RmiServerSingletons.class
│  drwxr-xr-x  2.0 unx        0 b- defN 80-Feb-01 00:00 META-INF/io/
│  drwxr-xr-x  2.0 unx        0 b- defN 80-Feb-01 00:00 META-INF/io/opentelemetry/
│  drwxr-xr-x  2.0 unx        0 b- defN 80-Feb-01 00:00 META-INF/io/opentelemetry/instrumentation/
│  -rw-r--r--  2.0 unx       19 b- defN 80-Feb-01 00:00 META-INF/io/opentelemetry/instrumentation/io.opentelemetry.rmi.properties
│ -44 files, 75382 bytes uncompressed, 28262 bytes compressed:  62.5%
│ +44 files, 75009 bytes uncompressed, 28086 bytes compressed:  62.6%
├── io/opentelemetry/javaagent/instrumentation/rmi/client/RmiClientAttributesGetter.class
│ ├── javap -verbose -constants -s -l -private {}
│ │ @@ -68,25 +68,24 @@
│ │    #59 = Utf8               values
│ │    #60 = Utf8               Code
│ │    #61 = Utf8               LineNumberTable
│ │    #62 = Utf8               (Ljava/lang/String;)Lio/opentelemetry/javaagent/instrumentation/rmi/client/RmiClientAttributesGetter;
│ │    #63 = Utf8               LocalVariableTable
│ │    #64 = Utf8               name
│ │    #65 = Utf8               Ljava/lang/String;
│ │ -  #66 = Utf8               MethodParameters
│ │ -  #67 = Utf8               this
│ │ -  #68 = Utf8               Signature
│ │ -  #69 = Utf8               ()V
│ │ -  #70 = Utf8               method
│ │ -  #71 = Utf8               Ljava/lang/reflect/Method;
│ │ -  #72 = Utf8               (Ljava/lang/Object;)Ljava/lang/String;
│ │ -  #73 = Utf8               <clinit>
│ │ -  #74 = Utf8               Ljava/lang/Enum<Lio/opentelemetry/javaagent/instrumentation/rmi/client/RmiClientAttributesGetter;>;Lio/opentelemetry/instrumentation/api/incubator/semconv/rpc/RpcAttributesGetter<Ljava/lang/reflect/Method;>;
│ │ -  #75 = Utf8               SourceFile
│ │ -  #76 = Utf8               RmiClientAttributesGetter.java
│ │ +  #66 = Utf8               this
│ │ +  #67 = Utf8               Signature
│ │ +  #68 = Utf8               ()V
│ │ +  #69 = Utf8               method
│ │ +  #70 = Utf8               Ljava/lang/reflect/Method;
│ │ +  #71 = Utf8               (Ljava/lang/Object;)Ljava/lang/String;
│ │ +  #72 = Utf8               <clinit>
│ │ +  #73 = Utf8               Ljava/lang/Enum<Lio/opentelemetry/javaagent/instrumentation/rmi/client/RmiClientAttributesGetter;>;Lio/opentelemetry/instrumentation/api/incubator/semconv/rpc/RpcAttributesGetter<Ljava/lang/reflect/Method;>;
│ │ +  #74 = Utf8               SourceFile
│ │ +  #75 = Utf8               RmiClientAttributesGetter.java
│ │  {
│ │    public static final io.opentelemetry.javaagent.instrumentation.rmi.client.RmiClientAttributesGetter INSTANCE;
│ │      descriptor: Lio/opentelemetry/javaagent/instrumentation/rmi/client/RmiClientAttributesGetter;
│ │      flags: (0x4019) ACC_PUBLIC, ACC_STATIC, ACC_FINAL, ACC_ENUM
│ │  
│ │    private static final io.opentelemetry.javaagent.instrumentation.rmi.client.RmiClientAttributesGetter[] $VALUES;
│ │      descriptor: [Lio/opentelemetry/javaagent/instrumentation/rmi/client/RmiClientAttributesGetter;
│ │ @@ -115,17 +114,14 @@
│ │           6: checkcast     #1                  // class io/opentelemetry/javaagent/instrumentation/rmi/client/RmiClientAttributesGetter
│ │           9: areturn
│ │        LineNumberTable:
│ │          line 11: 0
│ │        LocalVariableTable:
│ │          Start  Length  Slot  Name   Signature
│ │              0      10     0  name   Ljava/lang/String;
│ │ -    MethodParameters:
│ │ -      Name                           Flags
│ │ -      <no name>                      mandated
│ │  
│ │    private io.opentelemetry.javaagent.instrumentation.rmi.client.RmiClientAttributesGetter();
│ │      descriptor: (Ljava/lang/String;I)V
│ │      flags: (0x0002) ACC_PRIVATE
│ │      Code:
│ │        stack=3, locals=3, args_size=3
│ │           0: aload_0
│ │ @@ -134,19 +130,15 @@
│ │           3: invokespecial #22                 // Method java/lang/Enum."<init>":(Ljava/lang/String;I)V
│ │           6: return
│ │        LineNumberTable:
│ │          line 11: 0
│ │        LocalVariableTable:
│ │          Start  Length  Slot  Name   Signature
│ │              0       7     0  this   Lio/opentelemetry/javaagent/instrumentation/rmi/client/RmiClientAttributesGetter;
│ │ -    MethodParameters:
│ │ -      Name                           Flags
│ │ -      <no name>                      synthetic
│ │ -      <no name>                      synthetic
│ │ -    Signature: #69                          // ()V
│ │ +    Signature: #68                          // ()V
│ │  
│ │    public java.lang.String getSystem(java.lang.reflect.Method);
│ │      descriptor: (Ljava/lang/reflect/Method;)Ljava/lang/String;
│ │      flags: (0x0001) ACC_PUBLIC
│ │      Code:
...

3 / 3 central/io/opentelemetry/javaagent/opentelemetry-javaagent/2.4.0/opentelemetry-javaagent-2.4.0.jar repository/io/opentelemetry/javaagent/opentelemetry-javaagent/2.4.0/opentelemetry-javaagent-2.4.0.jar
--- central/io/opentelemetry/javaagent/opentelemetry-javaagent/2.4.0/opentelemetry-javaagent-2.4.0.jar
+++ repository/io/opentelemetry/javaagent/opentelemetry-javaagent/2.4.0/opentelemetry-javaagent-2.4.0.jar
├── zipinfo {}
│ @@ -1,8 +1,8 @@
│ -Zip file size: 21340604 bytes, number of entries: 14240
│ +Zip file size: 21340397 bytes, number of entries: 14240
│  drwxr-xr-x  2.0 unx        0 b- defN 80-Feb-01 00:00 META-INF/
│  -rw-r--r--  2.0 unx      511 b- defN 80-Feb-01 00:00 META-INF/MANIFEST.MF
│  drwxr-xr-x  2.0 unx        0 b- defN 80-Feb-01 00:00 META-INF/licenses/
│  -rw-r--r--  2.0 unx    27608 b- defN 80-Feb-01 00:00 META-INF/licenses/licenses.md
│  drwxr-xr-x  2.0 unx        0 b- defN 80-Feb-01 00:00 META-INF/licenses/byte-buddy-dep-1.14.15.jar/
│  drwxr-xr-x  2.0 unx        0 b- defN 80-Feb-01 00:00 META-INF/licenses/byte-buddy-dep-1.14.15.jar/META-INF/
│  -rw-r--r--  2.0 unx    10140 b- defN 80-Feb-01 00:00 META-INF/licenses/byte-buddy-dep-1.14.15.jar/META-INF/LICENSE
│ @@ -5189,42 +5189,42 @@
│  -rw-r--r--  2.0 unx     5685 b- defN 80-Feb-01 00:00 inst/io/opentelemetry/javaagent/instrumentation/restlet/v2_0/RestletSingletons.classdata
│  -rw-r--r--  2.0 unx     2483 b- defN 80-Feb-01 00:00 inst/io/opentelemetry/javaagent/instrumentation/restlet/v2_0/RouteInstrumentation$RouteBeforeHandleAdvice.classdata
│  -rw-r--r--  2.0 unx     2447 b- defN 80-Feb-01 00:00 inst/io/opentelemetry/javaagent/instrumentation/restlet/v2_0/RouteInstrumentation.classdata
│  -rw-r--r--  2.0 unx     5273 b- defN 80-Feb-01 00:00 inst/io/opentelemetry/javaagent/instrumentation/restlet/v2_0/ServerInstrumentation$ServerHandleAdvice.classdata
│  -rw-r--r--  2.0 unx     2256 b- defN 80-Feb-01 00:00 inst/io/opentelemetry/javaagent/instrumentation/restlet/v2_0/ServerInstrumentation.classdata
│  drwxr-xr-x  2.0 unx        0 b- defN 80-Feb-01 00:00 inst/io/opentelemetry/javaagent/instrumentation/rmi/
│  drwxr-xr-x  2.0 unx        0 b- defN 80-Feb-01 00:00 inst/io/opentelemetry/javaagent/instrumentation/rmi/client/
│ --rw-r--r--  2.0 unx     2392 b- defN 80-Feb-01 00:00 inst/io/opentelemetry/javaagent/instrumentation/rmi/client/RmiClientAttributesGetter.classdata
│ +-rw-r--r--  2.0 unx     2314 b- defN 80-Feb-01 00:00 inst/io/opentelemetry/javaagent/instrumentation/rmi/client/RmiClientAttributesGetter.classdata
│  -rw-r--r--  2.0 unx     1879 b- defN 80-Feb-01 00:00 inst/io/opentelemetry/javaagent/instrumentation/rmi/client/RmiClientInstrumentationModule.classdata
│  -rw-r--r--  2.0 unx     3176 b- defN 80-Feb-01 00:00 inst/io/opentelemetry/javaagent/instrumentation/rmi/client/RmiClientSingletons.classdata
│  -rw-r--r--  2.0 unx     3397 b- defN 80-Feb-01 00:00 inst/io/opentelemetry/javaagent/instrumentation/rmi/client/UnicastRefInstrumentation$InvokeAdvice.classdata
│  -rw-r--r--  2.0 unx     2332 b- defN 80-Feb-01 00:00 inst/io/opentelemetry/javaagent/instrumentation/rmi/client/UnicastRefInstrumentation.classdata
│  drwxr-xr-x  2.0 unx        0 b- defN 80-Feb-01 00:00 inst/io/opentelemetry/javaagent/instrumentation/rmi/context/
│ --rw-r--r--  2.0 unx     2939 b- defN 80-Feb-01 00:00 inst/io/opentelemetry/javaagent/instrumentation/rmi/context/ContextPayload$ContextPayloadGetter.classdata
│ --rw-r--r--  2.0 unx     2481 b- defN 80-Feb-01 00:00 inst/io/opentelemetry/javaagent/instrumentation/rmi/context/ContextPayload$ContextPayloadSetter.classdata
│ +-rw-r--r--  2.0 unx     2868 b- defN 80-Feb-01 00:00 inst/io/opentelemetry/javaagent/instrumentation/rmi/context/ContextPayload$ContextPayloadGetter.classdata
│ +-rw-r--r--  2.0 unx     2417 b- defN 80-Feb-01 00:00 inst/io/opentelemetry/javaagent/instrumentation/rmi/context/ContextPayload$ContextPayloadSetter.classdata
│  -rw-r--r--  2.0 unx     4440 b- defN 80-Feb-01 00:00 inst/io/opentelemetry/javaagent/instrumentation/rmi/context/ContextPayload.classdata
│  -rw-r--r--  2.0 unx     5540 b- defN 80-Feb-01 00:00 inst/io/opentelemetry/javaagent/instrumentation/rmi/context/ContextPropagator.classdata
│  -rw-r--r--  2.0 unx     7380 b- defN 80-Feb-01 00:00 inst/io/opentelemetry/javaagent/instrumentation/rmi/context/RmiContextPropagationInstrumentationModule.classdata
│  drwxr-xr-x  2.0 unx        0 b- defN 80-Feb-01 00:00 inst/io/opentelemetry/javaagent/instrumentation/rmi/context/client/
│  -rw-r--r--  2.0 unx     3296 b- defN 80-Feb-01 00:00 inst/io/opentelemetry/javaagent/instrumentation/rmi/context/client/RmiClientContextInstrumentation$StreamRemoteCallConstructorAdvice.classdata
│  -rw-r--r--  2.0 unx     5077 b- defN 80-Feb-01 00:00 inst/io/opentelemetry/javaagent/instrumentation/rmi/context/client/RmiClientContextInstrumentation.classdata
│  drwxr-xr-x  2.0 unx        0 b- defN 80-Feb-01 00:00 inst/io/opentelemetry/javaagent/instrumentation/rmi/context/jpms/
│ --rw-r--r--  2.0 unx     1861 b- defN 80-Feb-01 00:00 inst/io/opentelemetry/javaagent/instrumentation/rmi/context/jpms/ExposeRmiModuleInstrumentation$1.classdata
│ --rw-r--r--  2.0 unx     1606 b- defN 80-Feb-01 00:00 inst/io/opentelemetry/javaagent/instrumentation/rmi/context/jpms/ExposeRmiModuleInstrumentation$2.classdata
│ +-rw-r--r--  2.0 unx     1820 b- defN 80-Feb-01 00:00 inst/io/opentelemetry/javaagent/instrumentation/rmi/context/jpms/ExposeRmiModuleInstrumentation$1.classdata
│ +-rw-r--r--  2.0 unx     1565 b- defN 80-Feb-01 00:00 inst/io/opentelemetry/javaagent/instrumentation/rmi/context/jpms/ExposeRmiModuleInstrumentation$2.classdata
│  -rw-r--r--  2.0 unx     5819 b- defN 80-Feb-01 00:00 inst/io/opentelemetry/javaagent/instrumentation/rmi/context/jpms/ExposeRmiModuleInstrumentation.classdata
│  -rw-r--r--  2.0 unx     1652 b- defN 80-Feb-01 00:00 inst/io/opentelemetry/javaagent/instrumentation/rmi/context/jpms/RmiJpmsInstrumentationModule.classdata
│  drwxr-xr-x  2.0 unx        0 b- defN 80-Feb-01 00:00 inst/io/opentelemetry/javaagent/instrumentation/rmi/context/server/
│  -rw-r--r--  2.0 unx      574 b- defN 80-Feb-01 00:00 inst/io/opentelemetry/javaagent/instrumentation/rmi/context/server/ContextDispatcher$NoopRemote.classdata
│  -rw-r--r--  2.0 unx     3548 b- defN 80-Feb-01 00:00 inst/io/opentelemetry/javaagent/instrumentation/rmi/context/server/ContextDispatcher.classdata
│  -rw-r--r--  2.0 unx     1795 b- defN 80-Feb-01 00:00 inst/io/opentelemetry/javaagent/instrumentation/rmi/context/server/RmiServerContextInstrumentation$ObjectTableAdvice.classdata
│  -rw-r--r--  2.0 unx     2327 b- defN 80-Feb-01 00:00 inst/io/opentelemetry/javaagent/instrumentation/rmi/context/server/RmiServerContextInstrumentation.classdata
│  drwxr-xr-x  2.0 unx        0 b- defN 80-Feb-01 00:00 inst/io/opentelemetry/javaagent/instrumentation/rmi/server/
│  -rw-r--r--  2.0 unx     5067 b- defN 80-Feb-01 00:00 inst/io/opentelemetry/javaagent/instrumentation/rmi/server/RemoteServerInstrumentation$PublicMethodAdvice.classdata
│  -rw-r--r--  2.0 unx     2306 b- defN 80-Feb-01 00:00 inst/io/opentelemetry/javaagent/instrumentation/rmi/server/RemoteServerInstrumentation.classdata
│ --rw-r--r--  2.0 unx     2683 b- defN 80-Feb-01 00:00 inst/io/opentelemetry/javaagent/instrumentation/rmi/server/RmiServerAttributesGetter.classdata
│ +-rw-r--r--  2.0 unx     2605 b- defN 80-Feb-01 00:00 inst/io/opentelemetry/javaagent/instrumentation/rmi/server/RmiServerAttributesGetter.classdata
│  -rw-r--r--  2.0 unx     1881 b- defN 80-Feb-01 00:00 inst/io/opentelemetry/javaagent/instrumentation/rmi/server/RmiServerInstrumentationModule.classdata
│  -rw-r--r--  2.0 unx     3310 b- defN 80-Feb-01 00:00 inst/io/opentelemetry/javaagent/instrumentation/rmi/server/RmiServerSingletons.classdata
│  drwxr-xr-x  2.0 unx        0 b- defN 80-Feb-01 00:00 inst/io/opentelemetry/javaagent/instrumentation/rocketmqclient/
│  drwxr-xr-x  2.0 unx        0 b- defN 80-Feb-01 00:00 inst/io/opentelemetry/javaagent/instrumentation/rocketmqclient/v4_8/
│  -rw-r--r--  2.0 unx     2485 b- defN 80-Feb-01 00:00 inst/io/opentelemetry/javaagent/instrumentation/rocketmqclient/v4_8/RocketMqClientHooks.classdata
│  -rw-r--r--  2.0 unx     1706 b- defN 80-Feb-01 00:00 inst/io/opentelemetry/javaagent/instrumentation/rocketmqclient/v4_8/RocketMqConsumerInstrumentation$StartAdvice.classdata
│  -rw-r--r--  2.0 unx     2170 b- defN 80-Feb-01 00:00 inst/io/opentelemetry/javaagent/instrumentation/rocketmqclient/v4_8/RocketMqConsumerInstrumentation.classdata
│ @@ -14235,8 +14235,8 @@
│  -rw-r--r--  2.0 unx     2761 b- defN 80-Feb-01 00:00 inst/zipkin2/v1/V1BinaryAnnotation.classdata
│  -rw-r--r--  2.0 unx     4261 b- defN 80-Feb-01 00:00 inst/zipkin2/v1/V1Span$Builder.classdata
│  -rw-r--r--  2.0 unx     4876 b- defN 80-Feb-01 00:00 inst/zipkin2/v1/V1Span.classdata
│  -rw-r--r--  2.0 unx     9226 b- defN 80-Feb-01 00:00 inst/zipkin2/v1/V1SpanConverter.classdata
│  -rw-r--r--  2.0 unx      755 b- defN 80-Feb-01 00:00 inst/zipkin2/v1/V2SpanConverter$1.classdata
│  -rw-r--r--  2.0 unx     2836 b- defN 80-Feb-01 00:00 inst/zipkin2/v1/V2SpanConverter$V1SpanMetadata.classdata
│  -rw-r--r--  2.0 unx     3818 b- defN 80-Feb-01 00:00 inst/zipkin2/v1/V2SpanConverter.classdata
│ -14240 files, 52163240 bytes uncompressed, 17883740 bytes compressed:  65.7%
│ +14240 files, 52162867 bytes uncompressed, 17883533 bytes compressed:  65.7%
├── inst/io/opentelemetry/javaagent/instrumentation/rmi/client/RmiClientAttributesGetter.classdata
│┄ Command `'javap -verbose -constants -s -l -private {}'` failed with exit code 1. Standard output:
│┄     Error: class not found: /tmp/diffoscope_m1lsoapv_240/tmpb6_v2vkh_ZipContainer/RmiClientAttributesGetter.classdata
│ @@ -1,8 +1,8 @@
│ -00000000: cafe babe 0000 0034 004d 0100 4f69 6f2f  .......4.M..Oio/
│ +00000000: cafe babe 0000 0034 004c 0100 4f69 6f2f  .......4.L..Oio/
│  00000010: 6f70 656e 7465 6c65 6d65 7472 792f 6a61  opentelemetry/ja
│  00000020: 7661 6167 656e 742f 696e 7374 7275 6d65  vaagent/instrume
│  00000030: 6e74 6174 696f 6e2f 726d 692f 636c 6965  ntation/rmi/clie
│  00000040: 6e74 2f52 6d69 436c 6965 6e74 4174 7472  nt/RmiClientAttr
│  00000050: 6962 7574 6573 4765 7474 6572 0700 0101  ibutesGetter....
│  00000060: 00e0 4c6a 6176 612f 6c61 6e67 2f45 6e75  ..Ljava/lang/Enu
│  00000070: 6d3c 4c69 6f2f 6f70 656e 7465 6c65 6d65  m<Lio/openteleme
│ @@ -90,61 +90,56 @@
│  00000590: 0024 0a00 0200 3b0c 0023 0024 0a00 0200  .$....;..#.$....
│  000005a0: 3d01 0007 2476 616c 7565 730c 0009 000a  =...$values.....
│  000005b0: 0900 0200 4001 0008 3c63 6c69 6e69 743e  ....@...<clinit>
│  000005c0: 0800 090a 0002 0020 0c00 3f00 0e0a 0002  ....... ..?.....
│  000005d0: 0045 0100 0443 6f64 6501 000f 4c69 6e65  .E...Code...Line
│  000005e0: 4e75 6d62 6572 5461 626c 6501 0012 4c6f  NumberTable...Lo
│  000005f0: 6361 6c56 6172 6961 626c 6554 6162 6c65  calVariableTable
│ -00000600: 0100 104d 6574 686f 6450 6172 616d 6574  ...MethodParamet
│ -00000610: 6572 7301 0009 5369 676e 6174 7572 6501  ers...Signature.
│ -00000620: 000a 536f 7572 6365 4669 6c65 4030 0002  ..SourceFile@0..
│ -00000630: 0005 0001 0007 0002 4019 0009 000a 0000  ........@.......
│ -00000640: 101a 000b 000c 0000 000b 0009 000d 000e  ................
│ -00000650: 0001 0047 0000 0022 0001 0000 0000 000a  ...G..."........
│ -00000660: b200 10b6 0015 c000 11b0 0000 0001 0048  ...............H
│ -00000670: 0000 0006 0001 0000 000b 0009 0016 0017  ................
│ -00000680: 0002 0047 0000 0034 0002 0001 0000 000a  ...G...4........
│ -00000690: 1202 2ab8 001a c000 02b0 0000 0002 0048  ..*............H
│ -000006a0: 0000 0006 0001 0000 000b 0049 0000 000c  ...........I....
│ -000006b0: 0001 0000 000a 001b 001c 0000 004a 0000  .............J..
...
